Workbook

Sheet JANEIRO
B1: Fluxo de Caixa 2026 CTR | C1: Janeiro | D1: % ACUMULADO JAN/2026 | E1: % Acum no Ano Comparação | H1: Matriz | I1: Filia Porto | J1: Filia Palmas
A2: Disponíveis Nas Contas Movimento | B2: Disponíveis Nas Contas Movimento inicial | C2: =SUBTOTAL(109,C3:C25) -> 67410.42 | D2: =SUM(D3:D25) -> 1
B3: 1.0 - TESOURARIA MATRIZ PALMAS | C3: 148.53 | D3: =IF(C3=0,"0,00%",C3/$C$2) -> 0.0022033686 | G3: 1
B4: 1.1 - BANCO DO BRASIL C.C.60409-7 MATRIZ | C4: 15268.12 | D4: =IF(C4=0,"0,00%",C4/$C$2) -> 0.22649495 | G4: 2
D5: =IF(C5=0,"0,00%",C5/$C$2) -> 0,00% | G5: 3
B6: 1.2-BRADESCO 15232-3 MATRIZ | C6: 8.62 | D6: =IF(C6=0,"0,00%",C6/$C$2) -> 0.00012787341 | G6: 4
D7: =IF(C7=0,"0,00%",C7/$C$2) -> 0,00% | G7: 5
B8: 1.3 - BANCO STONE MATRIZ C.C 40256726-7 | D8: =IF(C8=0,"0,00%",C8/$C$2) -> 0,00% | G8: 6
B9: 1.4 - BANCO DA AMAZONIA 071730-7 MATRIZ | C9: 124.56 | D9: =IF(C9=0,"0,00%",C9/$C$2) -> 0.0018477856 | G9: 7
B10: 1.4.1.INVESTIMENTO CDBORE RCP TXFL | D10: =IF(C10=0,"0,00%",C10/$C$2) -> 0,00% | G10: 8
B11: 1.5 - ITAU C.C.98671-6 MATRIZ | C11: 40443.69 | D11: =IF(C11=0,"0,00%",C11/$C$2) -> 0.59996199 | G11: 9
B12: 1.5.03. ITAU C.C 83290-2 GARANTIDA | C12: 902.73 | D12: =IF(C12=0,"0,00%",C12/$C$2) -> 0.01339155 | G12: 10
B13: 1.9 - CONTA PERDA/ROUBO/BONIFICAÇÃO E DOAÇÃO | C13: 0 | D13: =IF(C13=0,"0,00%",C13/$C$2) -> 0,00% | G13: 11
D14: =IF(C14=0,"0,00%",C14/$C$2) -> 0,00% | G14: 12
B15: 2.1 - BANCO DO BRASIL C.C.60638-3 FILIAL PALMAS | C15: 1415.61 | D15: =IF(C15=0,"0,00%",C15/$C$2) -> 0.020999869 | G15: 13
D16: =IF(C16=0,"0,00%",C16/$C$2) -> 0,00% | E16: =#REF! -> #REF! | G16: 14
D17: =IF(C17=0,"0,00%",C17/$C$2) -> 0,00% | E17: =#REF! -> #REF! | G17: 15
B18: 2.4 - ITAU C.C.98669-0 FILIAL PALMAS | C18: 536.72 | D18: =IF(C18=0,"0,00%",C18/$C$2) -> 0.0079619738 | E18: =#REF! -> #REF! | G18: 16
B19: 2.9 - CONTA PERDA/ROUBO E BONIFICAÇÃO FILIAL | C19: 0 | D19: =IF(C19=0,"0,00%",C19/$C$2) -> 0,00% | E19: =#REF! -> #REF! | G19: 17
B20: 4.0 - TESOURARIA FILIAL PORTO | C20: 1409.97 | D20: =IF(C20=0,"0,00%",C20/$C$2) -> 0.020916203 | E20: =#REF! -> #REF! | G20: 18
B21: 4.1 - BANCO DO BRASIL C.C.61105-0 FILIAL PORTO | C21: 57.34 | D21: =IF(C21=0,"0,00%",C21/$C$2) -> 0.00085061034 | E21: =#REF! -> #REF! | G21: 19
D22: =IF(C22=0,"0,00%",C22/$C$2) -> 0,00% | E22: =#REF! -> #REF! | G22: 20
B23: 4.4 - MERCADO PAGO PIX FILIAL PORTO | C23: 5412.19 | D23: =IF(C23=0,"0,00%",C23/$C$2) -> 0.080287143 | E23: =#REF! -> #REF! | G23: 21
B24: 4.9 - CONTA PERDA/ROUBO E BONIFICAÇÃO FILIAL | C24: 0 | D24: =IF(C24=0,"0,00%",C24/$C$2) -> 0,00% | G24: 22
B25: 91.CARTÃO ENDERED 5099+4596+6933+8072 - ESCRITORIO | C25: 1682.34 | D25: =IF(C25=0,"0,00%",C25/$C$2) -> 0.024956676 | G25: 23
D26: =IF(C26=0,"0,00%",C26/$C$2) -> 0,00% | E26: =#REF! -> #REF! | G26: 24
B27: Total Receitas Operacionais / Vendas | C27: =SUBTOTAL(109,C29:C51) -> 749632.93 | D27: =IFERROR(C27/C332,"") -> 0.99826619 | E27: 0.88526119 | H27: =H28+I28 -> 284105.37
A28: 1.1. Receita com Vendas | B28: 1.1. Receita com Vendas | C28: =SUBTOTAL(109,C29:C47) -> 749632.93 | D28: =SUM(D29:D47) -> 0.99826619 | E28: 0.88251933 | H28: =SUM(H29:H36) -> 42578.96 | I28: =SUM(I29:I36) -> 241526.41 | J28: =SUM(J29:J36) -> 465527.56
B29: 1.1.01. Receita em Dinheiro | C29: =H29+I29+J29 -> 2199.78 | D29: =IF(C29=0,"0,00%",C29/$C$332) -> 0.0029293884 | E29: 0.079252981 | F29: =IF(Fluxo_de_Caixa_Janeiro34591171012151619[[#This Row],[% ACUMULADO DEZ/2026]]>=Fluxo_de_Caixa_Janeiro34591171012151619[[#This Row],[% Acum no Ano Comparação]],"Verd","Fals") -> Verd | I29: =3454.6-2223.58 -> 1231.02 | J29: 968.76
B30: 1.1.01. Receita em Cartão (Crédito e Débito) | C30: =H30+I30+J30 -> 328505.72 | D30: =IF(C30=0,"0,00%",C30/$C$332) -> 0.43746231 | E30: 0.092740536 | F30: =IF(Fluxo_de_Caixa_Janeiro34591171012151619[[#This Row],[% ACUMULADO DEZ/2026]]>=Fluxo_de_Caixa_Janeiro34591171012151619[[#This Row],[% Acum no Ano Comparação]],"Verd","Fals") -> Verd | G30: =C361 -> -150.01 | H30: 6947.26 | I30: 61647.12 | J30: 259911.34
B31: 1.1.01. Receita de Cheque A Vista | C31: =H31+I31+J31 -> 15000 | D31: =IF(C31=0,"0,00%",C31/$C$332) -> 0.0199751 | E31: 0.00028628486 | F31: =IF(Fluxo_de_Caixa_Janeiro34591171012151619[[#This Row],[% ACUMULADO DEZ/2026]]>=Fluxo_de_Caixa_Janeiro34591171012151619[[#This Row],[% Acum no Ano Comparação]],"Verd","Fals") -> Verd | I31: 15000
B32: 1.1.01. Receita de Cheque Pré | C32: =H32+I32+J32 -> 0 | D32: =IF(C32=0,"0,00%",C32/$C$332) -> 0,00% | E32: 0.0063111634 | F32: =IF(Fluxo_de_Caixa_Janeiro34591171012151619[[#This Row],[% ACUMULADO DEZ/2026]]>=Fluxo_de_Caixa_Janeiro34591171012151619[[#This Row],[% Acum no Ano Comparação]],"Verd","Fals") -> Verd
B33: 1.1.01. Recebimento de Carteira (Notinha) | C33: =H33+I33+J33 -> 0 | D33: =IF(C33=0,"0,00%",C33/$C$332) -> 0,00% | E33: 0.0001318638 | F33: =IF(Fluxo_de_Caixa_Janeiro34591171012151619[[#This Row],[% ACUMULADO DEZ/2026]]>=Fluxo_de_Caixa_Janeiro34591171012151619[[#This Row],[% Acum no Ano Comparação]],"Verd","Fals") -> Verd
B34: 1.1.01. Recebimento de Boletos | C34: =H34+I34+J34 -> 144411.43 | D34: =IF(C34=0,"0,00%",C34/$C$332) -> 0.19230885 | E34: 0.66745712 | F34: =IF(Fluxo_de_Caixa_Janeiro34591171012151619[[#This Row],[% ACUMULADO DEZ/2026]]>=Fluxo_de_Caixa_Janeiro34591171012151619[[#This Row],[% Acum no Ano Comparação]],"Verd","Fals") -> Verd | H34: 10372.54 | I34: 46325.81 | J34: 87713.08
B35: 1.1.01. Recebimento em Depósito e Dep. PIX | C35: =H35+I35+J35 -> 259516 | D35: =IF(C35=0,"0,00%",C35/$C$332) -> 0.34559054 | E35: 0.036171198 | F35: =IF(Fluxo_de_Caixa_Janeiro34591171012151619[[#This Row],[% ACUMULADO DEZ/2026]]>=Fluxo_de_Caixa_Janeiro34591171012151619[[#This Row],[% Acum no Ano Comparação]],"Verd","Fals") -> Verd | H35: 25259.16 | I35: 117322.46 | J35: 116934.38
B36: 1.1.02. Recebimento Cheque Devolvido | C36: =H36+I36+J36 -> 0 | D36: =IF(C36=0,"0,00%",C36/$C$332) -> 0,00% | E36: 0.00016817802 | F36: =IF(Fluxo_de_Caixa_Janeiro34591171012151619[[#This Row],[% ACUMULADO DEZ/2026]]>=Fluxo_de_Caixa_Janeiro34591171012151619[[#This Row],[% Acum no Ano Comparação]],"Verd","Fals") -> Verd
D37: =IF(C37=0,"0,00%",C37/$C$332) -> 0,00% | E37: =#REF! -> #REF! | F37: =IF(Fluxo_de_Caixa_Janeiro34591171012151619[[#This Row],[% ACUMULADO DEZ/2026]]>=Fluxo_de_Caixa_Janeiro34591171012151619[[#This Row],[% Acum no Ano Comparação]],"Verd","Fals") -> #REF!
D38: =IF(C38=0,"0,00%",C38/$C$332) -> 0,00% | E38: =#REF! -> #REF! | F38: =IF(Fluxo_de_Caixa_Janeiro34591171012151619[[#This Row],[% ACUMULADO DEZ/2026]]>=Fluxo_de_Caixa_Janeiro34591171012151619[[#This Row],[% Acum no Ano Comparação]],"Verd","Fals") -> #REF!
D39: =IF(C39=0,"0,00%",C39/$C$332) -> 0,00% | E39: =#REF! -> #REF! | F39: =IF(Fluxo_de_Caixa_Janeiro34591171012151619[[#This Row],[% ACUMULADO DEZ/2026]]>=Fluxo_de_Caixa_Janeiro34591171012151619[[#This Row],[% Acum no Ano Comparação]],"Verd","Fals") -> #REF!
D40: =IF(C40=0,"0,00%",C40/$C$332) -> 0,00% | E40: =#REF! -> #REF! | F40: =IF(Fluxo_de_Caixa_Janeiro34591171012151619[[#This Row],[% ACUMULADO DEZ/2026]]>=Fluxo_de_Caixa_Janeiro34591171012151619[[#This Row],[% Acum no Ano Comparação]],"Verd","Fals") -> #REF!
D41: =IF(C41=0,"0,00%",C41/$C$332) -> 0,00% | E41: =#REF! -> #REF! | F41: =IF(Fluxo_de_Caixa_Janeiro34591171012151619[[#This Row],[% ACUMULADO DEZ/2026]]>=Fluxo_de_Caixa_Janeiro34591171012151619[[#This Row],[% Acum no Ano Comparação]],"Verd","Fals") -> #REF!
D42: =IF(C42=0,"0,00%",C42/$C$332) -> 0,00% | E42: =#REF! -> #REF! | F42: =IF(Fluxo_de_Caixa_Janeiro34591171012151619[[#This Row],[% ACUMULADO DEZ/2026]]>=Fluxo_de_Caixa_Janeiro34591171012151619[[#This Row],[% Acum no Ano Comparação]],"Verd","Fals") -> #REF!
D43: =IF(C43=0,"0,00%",C43/$C$332) -> 0,00% | E43: =#REF! -> #REF! | F43: =IF(Fluxo_de_Caixa_Janeiro34591171012151619[[#This Row],[% ACUMULADO DEZ/2026]]>=Fluxo_de_Caixa_Janeiro34591171012151619[[#This Row],[% Acum no Ano Comparação]],"Verd","Fals") -> #REF!
D44: =IF(C44=0,"0,00%",C44/$C$332) -> 0,00% | E44: =#REF! -> #REF! | F44: =IF(Fluxo_de_Caixa_Janeiro34591171012151619[[#This Row],[% ACUMULADO DEZ/2026]]>=Fluxo_de_Caixa_Janeiro34591171012151619[[#This Row],[% Acum no Ano Comparação]],"Verd","Fals") -> #REF!
D45: =IF(C45=0,"0,00%",C45/$C$332) -> 0,00% | E45: =#REF! -> #REF! | F45: =IF(Fluxo_de_Caixa_Janeiro34591171012151619[[#This Row],[% ACUMULADO DEZ/2026]]>=Fluxo_de_Caixa_Janeiro34591171012151619[[#This Row],[% Acum no Ano Comparação]],"Verd","Fals") -> #REF!
C46: 0 | D46: =IF(C46=0,"0,00%",C46/$C$332) -> 0,00% | E46: =#REF! -> #REF! | F46: =IF(Fluxo_de_Caixa_Janeiro34591171012151619[[#This Row],[% ACUMULADO DEZ/2026]]>=Fluxo_de_Caixa_Janeiro34591171012151619[[#This Row],[% Acum no Ano Comparação]],"Verd","Fals") -> #REF!
D47: =IF(C47=0,"0,00%",C47/$C$332) -> 0,00% | E47: =#REF! -> #REF! | F47: =IF(Fluxo_de_Caixa_Janeiro34591171012151619[[#This Row],[% ACUMULADO DEZ/2026]]>=Fluxo_de_Caixa_Janeiro34591171012151619[[#This Row],[% Acum no Ano Comparação]],"Verd","Fals") -> #REF!
A48: 1.5. Receita de Garantias | B48: 1.5. Receita de Garantias | C48: =+SUBTOTAL(109,C49:C51) -> 0 | D48: =SUM(D49:D51) -> 0 | E48: 0.0027418655 | H48: =SUM(H49:H51) -> 0 | I48: =SUM(I49:I51) -> 0 | J48: =SUM(J49:J51) -> 0
B49: 1.2.01. RECEITA EM DINHEIRO | C49: =H49+I49 -> 0 | D49: =IF(C49=0,"0,00%",C49/$C$332) -> 0,00% | E49: 0.0024323151 | F49: =IF(Fluxo_de_Caixa_Janeiro34591171012151619[[#This Row],[% ACUMULADO DEZ/2026]]>=Fluxo_de_Caixa_Janeiro34591171012151619[[#This Row],[% Acum no Ano Comparação]],"Verd","Fals") -> Verd
B50: 1.2.02. RECEITA EM MERCADORIA | C50: =H50+I50 -> 0 | D50: =IF(C50=0,"0,00%",C50/$C$332) -> 0,00% | E50: 0.00030955038 | F50: =IF(Fluxo_de_Caixa_Janeiro34591171012151619[[#This Row],[% ACUMULADO DEZ/2026]]>=Fluxo_de_Caixa_Janeiro34591171012151619[[#This Row],[% Acum no Ano Comparação]],"Verd","Fals") -> Verd
C51: =H51+I51 -> 0 | D51: =IF(C51=0,"0,00%",C51/$C$332) -> 0,00% | E51: =#REF! -> #REF! | F51: =IF(Fluxo_de_Caixa_Janeiro34591171012151619[[#This Row],[% ACUMULADO DEZ/2026]]>=Fluxo_de_Caixa_Janeiro34591171012151619[[#This Row],[% Acum no Ano Comparação]],"Verd","Fals") -> #REF!
A52: 2.1. Despesa Com Custo de Aquisição | B52: 2.1. Despesa Com Custo de Aquisição | C52: =-SUBTOTAL(109,C53:C59) -> -460642.66 | D52: =-IFERROR(C52/$C$27,"0,00") -> 0.61449096 | E52: 0.7032551 | F52: =IF(Fluxo_de_Caixa_Janeiro34591171012151619[[#This Row],[% ACUMULADO DEZ/2026]]<=Fluxo_de_Caixa_Janeiro34591171012151619[[#This Row],[% Acum no Ano Comparação]],"Verd","Fals") -> Verd | H52: =-SUBTOTAL(109,H53:H59) -> -444192.1 | I52: =-SUBTOTAL(109,I53:I59) -> -16450.56 | J52: =-SUBTOTAL(109,J53:J59) -> 0
B53: 2.1.01.FORNECEDORES DE MERCADORIAS REVENDA | C53: =H53+I53+J53 -> 450059.19 | D53: =IFERROR(C53/$C$27,"0,00%") -> 0.60037276 | E53: 0.70044704 | F53: =IF(Fluxo_de_Caixa_Janeiro34591171012151619[[#This Row],[% ACUMULADO DEZ/2026]]<=Fluxo_de_Caixa_Janeiro34591171012151619[[#This Row],[% Acum no Ano Comparação]],"Verd","Fals") -> Fals | H53: 434081.63 | I53: 15977.56
B54: 2.1.02.ADIANT. FORNEC. MERCA. REVENDA | C54: =H54+I54+J54 -> 0 | D54: =IFERROR(C54/$C$27,"0,00%") -> 0 | E54: 0.0028080664 | F54: =IF(Fluxo_de_Caixa_Janeiro34591171012151619[[#This Row],[% ACUMULADO DEZ/2026]]<=Fluxo_de_Caixa_Janeiro34591171012151619[[#This Row],[% Acum no Ano Comparação]],"Verd","Fals") -> Fals
B55: 2.1.03.TRANSPORTADORA MERCA. REVENDA | C55: =H55+I55+J55 -> 10103.47 | D55: =IFERROR(C55/$C$27,"0,00%") -> 0.01347789 | E55: 0 | F55: =IF(Fluxo_de_Caixa_Janeiro34591171012151619[[#This Row],[% ACUMULADO DEZ/2026]]<=Fluxo_de_Caixa_Janeiro34591171012151619[[#This Row],[% Acum no Ano Comparação]],"Verd","Fals") -> Fals | H55: 9630.47 | I55: 473
B56: 2.1.04.OUTROS CUSTOS DE MERC.REVENDA | C56: =H56+I56+J56 -> 480 | D56: =IFERROR(C56/$C$27,"0,00%") -> 0.00064031339 | E56: =#REF! -> #REF! | F56: =IF(Fluxo_de_Caixa_Janeiro34591171012151619[[#This Row],[% ACUMULADO DEZ/2026]]<=Fluxo_de_Caixa_Janeiro34591171012151619[[#This Row],[% Acum no Ano Comparação]],"Verd","Fals") -> #REF! | H56: 480
B57: 2.1.05.TRANSFE DE MERCAD REVENDA MATRIZ | C57: =H57+I57+J57 -> 0 | D57: =IFERROR(C57/$C$27,"0,00%") -> 0 | E57: =#REF! -> #REF! | F57: =IF(Fluxo_de_Caixa_Janeiro34591171012151619[[#This Row],[% ACUMULADO DEZ/2026]]<=Fluxo_de_Caixa_Janeiro34591171012151619[[#This Row],[% Acum no Ano Comparação]],"Verd","Fals") -> #REF!
D58: =IFERROR(C58/$C$27,"0,00%") -> 0 | E58: =#REF! -> #REF! | F58: =IF(Fluxo_de_Caixa_Janeiro34591171012151619[[#This Row],[% ACUMULADO DEZ/2026]]<=Fluxo_de_Caixa_Janeiro34591171012151619[[#This Row],[% Acum no Ano Comparação]],"Verd","Fals") -> #REF!
D59: =IFERROR(C59/$C$27,"0,00%") -> 0 | E59: =#REF! -> #REF! | F59: =IF(Fluxo_de_Caixa_Janeiro34591171012151619[[#This Row],[% ACUMULADO DEZ/2026]]<=Fluxo_de_Caixa_Janeiro34591171012151619[[#This Row],[% Acum no Ano Comparação]],"Verd","Fals") -> #REF!
A60: 2.2. Inadimplência e Perdas | B60: 2.2. Inadimplência e Perdas | C60: =-SUBTOTAL(109,C61:C69) -> 0 | D60: =-IFERROR(C60/$C$27,"0,00") -> 0 | E60: 0.0013173948 | F60: =IF(Fluxo_de_Caixa_Janeiro34591171012151619[[#This Row],[% ACUMULADO DEZ/2026]]<=Fluxo_de_Caixa_Janeiro34591171012151619[[#This Row],[% Acum no Ano Comparação]],"Verd","Fals") -> Verd | H60: =-SUBTOTAL(109,H61:H69) -> 0 | I60: =-SUBTOTAL(109,I61:I69) -> 0 | J60: =-SUBTOTAL(109,J61:J69) -> 0
B61: 2.2.01.CONTAS PERDIDAS/NÃO PAGAS | C61: =H61+I61+J61 -> 0 | D61: =IFERROR(C61/$C$27,"0,00%") -> 0 | E61: 0 | F61: =IF(Fluxo_de_Caixa_Janeiro34591171012151619[[#This Row],[% ACUMULADO DEZ/2026]]<=Fluxo_de_Caixa_Janeiro34591171012151619[[#This Row],[% Acum no Ano Comparação]],"Verd","Fals") -> Fals
B62: 2.2.02.BOLETOS DESCONTADOS DEVOLVIDOS | C62: =H62+I62+J62 -> 0 | D62: =IFERROR(C62/$C$27,"0,00%") -> 0 | E62: 0 | F62: =IF(Fluxo_de_Caixa_Janeiro34591171012151619[[#This Row],[% ACUMULADO DEZ/2026]]<=Fluxo_de_Caixa_Janeiro34591171012151619[[#This Row],[% Acum no Ano Comparação]],"Verd","Fals") -> Fals
B63: 2.2.03.CHEQUES DEVOLVIDOS | C63: =H63+I63+J63 -> 0 | D63: =IFERROR(C63/$C$27,"0,00%") -> 0 | E63: 0 | F63: =IF(Fluxo_de_Caixa_Janeiro34591171012151619[[#This Row],[% ACUMULADO DEZ/2026]]<=Fluxo_de_Caixa_Janeiro34591171012151619[[#This Row],[% Acum no Ano Comparação]],"Verd","Fals") -> Fals
B64: 2.2.04.BOLETOS DESCONTADOS DEVOLVIDOS | C64: =H64+I64+J64 -> 0 | D64: =IFERROR(C64/$C$27,"0,00%") -> 0 | E64: 0.0012728671 | F64: =IF(Fluxo_de_Caixa_Janeiro34591171012151619[[#This Row],[% ACUMULADO DEZ/2026]]<=Fluxo_de_Caixa_Janeiro34591171012151619[[#This Row],[% Acum no Ano Comparação]],"Verd","Fals") -> Fals
B65: 2.2.05.PERDA, ROUBO E DETERIORAÇÃO | C65: =H65+I65+J65 -> 0 | D65: =IFERROR(C65/$C$27,"0,00%") -> 0 | E65: 4.4527688e-05 | F65: =IF(Fluxo_de_Caixa_Janeiro34591171012151619[[#This Row],[% ACUMULADO DEZ/2026]]<=Fluxo_de_Caixa_Janeiro34591171012151619[[#This Row],[% Acum no Ano Comparação]],"Verd","Fals") -> Fals
C66: =H66+I66+J66 -> 0 | D66: =IFERROR(C66/$C$27,"0,00%") -> 0 | E66: =#REF! -> #REF! | F66: =IF(Fluxo_de_Caixa_Janeiro34591171012151619[[#This Row],[% ACUMULADO DEZ/2026]]<=Fluxo_de_Caixa_Janeiro34591171012151619[[#This Row],[% Acum no Ano Comparação]],"Verd","Fals") -> #REF!
C67: =H67+I67+J67 -> 0 | D67: =IFERROR(C67/$C$27,"0,00%") -> 0 | E67: =#REF! -> #REF! | F67: =IF(Fluxo_de_Caixa_Janeiro34591171012151619[[#This Row],[% ACUMULADO DEZ/2026]]<=Fluxo_de_Caixa_Janeiro34591171012151619[[#This Row],[% Acum no Ano Comparação]],"Verd","Fals") -> #REF!
C68: =H68+I68+J68 -> 0 | D68: =IFERROR(C68/$C$27,"0,00%") -> 0 | E68: =#REF! -> #REF! | F68: =IF(Fluxo_de_Caixa_Janeiro34591171012151619[[#This Row],[% ACUMULADO DEZ/2026]]<=Fluxo_de_Caixa_Janeiro34591171012151619[[#This Row],[% Acum no Ano Comparação]],"Verd","Fals") -> #REF!
C69: =H69+I69+J69 -> 0 | D69: =IFERROR(C69/$C$27,"0,00%") -> 0 | E69: =#REF! -> #REF! | F69: =IF(Fluxo_de_Caixa_Janeiro34591171012151619[[#This Row],[% ACUMULADO DEZ/2026]]<=Fluxo_de_Caixa_Janeiro34591171012151619[[#This Row],[% Acum no Ano Comparação]],"Verd","Fals") -> #REF!
A70: 2.3. Impostos | B70: 2.3. Impostos | C70: =-SUBTOTAL(109,C71:C84) -> -57986.56 | D70: =-IFERROR(C70/$C$27,"0,00") -> 0.077353272 | E70: 0.12754151 | F70: =IF(Fluxo_de_Caixa_Janeiro34591171012151619[[#This Row],[% ACUMULADO DEZ/2026]]<=Fluxo_de_Caixa_Janeiro34591171012151619[[#This Row],[% Acum no Ano Comparação]],"Verd","Fals") -> Verd | H70: =-SUBTOTAL(109,H71:H84) -> -40063.59 | I70: =-SUBTOTAL(109,I71:I84) -> -9132.86 | J70: =-SUBTOTAL(109,J71:J84) -> -8790.11
D71: =IFERROR(C71/$C$27,"0,00%") -> 0 | E71: 0.0010503863 | F71: =IF(Fluxo_de_Caixa_Janeiro34591171012151619[[#This Row],[% ACUMULADO DEZ/2026]]<=Fluxo_de_Caixa_Janeiro34591171012151619[[#This Row],[% Acum no Ano Comparação]],"Verd","Fals") -> Fals
B72: 2.3.02.IRPJ (SE ESTIVER NO CMV) | C72: =H72+I72+J72 -> 0 | D72: =IFERROR(C72/$C$27,"0,00%") -> 0 | E72: 0.00062053498 | F72: =IF(Fluxo_de_Caixa_Janeiro34591171012151619[[#This Row],[% ACUMULADO DEZ/2026]]<=Fluxo_de_Caixa_Janeiro34591171012151619[[#This Row],[% Acum no Ano Comparação]],"Verd","Fals") -> Fals
B73: 2.3.03.CSSL (SE ESTIVER NO CMV) | C73: =H73+I73+J73 -> 0 | D73: =IFERROR(C73/$C$27,"0,00%") -> 0 | E73: 0.003344374 | F73: =IF(Fluxo_de_Caixa_Janeiro34591171012151619[[#This Row],[% ACUMULADO DEZ/2026]]<=Fluxo_de_Caixa_Janeiro34591171012151619[[#This Row],[% Acum no Ano Comparação]],"Verd","Fals") -> Fals
B74: 2.3.04.COFINS (SE ESTIVER NO CMV) | C74: =H74+I74+J74 -> 12167.71 | D74: =IFERROR(C74/$C$27,"0,00%") -> 0.016231557 | E74: 0.00072605477 | F74: =IF(Fluxo_de_Caixa_Janeiro34591171012151619[[#This Row],[% ACUMULADO DEZ/2026]]<=Fluxo_de_Caixa_Janeiro34591171012151619[[#This Row],[% Acum no Ano Comparação]],"Verd","Fals") -> Fals | H74: 12167.71
B75: 2.3.05.PIS (SE ESTIVER NO CMV) | C75: =H75+I75+J75 -> 2636.34 | D75: =IFERROR(C75/$C$27,"0,00%") -> 0.0035168412 | E75: 0.051721948 | F75: =IF(Fluxo_de_Caixa_Janeiro34591171012151619[[#This Row],[% ACUMULADO DEZ/2026]]<=Fluxo_de_Caixa_Janeiro34591171012151619[[#This Row],[% Acum no Ano Comparação]],"Verd","Fals") -> Fals | H75: 2636.34
B76: 2.3.06.ICMS – Normal (SE ESTIVER NO CMV) | C76: =H76+I76+J76 -> 20443.12 | D76: =IFERROR(C76/$C$27,"0,00%") -> 0.02727084 | E76: 0.067027605 | F76: =IF(Fluxo_de_Caixa_Janeiro34591171012151619[[#This Row],[% ACUMULADO DEZ/2026]]<=Fluxo_de_Caixa_Janeiro34591171012151619[[#This Row],[% Acum no Ano Comparação]],"Verd","Fals") -> Fals | H76: 3181.23 | I76: 9132.86 | J76: 8129.03
B77: 2.3.07. SUBSTITUIÇÃO TRIBUTARIA SAÍDA (TARE) | C77: =H77+I77+J77 -> 10059.1 | D77: =IFERROR(C77/$C$27,"0,00%") -> 0.013418701 | E77: 0.0030506108 | F77: =IF(Fluxo_de_Caixa_Janeiro34591171012151619[[#This Row],[% ACUMULADO DEZ/2026]]<=Fluxo_de_Caixa_Janeiro34591171012151619[[#This Row],[% Acum no Ano Comparação]],"Verd","Fals") -> Fals | H77: 10059.1
B78: 2.3.08.SUBSTITUIÇÃO TRIBUTÁRIA NA ENTRADA | C78: =H78+I78+J78 -> 0 | D78: =IFERROR(C78/$C$27,"0,00%") -> 0 | E78: =#REF! -> #REF! | F78: =IF(Fluxo_de_Caixa_Janeiro34591171012151619[[#This Row],[% ACUMULADO DEZ/2026]]<=Fluxo_de_Caixa_Janeiro34591171012151619[[#This Row],[% Acum no Ano Comparação]],"Verd","Fals") -> #REF!
B79: 2.3.09.FUNDO DESENVOLVIMENTO ECONOMICO (TARE) | C79: =H79+I79+J79 -> 117.55 | D79: =IFERROR(C79/$C$27,"0,00%") -> 0.00015681008 | E79: =#REF! -> #REF! | F79: =IF(Fluxo_de_Caixa_Janeiro34591171012151619[[#This Row],[% ACUMULADO DEZ/2026]]<=Fluxo_de_Caixa_Janeiro34591171012151619[[#This Row],[% Acum no Ano Comparação]],"Verd","Fals") -> #REF! | H79: 117.55
C80: =H80+I80+J80 -> 0 | D80: =IFERROR(C80/$C$27,"0,00%") -> 0 | E80: =#REF! -> #REF! | F80: =IF(Fluxo_de_Caixa_Janeiro34591171012151619[[#This Row],[% ACUMULADO DEZ/2026]]<=Fluxo_de_Caixa_Janeiro34591171012151619[[#This Row],[% Acum no Ano Comparação]],"Verd","Fals") -> #REF!
C81: =H81+I81+J81 -> 0 | D81: =IFERROR(C81/$C$27,"0,00%") -> 0 | E81: =#REF! -> #REF! | F81: =IF(Fluxo_de_Caixa_Janeiro34591171012151619[[#This Row],[% ACUMULADO DEZ/2026]]<=Fluxo_de_Caixa_Janeiro34591171012151619[[#This Row],[% Acum no Ano Comparação]],"Verd","Fals") -> #REF!
B82: 2.3.11. Impostos Parcelado | C82: =H82+I82+J82 -> 12562.74 | D82: =IFERROR(C82/$C$27,"0,00%") -> 0.016758522 | E82: =#REF! -> #REF! | F82: =IF(Fluxo_de_Caixa_Janeiro34591171012151619[[#This Row],[% ACUMULADO DEZ/2026]]<=Fluxo_de_Caixa_Janeiro34591171012151619[[#This Row],[% Acum no Ano Comparação]],"Verd","Fals") -> #REF! | H82: 11901.66 | I82: 0 | J82: 661.08
D83: =IFERROR(C83/$C$27,"0,00%") -> 0 | E83: =#REF! -> #REF! | F83: =IF(Fluxo_de_Caixa_Janeiro34591171012151619[[#This Row],[% ACUMULADO DEZ/2026]]<=Fluxo_de_Caixa_Janeiro34591171012151619[[#This Row],[% Acum no Ano Comparação]],"Verd","Fals") -> #REF!
D84: =IFERROR(C84/$C$27,"0,00%") -> 0 | E84: =#REF! -> #REF! | F84: =IF(Fluxo_de_Caixa_Janeiro34591171012151619[[#This Row],[% ACUMULADO DEZ/2026]]<=Fluxo_de_Caixa_Janeiro34591171012151619[[#This Row],[% Acum no Ano Comparação]],"Verd","Fals") -> #REF!
B85: Total dos Custos | C85: =-SUBTOTAL(109,C52:C84) -> -518629.22 | D85: =IFERROR(C85/C27,"0,00%") -> -0.69184423 | E85: =#REF! -> #REF! | F85: =IF(Fluxo_de_Caixa_Janeiro34591171012151619[[#This Row],[% ACUMULADO DEZ/2026]]<=Fluxo_de_Caixa_Janeiro34591171012151619[[#This Row],[% Acum no Ano Comparação]],"Verd","Fals") -> #REF! | H85: =-SUBTOTAL(109,H52:H84) -> -484255.69 | I85: =-SUBTOTAL(109,I52:I84) -> -25583.42 | J85: =-SUBTOTAL(109,J52:J84) -> -8790.11
B86: Receita Operacional Bruta | C86: =SUM(C27,C85) -> 231003.71 | D86: =IFERROR(C86/C27,"0,00%") -> 0.30815577 | E86: =#REF! -> #REF! | F86: =IF(Fluxo_de_Caixa_Janeiro34591171012151619[[#This Row],[% ACUMULADO DEZ/2026]]>=Fluxo_de_Caixa_Janeiro34591171012151619[[#This Row],[% Acum no Ano Comparação]],"Verd","Fals") -> #REF!
B87: 300. Despesas Operac. Fixas e Variáveis
A88: 3.1. DESPESA COM VENDAS | B88: 3.1. DESPESA COM VENDAS | C88: =-SUBTOTAL(109,C89:C99) -> -60045.89 | D88: =-IFERROR(C88/$C$27,"0,00") -> 0.08010039 | E88: 0.030857534 | F88: =IF(Fluxo_de_Caixa_Janeiro34591171012151619[[#This Row],[% ACUMULADO DEZ/2026]]<=Fluxo_de_Caixa_Janeiro34591171012151619[[#This Row],[% Acum no Ano Comparação]],"Verd","Fals") -> Verd | H88: =-SUBTOTAL(109,H89:H99) -> -55684.22 | I88: =-SUBTOTAL(109,I89:I99) -> -822.24 | J88: =-SUBTOTAL(109,J89:J99) -> -3539.43
B89: 3.1.01. Marketing e Propaganda | C89: =H89+I89+J89 -> 2535 | D89: =IFERROR(C89/$C$27,"0,00%") -> 0.0033816551 | E89: 0.0010458541 | F89: =IF(Fluxo_de_Caixa_Janeiro34591171012151619[[#This Row],[% ACUMULADO DEZ/2026]]<=Fluxo_de_Caixa_Janeiro34591171012151619[[#This Row],[% Acum no Ano Comparação]],"Verd","Fals") -> Fals | H89: 2535
B90: 3.1.02. Promoções e Eventos(Brindes/Café da Manhã p clientes/etc) | C90: =H90+I90+J90 -> 0 | D90: =IFERROR(C90/$C$27,"0,00%") -> 0 | E90: 0.0011119768 | F90: =IF(Fluxo_de_Caixa_Janeiro34591171012151619[[#This Row],[% ACUMULADO DEZ/2026]]<=Fluxo_de_Caixa_Janeiro34591171012151619[[#This Row],[% Acum no Ano Comparação]],"Verd","Fals") -> Fals
B91: 3.1.03. Sacolas e Embalagens | C91: =H91+I91+J91 -> 0 | D91: =IFERROR(C91/$C$27,"0,00%") -> 0 | E91: 0.00064528103 | F91: =IF(Fluxo_de_Caixa_Janeiro34591171012151619[[#This Row],[% ACUMULADO DEZ/2026]]<=Fluxo_de_Caixa_Janeiro34591171012151619[[#This Row],[% Acum no Ano Comparação]],"Verd","Fals") -> Fals
B92: 3.1.04.DIARIAS E DESPESAS COM VENDEDOR (passagem ônibus, hotel. Etc) | C92: =H92+I92+J92 -> 0 | D92: =IFERROR(C92/$C$27,"0,00%") -> 0 | E92: 8.9915448e-05 | F92: =IF(Fluxo_de_Caixa_Janeiro34591171012151619[[#This Row],[% ACUMULADO DEZ/2026]]<=Fluxo_de_Caixa_Janeiro34591171012151619[[#This Row],[% Acum no Ano Comparação]],"Verd","Fals") -> Fals
B93: 3.1.05. Comissão Representente Comercial | C93: =H93+I93+J93 -> 34232.57 | D93: =IFERROR(C93/$C$27,"0,00%") -> 0.045665777 | E93: 0.012983049 | F93: =IF(Fluxo_de_Caixa_Janeiro34591171012151619[[#This Row],[% ACUMULADO DEZ/2026]]<=Fluxo_de_Caixa_Janeiro34591171012151619[[#This Row],[% Acum no Ano Comparação]],"Verd","Fals") -> Fals | H93: 34232.57
B94: 3.1.06. Frete com entrega de vendas | C94: =H94+I94+J94 -> 5767.8 | D94: =IFERROR(C94/$C$27,"0,00%") -> 0.0076941657 | E94: 0.013626993 | F94: =IF(Fluxo_de_Caixa_Janeiro34591171012151619[[#This Row],[% ACUMULADO DEZ/2026]]<=Fluxo_de_Caixa_Janeiro34591171012151619[[#This Row],[% Acum no Ano Comparação]],"Verd","Fals") -> Fals | H94: 2987.86 | J94: 2779.94
B95: 3.1.07. TAXAS C/ CART CRÉD/DÉBIT | C95: =H95+I95+J95 -> 17461.46 | D95: =IFERROR(C95/$C$27,"0,00%") -> 0.023293347 | E95: 0.0013544651 | F95: =IF(Fluxo_de_Caixa_Janeiro34591171012151619[[#This Row],[% ACUMULADO DEZ/2026]]<=Fluxo_de_Caixa_Janeiro34591171012151619[[#This Row],[% Acum no Ano Comparação]],"Verd","Fals") -> Fals | H95: 15879.73 | I95: 822.24 | J95: 759.49
B96: 3.1.08. Serviço Motoboy Entrega Vendas | C96: =H96+I96+J96 -> 0 | D96: =IFERROR(C96/$C$27,"0,00%") -> 0 | E96: 0.0013544651 | F96: =IF(Fluxo_de_Caixa_Janeiro34591171012151619[[#This Row],[% ACUMULADO DEZ/2026]]<=Fluxo_de_Caixa_Janeiro34591171012151619[[#This Row],[% Acum no Ano Comparação]],"Verd","Fals") -> Fals
B97: 3.1.09. PGTO DISTRATO REPRES COMERCIAL | C97: =H97+I97+J97 -> 0 | D97: =IFERROR(C97/$C$27,"0,00%") -> 0 | E97: 0.0013544651 | F97: =IF(Fluxo_de_Caixa_Janeiro34591171012151619[[#This Row],[% ACUMULADO DEZ/2026]]<=Fluxo_de_Caixa_Janeiro34591171012151619[[#This Row],[% Acum no Ano Comparação]],"Verd","Fals") -> Fals
B98: 3.1.10. TARIFA PIX RECEBIDO | C98: =H98+I98+J98 -> 49.06 | D98: =IFERROR(C98/$C$27,"0,00%") -> 6.5445364e-05 | E98: 0.0013544651 | F98: =IF(Fluxo_de_Caixa_Janeiro34591171012151619[[#This Row],[% ACUMULADO DEZ/2026]]<=Fluxo_de_Caixa_Janeiro34591171012151619[[#This Row],[% Acum no Ano Comparação]],"Verd","Fals") -> Fals | H98: 49.06
D99: =IFERROR(C99/$C$27,"0,00%") -> 0 | E99: =#REF! -> #REF! | F99: =IF(Fluxo_de_Caixa_Janeiro34591171012151619[[#This Row],[% ACUMULADO DEZ/2026]]<=Fluxo_de_Caixa_Janeiro34591171012151619[[#This Row],[% Acum no Ano Comparação]],"Verd","Fals") -> #REF!
A100: 3.2. FUNCIONÁRIO | B100: 3.2. DESPESA COM FUNCIONÁRIO | C100: =-SUBTOTAL(109,C101:C130) -> -64579.58 | D100: =-IFERROR(C100/$C$27,"0,00") -> 0.08614827 | E100: 0.067282262 | F100: =IF(Fluxo_de_Caixa_Janeiro34591171012151619[[#This Row],[% ACUMULADO DEZ/2026]]<=Fluxo_de_Caixa_Janeiro34591171012151619[[#This Row],[% Acum no Ano Comparação]],"Verd","Fals") -> Verd | H100: =-SUBTOTAL(109,H101:H130) -> -64226.58 | I100: =-SUBTOTAL(109,I101:I130) -> -353 | J100: =-SUBTOTAL(109,J101:J130) -> 0
...

Sheet FEVEREIRO
B1: Fluxo de Caixa 2026 CTR | C1: Fevereiro | D1: % ACUMULADO FEV/2026 | E1: % Acum no Ano Comparação | H1: Matriz | I1: Filia Porto | J1: Filia Palmas
A2: Disponíveis Nas Contas Movimento | B2: =Fluxo_de_Caixa_Janeiro[[#This Row],[Fluxo de Caixa 2026 CTR]] -> Disponíveis Nas Contas Movimento inicial | C2: =SUBTOTAL(109,C3:C26) -> 31847.63 | D2: =SUM(D3:D26) -> 0.99476131
B3: =Fluxo_de_Caixa_Janeiro[[#This Row],[Fluxo de Caixa 2026 CTR]] -> 1.0 - TESOURARIA MATRIZ PALMAS | C3: =JANEIRO!C337 -> 40.53 | D3: =IF(C3=0,"0,00%",C3/$C$2) -> 0.0012726222
B4: =Fluxo_de_Caixa_Janeiro[[#This Row],[Fluxo de Caixa 2026 CTR]] -> 1.1 - BANCO DO BRASIL C.C.60409-7 MATRIZ | C4: =JANEIRO!C338 -> 108.85 | D4: =IF(C4=0,"0,00%",C4/$C$2) -> 0.0034178367
B5: =Fluxo_de_Caixa_Janeiro[[#This Row],[Fluxo de Caixa 2026 CTR]] -> 0 | C5: =JANEIRO!C339 -> 0 | D5: =IF(C5=0,"0,00%",C5/$C$2) -> 0,00%
B6: =Fluxo_de_Caixa_Janeiro[[#This Row],[Fluxo de Caixa 2026 CTR]] -> 1.2-BRADESCO 15232-3 MATRIZ | C6: =JANEIRO!C340 -> 3332.91 | D6: =IF(C6=0,"0,00%",C6/$C$2) -> 0.10465174
B7: =Fluxo_de_Caixa_Janeiro[[#This Row],[Fluxo de Caixa 2026 CTR]] -> 0 | C7: =JANEIRO!C341 -> 0 | D7: =IF(C7=0,"0,00%",C7/$C$2) -> 0,00%
B8: =Fluxo_de_Caixa_Janeiro[[#This Row],[Fluxo de Caixa 2026 CTR]] -> 1.3 - BANCO STONE MATRIZ C.C 40256726-7 | C8: =JANEIRO!C342 -> 2671 | D8: =IF(C8=0,"0,00%",C8/$C$2) -> 0.083868093 | E8: =#REF! -> #REF!
B9: =Fluxo_de_Caixa_Janeiro[[#This Row],[Fluxo de Caixa 2026 CTR]] -> 1.4 - BANCO DA AMAZONIA 071730-7 MATRIZ | C9: =JANEIRO!C343 -> 281.78 | D9: =IF(C9=0,"0,00%",C9/$C$2) -> 0.0088477541 | E9: =#REF! -> #REF!
B10: =Fluxo_de_Caixa_Janeiro[[#This Row],[Fluxo de Caixa 2026 CTR]] -> 1.4.1.INVESTIMENTO CDBORE RCP TXFL | C10: =JANEIRO!C344 -> 0 | D10: =IF(C10=0,"0,00%",C10/$C$2) -> 0,00% | E10: =#REF! -> #REF!
B11: =Fluxo_de_Caixa_Janeiro[[#This Row],[Fluxo de Caixa 2026 CTR]] -> 1.5 - ITAU C.C.98671-6 MATRIZ | C11: =JANEIRO!C345 -> 18153.73 | D11: =IF(C11=0,"0,00%",C11/$C$2) -> 0.57001824 | E11: =#REF! -> #REF!
B12: =Fluxo_de_Caixa_Janeiro[[#This Row],[Fluxo de Caixa 2026 CTR]] -> 1.5.03. ITAU C.C 83290-2 GARANTIDA | C12: =JANEIRO!C346 -> 1286.28 | D12: =IF(C12=0,"0,00%",C12/$C$2) -> 0.040388563 | E12: =#REF! -> #REF!
B13: =Fluxo_de_Caixa_Janeiro[[#This Row],[Fluxo de Caixa 2026 CTR]] -> 1.9 - CONTA PERDA/ROUBO/BONIFICAÇÃO E DOAÇÃO | C13: =JANEIRO!C347 -> 0 | D13: =IF(C13=0,"0,00%",C13/$C$2) -> 0,00%
B14: =Fluxo_de_Caixa_Janeiro[[#This Row],[Fluxo de Caixa 2026 CTR]] -> 0 | C14: =JANEIRO!C348 -> 0 | D14: =IF(C14=0,"0,00%",C14/$C$2) -> 0,00%
B15: =Fluxo_de_Caixa_Janeiro[[#This Row],[Fluxo de Caixa 2026 CTR]] -> 2.1 - BANCO DO BRASIL C.C.60638-3 FILIAL PALMAS | C15: =JANEIRO!C349 -> 1829.48 | D15: =IF(C15=0,"0,00%",C15/$C$2) -> 0.057444777
B16: =Fluxo_de_Caixa_Janeiro[[#This Row],[Fluxo de Caixa 2026 CTR]] -> 0 | C16: =JANEIRO!C350 -> 0 | D16: =IF(C16=0,"0,00%",C16/$C$2) -> 0,00%
B17: =Fluxo_de_Caixa_Janeiro[[#This Row],[Fluxo de Caixa 2026 CTR]] -> 0 | C17: =JANEIRO!C351 -> 0 | D17: =IF(C17=0,"0,00%",C17/$C$2) -> 0,00%
B18: =Fluxo_de_Caixa_Janeiro[[#This Row],[Fluxo de Caixa 2026 CTR]] -> 2.4 - ITAU C.C.98669-0 FILIAL PALMAS | C18: =JANEIRO!C352 -> 536.72 | D18: =IF(C18=0,"0,00%",C18/$C$2) -> 0.016852745
B19: =Fluxo_de_Caixa_Janeiro[[#This Row],[Fluxo de Caixa 2026 CTR]] -> 2.9 - CONTA PERDA/ROUBO E BONIFICAÇÃO FILIAL | C19: =JANEIRO!C353 -> -219.15 | D19: =IF(C19=0,"0,00%",C19/$C$2) -> -0.0068812028
B20: =Fluxo_de_Caixa_Janeiro[[#This Row],[Fluxo de Caixa 2026 CTR]] -> 4.0 - TESOURARIA FILIAL PORTO | C20: =JANEIRO!C354 -> 385.51 | D20: =IF(C20=0,"0,00%",C20/$C$2) -> 0.012104825
B21: =Fluxo_de_Caixa_Janeiro[[#This Row],[Fluxo de Caixa 2026 CTR]] -> 4.1 - BANCO DO BRASIL C.C.61105-0 FILIAL PORTO | C21: =JANEIRO!C355 -> 16.83 | E21: =#REF! -> #REF!
B22: =Fluxo_de_Caixa_Janeiro[[#This Row],[Fluxo de Caixa 2026 CTR]] -> 0 | C22: =JANEIRO!C356 -> 0 | E22: =#REF! -> #REF!
B23: =Fluxo_de_Caixa_Janeiro[[#This Row],[Fluxo de Caixa 2026 CTR]] -> 4.4 - MERCADO PAGO PIX FILIAL PORTO | C23: =JANEIRO!C357 -> 2060.42 | D23: =IF(C23=0,"0,00%",C23/$C$2) -> 0.06469618
B24: =Fluxo_de_Caixa_Janeiro[[#This Row],[Fluxo de Caixa 2026 CTR]] -> 4.9 - CONTA PERDA/ROUBO E BONIFICAÇÃO FILIAL | C24: =JANEIRO!C358 -> 0 | E24: =#REF! -> #REF!
B25: =Fluxo_de_Caixa_Janeiro[[#This Row],[Fluxo de Caixa 2026 CTR]] -> 91.CARTÃO ENDERED 5099+4596+6933+8072 - ESCRITORIO | C25: =JANEIRO!C359 -> 1362.74 | D25: =IF(C25=0,"0,00%",C25/$C$2) -> 0.042789369 | E25: =#REF! -> #REF!
B26: =Fluxo_de_Caixa_Janeiro[[#This Row],[Fluxo de Caixa 2026 CTR]] -> 0 | C26: =JANEIRO!C361 -> -150.01 | D26: =IF(C26=0,"0,00%",C26/$C$2) -> -0.0047102406 | G26: 24
B27: =Fluxo_de_Caixa_Janeiro[[#This Row],[Fluxo de Caixa 2026 CTR]] -> Total Receitas Operacionais / Vendas | C27: =SUBTOTAL(109,C29:C51) -> 1038589.1 | D27: =IFERROR(C27/C332,"") -> 0.99992917 | E27: 0.88526119 | H27: =H28+I28 -> 560226.19
A28: 1.1. Receita com Vendas | B28: =Fluxo_de_Caixa_Janeiro[[#This Row],[Fluxo de Caixa 2026 CTR]] -> 1.1. Receita com Vendas | C28: =SUBTOTAL(109,C29:C47) -> 1038589.1 | D28: =SUM(D29:D47) -> 0.99992917 | E28: 0.88251933 | H28: =SUM(H29:H36) -> 37065.49 | I28: =SUM(I29:I36) -> 523160.7 | J28: =SUM(J29:J36) -> 478362.9
B29: =Fluxo_de_Caixa_Janeiro[[#This Row],[Fluxo de Caixa 2026 CTR]] -> 1.1.01. Receita em Dinheiro | C29: =H29+I29+J29 -> 4660.37 | D29: =IF(C29=0,"0,00%",C29/$C$332) -> 0.0044868947 | E29: 0.079252981 | F29: =IF(Fluxo_de_Caixa_Janeiro34591171012151619[[#This Row],[% ACUMULADO DEZ/2026]]>=Fluxo_de_Caixa_Janeiro34591171012151619[[#This Row],[% Acum no Ano Comparação]],"Verd","Fals") -> Verd | H29: 135.61 | I29: 3436.01 | J29: 1088.75
B30: =Fluxo_de_Caixa_Janeiro[[#This Row],[Fluxo de Caixa 2026 CTR]] -> 1.1.01. Receita em Cartão (Crédito e Débito) | C30: =H30+I30+J30 -> 221053.51 | D30: =IF(C30=0,"0,00%",C30/$C$332) -> 0.21282512 | E30: 0.092740536 | F30: =IF(Fluxo_de_Caixa_Janeiro34591171012151619[[#This Row],[% ACUMULADO DEZ/2026]]>=Fluxo_de_Caixa_Janeiro34591171012151619[[#This Row],[% Acum no Ano Comparação]],"Verd","Fals") -> Verd | H30: 7056.17 | I30: 134559.92 | J30: 79437.42
B31: =Fluxo_de_Caixa_Janeiro[[#This Row],[Fluxo de Caixa 2026 CTR]] -> 1.1.01. Receita de Cheque A Vista | C31: =H31+I31+J31 -> 26907.75 | D31: =IF(C31=0,"0,00%",C31/$C$332) -> 0.025906149 | E31: 0.00028628486 | F31: =IF(Fluxo_de_Caixa_Janeiro34591171012151619[[#This Row],[% ACUMULADO DEZ/2026]]>=Fluxo_de_Caixa_Janeiro34591171012151619[[#This Row],[% Acum no Ano Comparação]],"Verd","Fals") -> Verd | I31: 26907.75
B32: =Fluxo_de_Caixa_Janeiro[[#This Row],[Fluxo de Caixa 2026 CTR]] -> 1.1.01. Receita de Cheque Pré | C32: =H32+I32+J32 -> 0 | D32: =IF(C32=0,"0,00%",C32/$C$332) -> 0,00% | E32: 0.0063111634 | F32: =IF(Fluxo_de_Caixa_Janeiro34591171012151619[[#This Row],[% ACUMULADO DEZ/2026]]>=Fluxo_de_Caixa_Janeiro34591171012151619[[#This Row],[% Acum no Ano Comparação]],"Verd","Fals") -> Verd | G32: =C361 -> 180.01
B33: =Fluxo_de_Caixa_Janeiro[[#This Row],[Fluxo de Caixa 2026 CTR]] -> 1.1.01. Recebimento de Carteira (Notinha) | C33: =H33+I33+J33 -> 0 | D33: =IF(C33=0,"0,00%",C33/$C$332) -> 0,00% | E33: 0.0001318638 | F33: =IF(Fluxo_de_Caixa_Janeiro34591171012151619[[#This Row],[% ACUMULADO DEZ/2026]]>=Fluxo_de_Caixa_Janeiro34591171012151619[[#This Row],[% Acum no Ano Comparação]],"Verd","Fals") -> Verd
B34: =Fluxo_de_Caixa_Janeiro[[#This Row],[Fluxo de Caixa 2026 CTR]] -> 1.1.01. Recebimento de Boletos | C34: =H34+I34+J34 -> 317162.15 | D34: =IF(C34=0,"0,00%",C34/$C$332) -> 0.30535626 | E34: 0.66745712 | F34: =IF(Fluxo_de_Caixa_Janeiro34591171012151619[[#This Row],[% ACUMULADO DEZ/2026]]>=Fluxo_de_Caixa_Janeiro34591171012151619[[#This Row],[% Acum no Ano Comparação]],"Verd","Fals") -> Verd | H34: 22534.42 | I34: =94826.7+10161.81 -> 104988.51 | J34: 189639.22
B35: =Fluxo_de_Caixa_Janeiro[[#This Row],[Fluxo de Caixa 2026 CTR]] -> 1.1.01. Recebimento em Depósito e Dep. PIX | C35: =H35+I35+J35 -> 468805.31 | D35: =IF(C35=0,"0,00%",C35/$C$332) -> 0.45135474 | E35: 0.036171198 | F35: =IF(Fluxo_de_Caixa_Janeiro34591171012151619[[#This Row],[% ACUMULADO DEZ/2026]]>=Fluxo_de_Caixa_Janeiro34591171012151619[[#This Row],[% Acum no Ano Comparação]],"Verd","Fals") -> Verd | H35: 7339.29 | I35: 253268.51 | J35: 208197.51
B36: =Fluxo_de_Caixa_Janeiro[[#This Row],[Fluxo de Caixa 2026 CTR]] -> 1.1.02. Recebimento Cheque Devolvido | C36: =H36+I36+J36 -> 0 | D36: =IF(C36=0,"0,00%",C36/$C$332) -> 0,00% | E36: 0.00016817802 | F36: =IF(Fluxo_de_Caixa_Janeiro34591171012151619[[#This Row],[% ACUMULADO DEZ/2026]]>=Fluxo_de_Caixa_Janeiro34591171012151619[[#This Row],[% Acum no Ano Comparação]],"Verd","Fals") -> Verd
B37: =Fluxo_de_Caixa_Janeiro[[#This Row],[Fluxo de Caixa 2026 CTR]] -> 0 | D37: =IF(C37=0,"0,00%",C37/$C$332) -> 0,00% | E37: =#REF! -> #REF! | F37: =IF(Fluxo_de_Caixa_Janeiro34591171012151619[[#This Row],[% ACUMULADO DEZ/2026]]>=Fluxo_de_Caixa_Janeiro34591171012151619[[#This Row],[% Acum no Ano Comparação]],"Verd","Fals") -> #REF!
B38: =Fluxo_de_Caixa_Janeiro[[#This Row],[Fluxo de Caixa 2026 CTR]] -> 0 | D38: =IF(C38=0,"0,00%",C38/$C$332) -> 0,00% | E38: =#REF! -> #REF! | F38: =IF(Fluxo_de_Caixa_Janeiro34591171012151619[[#This Row],[% ACUMULADO DEZ/2026]]>=Fluxo_de_Caixa_Janeiro34591171012151619[[#This Row],[% Acum no Ano Comparação]],"Verd","Fals") -> #REF!
B39: =Fluxo_de_Caixa_Janeiro[[#This Row],[Fluxo de Caixa 2026 CTR]] -> 0 | D39: =IF(C39=0,"0,00%",C39/$C$332) -> 0,00% | E39: =#REF! -> #REF! | F39: =IF(Fluxo_de_Caixa_Janeiro34591171012151619[[#This Row],[% ACUMULADO DEZ/2026]]>=Fluxo_de_Caixa_Janeiro34591171012151619[[#This Row],[% Acum no Ano Comparação]],"Verd","Fals") -> #REF!
B40: =Fluxo_de_Caixa_Janeiro[[#This Row],[Fluxo de Caixa 2026 CTR]] -> 0 | D40: =IF(C40=0,"0,00%",C40/$C$332) -> 0,00% | E40: =#REF! -> #REF! | F40: =IF(Fluxo_de_Caixa_Janeiro34591171012151619[[#This Row],[% ACUMULADO DEZ/2026]]>=Fluxo_de_Caixa_Janeiro34591171012151619[[#This Row],[% Acum no Ano Comparação]],"Verd","Fals") -> #REF!
B41: =Fluxo_de_Caixa_Janeiro[[#This Row],[Fluxo de Caixa 2026 CTR]] -> 0 | D41: =IF(C41=0,"0,00%",C41/$C$332) -> 0,00% | E41: =#REF! -> #REF! | F41: =IF(Fluxo_de_Caixa_Janeiro34591171012151619[[#This Row],[% ACUMULADO DEZ/2026]]>=Fluxo_de_Caixa_Janeiro34591171012151619[[#This Row],[% Acum no Ano Comparação]],"Verd","Fals") -> #REF!
B42: =Fluxo_de_Caixa_Janeiro[[#This Row],[Fluxo de Caixa 2026 CTR]] -> 0 | D42: =IF(C42=0,"0,00%",C42/$C$332) -> 0,00% | E42: =#REF! -> #REF! | F42: =IF(Fluxo_de_Caixa_Janeiro34591171012151619[[#This Row],[% ACUMULADO DEZ/2026]]>=Fluxo_de_Caixa_Janeiro34591171012151619[[#This Row],[% Acum no Ano Comparação]],"Verd","Fals") -> #REF!
B43: =Fluxo_de_Caixa_Janeiro[[#This Row],[Fluxo de Caixa 2026 CTR]] -> 0 | D43: =IF(C43=0,"0,00%",C43/$C$332) -> 0,00% | E43: =#REF! -> #REF! | F43: =IF(Fluxo_de_Caixa_Janeiro34591171012151619[[#This Row],[% ACUMULADO DEZ/2026]]>=Fluxo_de_Caixa_Janeiro34591171012151619[[#This Row],[% Acum no Ano Comparação]],"Verd","Fals") -> #REF!
B44: =Fluxo_de_Caixa_Janeiro[[#This Row],[Fluxo de Caixa 2026 CTR]] -> 0 | D44: =IF(C44=0,"0,00%",C44/$C$332) -> 0,00% | E44: =#REF! -> #REF! | F44: =IF(Fluxo_de_Caixa_Janeiro34591171012151619[[#This Row],[% ACUMULADO DEZ/2026]]>=Fluxo_de_Caixa_Janeiro34591171012151619[[#This Row],[% Acum no Ano Comparação]],"Verd","Fals") -> #REF!
B45: =Fluxo_de_Caixa_Janeiro[[#This Row],[Fluxo de Caixa 2026 CTR]] -> 0 | D45: =IF(C45=0,"0,00%",C45/$C$332) -> 0,00% | E45: =#REF! -> #REF! | F45: =IF(Fluxo_de_Caixa_Janeiro34591171012151619[[#This Row],[% ACUMULADO DEZ/2026]]>=Fluxo_de_Caixa_Janeiro34591171012151619[[#This Row],[% Acum no Ano Comparação]],"Verd","Fals") -> #REF!
B46: =Fluxo_de_Caixa_Janeiro[[#This Row],[Fluxo de Caixa 2026 CTR]] -> 0 | C46: 0 | D46: =IF(C46=0,"0,00%",C46/$C$332) -> 0,00% | E46: =#REF! -> #REF! | F46: =IF(Fluxo_de_Caixa_Janeiro34591171012151619[[#This Row],[% ACUMULADO DEZ/2026]]>=Fluxo_de_Caixa_Janeiro34591171012151619[[#This Row],[% Acum no Ano Comparação]],"Verd","Fals") -> #REF!
B47: =Fluxo_de_Caixa_Janeiro[[#This Row],[Fluxo de Caixa 2026 CTR]] -> 0 | D47: =IF(C47=0,"0,00%",C47/$C$332) -> 0,00% | E47: =#REF! -> #REF! | F47: =IF(Fluxo_de_Caixa_Janeiro34591171012151619[[#This Row],[% ACUMULADO DEZ/2026]]>=Fluxo_de_Caixa_Janeiro34591171012151619[[#This Row],[% Acum no Ano Comparação]],"Verd","Fals") -> #REF!
A48: 1.5. Receita de Garantias | B48: =Fluxo_de_Caixa_Janeiro[[#This Row],[Fluxo de Caixa 2026 CTR]] -> 1.5. Receita de Garantias | C48: =+SUBTOTAL(109,C49:C51) -> 0 | D48: =SUM(D49:D51) -> 0 | E48: 0.0027418655 | H48: =SUM(H49:H51) -> 0 | I48: =SUM(I49:I51) -> 0 | J48: =SUM(J49:J51) -> 0
B49: =Fluxo_de_Caixa_Janeiro[[#This Row],[Fluxo de Caixa 2026 CTR]] -> 1.2.01. RECEITA EM DINHEIRO | C49: =H49+I49 -> 0 | D49: =IF(C49=0,"0,00%",C49/$C$332) -> 0,00% | E49: 0.0024323151 | F49: =IF(Fluxo_de_Caixa_Janeiro34591171012151619[[#This Row],[% ACUMULADO DEZ/2026]]>=Fluxo_de_Caixa_Janeiro34591171012151619[[#This Row],[% Acum no Ano Comparação]],"Verd","Fals") -> Verd
B50: =Fluxo_de_Caixa_Janeiro[[#This Row],[Fluxo de Caixa 2026 CTR]] -> 1.2.02. RECEITA EM MERCADORIA | C50: =H50+I50 -> 0 | D50: =IF(C50=0,"0,00%",C50/$C$332) -> 0,00% | E50: 0.00030955038 | F50: =IF(Fluxo_de_Caixa_Janeiro34591171012151619[[#This Row],[% ACUMULADO DEZ/2026]]>=Fluxo_de_Caixa_Janeiro34591171012151619[[#This Row],[% Acum no Ano Comparação]],"Verd","Fals") -> Verd
B51: =Fluxo_de_Caixa_Janeiro[[#This Row],[Fluxo de Caixa 2026 CTR]] -> 0 | C51: =H51+I51 -> 0 | D51: =IF(C51=0,"0,00%",C51/$C$332) -> 0,00% | E51: =#REF! -> #REF! | F51: =IF(Fluxo_de_Caixa_Janeiro34591171012151619[[#This Row],[% ACUMULADO DEZ/2026]]>=Fluxo_de_Caixa_Janeiro34591171012151619[[#This Row],[% Acum no Ano Comparação]],"Verd","Fals") -> #REF!
A52: 2.1. Despesa Com Custo de Aquisição | B52: =Fluxo_de_Caixa_Janeiro[[#This Row],[Fluxo de Caixa 2026 CTR]] -> 2.1. Despesa Com Custo de Aquisição | C52: =-SUBTOTAL(109,C53:C59) -> -419540.11 | D52: =-IFERROR(C52/$C$27,"0,00") -> 0.40395197 | E52: 0.7032551 | F52: =IF(Fluxo_de_Caixa_Janeiro34591171012151619[[#This Row],[% ACUMULADO DEZ/2026]]<=Fluxo_de_Caixa_Janeiro34591171012151619[[#This Row],[% Acum no Ano Comparação]],"Verd","Fals") -> Verd | H52: =-SUBTOTAL(109,H53:H59) -> -397184.55 | I52: =-SUBTOTAL(109,I53:I59) -> -20410.32 | J52: =-SUBTOTAL(109,J53:J59) -> -1945.24
B53: =Fluxo_de_Caixa_Janeiro[[#This Row],[Fluxo de Caixa 2026 CTR]] -> 2.1.01.FORNECEDORES DE MERCADORIAS REVENDA | C53: =H53+I53+J53 -> 400361.57 | D53: =IFERROR(C53/$C$27,"0,00%") -> 0.38548602 | E53: 0.70044704 | F53: =IF(Fluxo_de_Caixa_Janeiro34591171012151619[[#This Row],[% ACUMULADO DEZ/2026]]<=Fluxo_de_Caixa_Janeiro34591171012151619[[#This Row],[% Acum no Ano Comparação]],"Verd","Fals") -> Fals | H53: 379782.19 | I53: 19363.74 | J53: 1215.64
B54: =Fluxo_de_Caixa_Janeiro[[#This Row],[Fluxo de Caixa 2026 CTR]] -> 2.1.02.ADIANT. FORNEC. MERCA. REVENDA | C54: =H54+I54+J54 -> 0 | D54: =IFERROR(C54/$C$27,"0,00%") -> 0 | E54: 0.0028080664 | F54: =IF(Fluxo_de_Caixa_Janeiro34591171012151619[[#This Row],[% ACUMULADO DEZ/2026]]<=Fluxo_de_Caixa_Janeiro34591171012151619[[#This Row],[% Acum no Ano Comparação]],"Verd","Fals") -> Fals
B55: =Fluxo_de_Caixa_Janeiro[[#This Row],[Fluxo de Caixa 2026 CTR]] -> 2.1.03.TRANSPORTADORA MERCA. REVENDA | C55: =H55+I55+J55 -> 19178.54 | D55: =IFERROR(C55/$C$27,"0,00%") -> 0.018465956 | E55: 0 | F55: =IF(Fluxo_de_Caixa_Janeiro34591171012151619[[#This Row],[% ACUMULADO DEZ/2026]]<=Fluxo_de_Caixa_Janeiro34591171012151619[[#This Row],[% Acum no Ano Comparação]],"Verd","Fals") -> Fals | H55: 17402.36 | I55: 1046.58 | J55: 729.6
B56: =Fluxo_de_Caixa_Janeiro[[#This Row],[Fluxo de Caixa 2026 CTR]] -> 2.1.04.OUTROS CUSTOS DE MERC.REVENDA | C56: =H56+I56+J56 -> 0 | D56: =IFERROR(C56/$C$27,"0,00%") -> 0 | E56: =#REF! -> #REF! | F56: =IF(Fluxo_de_Caixa_Janeiro34591171012151619[[#This Row],[% ACUMULADO DEZ/2026]]<=Fluxo_de_Caixa_Janeiro34591171012151619[[#This Row],[% Acum no Ano Comparação]],"Verd","Fals") -> #REF!
B57: =Fluxo_de_Caixa_Janeiro[[#This Row],[Fluxo de Caixa 2026 CTR]] -> 2.1.05.TRANSFE DE MERCAD REVENDA MATRIZ | C57: =H57+I57+J57 -> 0 | D57: =IFERROR(C57/$C$27,"0,00%") -> 0 | E57: =#REF! -> #REF! | F57: =IF(Fluxo_de_Caixa_Janeiro34591171012151619[[#This Row],[% ACUMULADO DEZ/2026]]<=Fluxo_de_Caixa_Janeiro34591171012151619[[#This Row],[% Acum no Ano Comparação]],"Verd","Fals") -> #REF!
B58: =Fluxo_de_Caixa_Janeiro[[#This Row],[Fluxo de Caixa 2026 CTR]] -> 0 | D58: =IFERROR(C58/$C$27,"0,00%") -> 0 | E58: =#REF! -> #REF! | F58: =IF(Fluxo_de_Caixa_Janeiro34591171012151619[[#This Row],[% ACUMULADO DEZ/2026]]<=Fluxo_de_Caixa_Janeiro34591171012151619[[#This Row],[% Acum no Ano Comparação]],"Verd","Fals") -> #REF!
B59: =Fluxo_de_Caixa_Janeiro[[#This Row],[Fluxo de Caixa 2026 CTR]] -> 0 | D59: =IFERROR(C59/$C$27,"0,00%") -> 0 | E59: =#REF! -> #REF! | F59: =IF(Fluxo_de_Caixa_Janeiro34591171012151619[[#This Row],[% ACUMULADO DEZ/2026]]<=Fluxo_de_Caixa_Janeiro34591171012151619[[#This Row],[% Acum no Ano Comparação]],"Verd","Fals") -> #REF!
A60: 2.2. Inadimplência e Perdas | B60: =Fluxo_de_Caixa_Janeiro[[#This Row],[Fluxo de Caixa 2026 CTR]] -> 2.2. Inadimplência e Perdas | C60: =-SUBTOTAL(109,C61:C69) -> -57235.67 | D60: =-IFERROR(C60/$C$27,"0,00") -> 0.055109061 | E60: 0.0013173948 | F60: =IF(Fluxo_de_Caixa_Janeiro34591171012151619[[#This Row],[% ACUMULADO DEZ/2026]]<=Fluxo_de_Caixa_Janeiro34591171012151619[[#This Row],[% Acum no Ano Comparação]],"Verd","Fals") -> Verd | H60: =-SUBTOTAL(109,H61:H69) -> -20953.13 | I60: =-SUBTOTAL(109,I61:I69) -> -29071.86 | J60: =-SUBTOTAL(109,J61:J69) -> -7210.68
B61: =Fluxo_de_Caixa_Janeiro[[#This Row],[Fluxo de Caixa 2026 CTR]] -> 2.2.01.CONTAS PERDIDAS/NÃO PAGAS | C61: =H61+I61+J61 -> 57235.67 | D61: =IFERROR(C61/$C$27,"0,00%") -> 0.055109061 | E61: 0 | F61: =IF(Fluxo_de_Caixa_Janeiro34591171012151619[[#This Row],[% ACUMULADO DEZ/2026]]<=Fluxo_de_Caixa_Janeiro34591171012151619[[#This Row],[% Acum no Ano Comparação]],"Verd","Fals") -> Fals | H61: 20953.13 | I61: 29071.86 | J61: 7210.68
B62: =Fluxo_de_Caixa_Janeiro[[#This Row],[Fluxo de Caixa 2026 CTR]] -> 2.2.02.BOLETOS DESCONTADOS DEVOLVIDOS | C62: =H62+I62+J62 -> 0 | D62: =IFERROR(C62/$C$27,"0,00%") -> 0 | E62: 0 | F62: =IF(Fluxo_de_Caixa_Janeiro34591171012151619[[#This Row],[% ACUMULADO DEZ/2026]]<=Fluxo_de_Caixa_Janeiro34591171012151619[[#This Row],[% Acum no Ano Comparação]],"Verd","Fals") -> Fals
B63: =Fluxo_de_Caixa_Janeiro[[#This Row],[Fluxo de Caixa 2026 CTR]] -> 2.2.03.CHEQUES DEVOLVIDOS | C63: =H63+I63+J63 -> 0 | D63: =IFERROR(C63/$C$27,"0,00%") -> 0 | E63: 0 | F63: =IF(Fluxo_de_Caixa_Janeiro34591171012151619[[#This Row],[% ACUMULADO DEZ/2026]]<=Fluxo_de_Caixa_Janeiro34591171012151619[[#This Row],[% Acum no Ano Comparação]],"Verd","Fals") -> Fals
B64: =Fluxo_de_Caixa_Janeiro[[#This Row],[Fluxo de Caixa 2026 CTR]] -> 2.2.04.BOLETOS DESCONTADOS DEVOLVIDOS | C64: =H64+I64+J64 -> 0 | D64: =IFERROR(C64/$C$27,"0,00%") -> 0 | E64: 0.0012728671 | F64: =IF(Fluxo_de_Caixa_Janeiro34591171012151619[[#This Row],[% ACUMULADO DEZ/2026]]<=Fluxo_de_Caixa_Janeiro34591171012151619[[#This Row],[% Acum no Ano Comparação]],"Verd","Fals") -> Fals
B65: =Fluxo_de_Caixa_Janeiro[[#This Row],[Fluxo de Caixa 2026 CTR]] -> 2.2.05.PERDA, ROUBO E DETERIORAÇÃO | C65: =H65+I65+J65 -> 0 | D65: =IFERROR(C65/$C$27,"0,00%") -> 0 | E65: 4.4527688e-05 | F65: =IF(Fluxo_de_Caixa_Janeiro34591171012151619[[#This Row],[% ACUMULADO DEZ/2026]]<=Fluxo_de_Caixa_Janeiro34591171012151619[[#This Row],[% Acum no Ano Comparação]],"Verd","Fals") -> Fals
B66: =Fluxo_de_Caixa_Janeiro[[#This Row],[Fluxo de Caixa 2026 CTR]] -> 0 | C66: =H66+I66+J66 -> 0 | D66: =IFERROR(C66/$C$27,"0,00%") -> 0 | E66: =#REF! -> #REF! | F66: =IF(Fluxo_de_Caixa_Janeiro34591171012151619[[#This Row],[% ACUMULADO DEZ/2026]]<=Fluxo_de_Caixa_Janeiro34591171012151619[[#This Row],[% Acum no Ano Comparação]],"Verd","Fals") -> #REF!
B67: =Fluxo_de_Caixa_Janeiro[[#This Row],[Fluxo de Caixa 2026 CTR]] -> 0 | C67: =H67+I67+J67 -> 0 | D67: =IFERROR(C67/$C$27,"0,00%") -> 0 | E67: =#REF! -> #REF! | F67: =IF(Fluxo_de_Caixa_Janeiro34591171012151619[[#This Row],[% ACUMULADO DEZ/2026]]<=Fluxo_de_Caixa_Janeiro34591171012151619[[#This Row],[% Acum no Ano Comparação]],"Verd","Fals") -> #REF!
B68: =Fluxo_de_Caixa_Janeiro[[#This Row],[Fluxo de Caixa 2026 CTR]] -> 0 | C68: =H68+I68+J68 -> 0 | D68: =IFERROR(C68/$C$27,"0,00%") -> 0 | E68: =#REF! -> #REF! | F68: =IF(Fluxo_de_Caixa_Janeiro34591171012151619[[#This Row],[% ACUMULADO DEZ/2026]]<=Fluxo_de_Caixa_Janeiro34591171012151619[[#This Row],[% Acum no Ano Comparação]],"Verd","Fals") -> #REF!
B69: =Fluxo_de_Caixa_Janeiro[[#This Row],[Fluxo de Caixa 2026 CTR]] -> 0 | C69: =H69+I69+J69 -> 0 | D69: =IFERROR(C69/$C$27,"0,00%") -> 0 | E69: =#REF! -> #REF! | F69: =IF(Fluxo_de_Caixa_Janeiro34591171012151619[[#This Row],[% ACUMULADO DEZ/2026]]<=Fluxo_de_Caixa_Janeiro34591171012151619[[#This Row],[% Acum no Ano Comparação]],"Verd","Fals") -> #REF!
A70: 2.3. Impostos | B70: =Fluxo_de_Caixa_Janeiro[[#This Row],[Fluxo de Caixa 2026 CTR]] -> 2.3. Impostos | C70: =-SUBTOTAL(109,C71:C84) -> -176996.86 | D70: =-IFERROR(C70/$C$27,"0,00") -> 0.17042049 | E70: 0.12754151 | F70: =IF(Fluxo_de_Caixa_Janeiro34591171012151619[[#This Row],[% ACUMULADO DEZ/2026]]<=Fluxo_de_Caixa_Janeiro34591171012151619[[#This Row],[% Acum no Ano Comparação]],"Verd","Fals") -> Verd | H70: =-SUBTOTAL(109,H71:H84) -> -123750.42 | I70: =-SUBTOTAL(109,I71:I84) -> -22175.94 | J70: =-SUBTOTAL(109,J71:J84) -> -31070.5
B71: =Fluxo_de_Caixa_Janeiro[[#This Row],[Fluxo de Caixa 2026 CTR]] -> 0 | D71: =IFERROR(C71/$C$27,"0,00%") -> 0 | E71: 0.0010503863 | F71: =IF(Fluxo_de_Caixa_Janeiro34591171012151619[[#This Row],[% ACUMULADO DEZ/2026]]<=Fluxo_de_Caixa_Janeiro34591171012151619[[#This Row],[% Acum no Ano Comparação]],"Verd","Fals") -> Fals
B72: =Fluxo_de_Caixa_Janeiro[[#This Row],[Fluxo de Caixa 2026 CTR]] -> 2.3.02.IRPJ (SE ESTIVER NO CMV) | C72: =H72+I72+J72 -> 50219.25 | D72: =IFERROR(C72/$C$27,"0,00%") -> 0.048353339 | E72: 0.00062053498 | F72: =IF(Fluxo_de_Caixa_Janeiro34591171012151619[[#This Row],[% ACUMULADO DEZ/2026]]<=Fluxo_de_Caixa_Janeiro34591171012151619[[#This Row],[% Acum no Ano Comparação]],"Verd","Fals") -> Fals | H72: 50219.25
B73: =Fluxo_de_Caixa_Janeiro[[#This Row],[Fluxo de Caixa 2026 CTR]] -> 2.3.03.CSSL (SE ESTIVER NO CMV) | C73: =H73+I73+J73 -> 30668.76 | D73: =IFERROR(C73/$C$27,"0,00%") -> 0.029529253 | E73: 0.003344374 | F73: =IF(Fluxo_de_Caixa_Janeiro34591171012151619[[#This Row],[% ACUMULADO DEZ/2026]]<=Fluxo_de_Caixa_Janeiro34591171012151619[[#This Row],[% Acum no Ano Comparação]],"Verd","Fals") -> Fals | H73: 30668.76
B74: =Fluxo_de_Caixa_Janeiro[[#This Row],[Fluxo de Caixa 2026 CTR]] -> 2.3.04.COFINS (SE ESTIVER NO CMV) | C74: =H74+I74+J74 -> 0 | D74: =IFERROR(C74/$C$27,"0,00%") -> 0 | E74: 0.00072605477 | F74: =IF(Fluxo_de_Caixa_Janeiro34591171012151619[[#This Row],[% ACUMULADO DEZ/2026]]<=Fluxo_de_Caixa_Janeiro34591171012151619[[#This Row],[% Acum no Ano Comparação]],"Verd","Fals") -> Fals
B75: =Fluxo_de_Caixa_Janeiro[[#This Row],[Fluxo de Caixa 2026 CTR]] -> 2.3.05.PIS (SE ESTIVER NO CMV) | C75: =H75+I75+J75 -> 0 | D75: =IFERROR(C75/$C$27,"0,00%") -> 0 | E75: 0.051721948 | F75: =IF(Fluxo_de_Caixa_Janeiro34591171012151619[[#This Row],[% ACUMULADO DEZ/2026]]<=Fluxo_de_Caixa_Janeiro34591171012151619[[#This Row],[% Acum no Ano Comparação]],"Verd","Fals") -> Fals
B76: =Fluxo_de_Caixa_Janeiro[[#This Row],[Fluxo de Caixa 2026 CTR]] -> 2.3.06.ICMS – Normal (SE ESTIVER NO CMV) | C76: =H76+I76+J76 -> 66402.54 | D76: =IFERROR(C76/$C$27,"0,00%") -> 0.063935334 | E76: 0.067027605 | F76: =IF(Fluxo_de_Caixa_Janeiro34591171012151619[[#This Row],[% ACUMULADO DEZ/2026]]<=Fluxo_de_Caixa_Janeiro34591171012151619[[#This Row],[% Acum no Ano Comparação]],"Verd","Fals") -> Fals | H76: 13817.18 | I76: 22175.94 | J76: 30409.42
B77: =Fluxo_de_Caixa_Janeiro[[#This Row],[Fluxo de Caixa 2026 CTR]] -> 2.3.07. SUBSTITUIÇÃO TRIBUTARIA SAÍDA (TARE) | C77: =H77+I77+J77 -> 13988.27 | D77: =IFERROR(C77/$C$27,"0,00%") -> 0.013468532 | E77: 0.0030506108 | F77: =IF(Fluxo_de_Caixa_Janeiro34591171012151619[[#This Row],[% ACUMULADO DEZ/2026]]<=Fluxo_de_Caixa_Janeiro34591171012151619[[#This Row],[% Acum no Ano Comparação]],"Verd","Fals") -> Fals | H77: 13988.27
B78: =Fluxo_de_Caixa_Janeiro[[#This Row],[Fluxo de Caixa 2026 CTR]] -> 2.3.08.SUBSTITUIÇÃO TRIBUTÁRIA NA ENTRADA | C78: =H78+I78+J78 -> 0 | D78: =IFERROR(C78/$C$27,"0,00%") -> 0 | E78: =#REF! -> #REF! | F78: =IF(Fluxo_de_Caixa_Janeiro34591171012151619[[#This Row],[% ACUMULADO DEZ/2026]]<=Fluxo_de_Caixa_Janeiro34591171012151619[[#This Row],[% Acum no Ano Comparação]],"Verd","Fals") -> #REF!
B79: =Fluxo_de_Caixa_Janeiro[[#This Row],[Fluxo de Caixa 2026 CTR]] -> 2.3.09.FUNDO DESENVOLVIMENTO ECONOMICO (TARE) | C79: =H79+I79+J79 -> 204.79 | D79: =IFERROR(C79/$C$27,"0,00%") -> 0.00019718097 | E79: =#REF! -> #REF! | F79: =IF(Fluxo_de_Caixa_Janeiro34591171012151619[[#This Row],[% ACUMULADO DEZ/2026]]<=Fluxo_de_Caixa_Janeiro34591171012151619[[#This Row],[% Acum no Ano Comparação]],"Verd","Fals") -> #REF! | H79: 204.79
B80: =Fluxo_de_Caixa_Janeiro[[#This Row],[Fluxo de Caixa 2026 CTR]] -> 0 | C80: =H80+I80+J80 -> 0 | D80: =IFERROR(C80/$C$27,"0,00%") -> 0 | E80: =#REF! -> #REF! | F80: =IF(Fluxo_de_Caixa_Janeiro34591171012151619[[#This Row],[% ACUMULADO DEZ/2026]]<=Fluxo_de_Caixa_Janeiro34591171012151619[[#This Row],[% Acum no Ano Comparação]],"Verd","Fals") -> #REF!
B81: =Fluxo_de_Caixa_Janeiro[[#This Row],[Fluxo de Caixa 2026 CTR]] -> 0 | C81: =H81+I81+J81 -> 0 | D81: =IFERROR(C81/$C$27,"0,00%") -> 0 | E81: =#REF! -> #REF! | F81: =IF(Fluxo_de_Caixa_Janeiro34591171012151619[[#This Row],[% ACUMULADO DEZ/2026]]<=Fluxo_de_Caixa_Janeiro34591171012151619[[#This Row],[% Acum no Ano Comparação]],"Verd","Fals") -> #REF!
B82: =Fluxo_de_Caixa_Janeiro[[#This Row],[Fluxo de Caixa 2026 CTR]] -> 2.3.11. Impostos Parcelado | C82: =H82+I82+J82 -> 15513.25 | D82: =IFERROR(C82/$C$27,"0,00%") -> 0.014936851 | E82: =#REF! -> #REF! | F82: =IF(Fluxo_de_Caixa_Janeiro34591171012151619[[#This Row],[% ACUMULADO DEZ/2026]]<=Fluxo_de_Caixa_Janeiro34591171012151619[[#This Row],[% Acum no Ano Comparação]],"Verd","Fals") -> #REF! | H82: 14852.17 | J82: 661.08
B83: =Fluxo_de_Caixa_Janeiro[[#This Row],[Fluxo de Caixa 2026 CTR]] -> 0 | D83: =IFERROR(C83/$C$27,"0,00%") -> 0 | E83: =#REF! -> #REF! | F83: =IF(Fluxo_de_Caixa_Janeiro34591171012151619[[#This Row],[% ACUMULADO DEZ/2026]]<=Fluxo_de_Caixa_Janeiro34591171012151619[[#This Row],[% Acum no Ano Comparação]],"Verd","Fals") -> #REF!
B84: =Fluxo_de_Caixa_Janeiro[[#This Row],[Fluxo de Caixa 2026 CTR]] -> 0 | D84: =IFERROR(C84/$C$27,"0,00%") -> 0 | E84: =#REF! -> #REF! | F84: =IF(Fluxo_de_Caixa_Janeiro34591171012151619[[#This Row],[% ACUMULADO DEZ/2026]]<=Fluxo_de_Caixa_Janeiro34591171012151619[[#This Row],[% Acum no Ano Comparação]],"Verd","Fals") -> #REF!
B85: =Fluxo_de_Caixa_Janeiro[[#This Row],[Fluxo de Caixa 2026 CTR]] -> Total dos Custos | C85: =-SUBTOTAL(109,C52:C84) -> -653772.64 | D85: =IFERROR(C85/C27,"0,00%") -> -0.62948152 | E85: =#REF! -> #REF! | F85: =IF(Fluxo_de_Caixa_Janeiro34591171012151619[[#This Row],[% ACUMULADO DEZ/2026]]<=Fluxo_de_Caixa_Janeiro34591171012151619[[#This Row],[% Acum no Ano Comparação]],"Verd","Fals") -> #REF! | H85: =-SUBTOTAL(109,H52:H84) -> -541888.1 | I85: =-SUBTOTAL(109,I52:I84) -> -71658.12 | J85: =-SUBTOTAL(109,J52:J84) -> -40226.42
B86: =Fluxo_de_Caixa_Janeiro[[#This Row],[Fluxo de Caixa 2026 CTR]] -> Receita Operacional Bruta | C86: =SUM(C27,C85) -> 384816.45 | D86: =IFERROR(C86/C27,"0,00%") -> 0.37051848 | E86: =#REF! -> #REF! | F86: =IF(Fluxo_de_Caixa_Janeiro34591171012151619[[#This Row],[% ACUMULADO DEZ/2026]]>=Fluxo_de_Caixa_Janeiro34591171012151619[[#This Row],[% Acum no Ano Comparação]],"Verd","Fals") -> #REF!
B87: =Fluxo_de_Caixa_Janeiro[[#This Row],[Fluxo de Caixa 2026 CTR]] -> 300. Despesas Operac. Fixas e Variáveis
A88: 3.1. DESPESA COM VENDAS | B88: =Fluxo_de_Caixa_Janeiro[[#This Row],[Fluxo de Caixa 2026 CTR]] -> 3.1. DESPESA COM VENDAS | C88: =-SUBTOTAL(109,C89:C99) -> -74448.1 | D88: =-IFERROR(C88/$C$27,"0,00") -> 0.071681958 | E88: 0.030857534 | F88: =IF(Fluxo_de_Caixa_Janeiro34591171012151619[[#This Row],[% ACUMULADO DEZ/2026]]<=Fluxo_de_Caixa_Janeiro34591171012151619[[#This Row],[% Acum no Ano Comparação]],"Verd","Fals") -> Verd | H88: =-SUBTOTAL(109,H89:H99) -> -68990.28 | I88: =-SUBTOTAL(109,I89:I99) -> -170.5 | J88: =-SUBTOTAL(109,J89:J99) -> -5287.32
B89: =Fluxo_de_Caixa_Janeiro[[#This Row],[Fluxo de Caixa 2026 CTR]] -> 3.1.01. Marketing e Propaganda | C89: =H89+I89+J89 -> 2535 | D89: =IFERROR(C89/$C$27,"0,00%") -> 0.0024408113 | E89: 0.0010458541 | F89: =IF(Fluxo_de_Caixa_Janeiro34591171012151619[[#This Row],[% ACUMULADO DEZ/2026]]<=Fluxo_de_Caixa_Janeiro34591171012151619[[#This Row],[% Acum no Ano Comparação]],"Verd","Fals") -> Fals | H89: 2535
B90: =Fluxo_de_Caixa_Janeiro[[#This Row],[Fluxo de Caixa 2026 CTR]] -> 3.1.02. Promoções e Eventos(Brindes/Café da Manhã p clientes/etc) | C90: =H90+I90+J90 -> 0 | D90: =IFERROR(C90/$C$27,"0,00%") -> 0 | E90: 0.0011119768 | F90: =IF(Fluxo_de_Caixa_Janeiro34591171012151619[[#This Row],[% ACUMULADO DEZ/2026]]<=Fluxo_de_Caixa_Janeiro34591171012151619[[#This Row],[% Acum no Ano Comparação]],"Verd","Fals") -> Fals
B91: =Fluxo_de_Caixa_Janeiro[[#This Row],[Fluxo de Caixa 2026 CTR]] -> 3.1.03. Sacolas e Embalagens | C91: =H91+I91+J91 -> 0 | D91: =IFERROR(C91/$C$27,"0,00%") -> 0 | E91: 0.00064528103 | F91: =IF(Fluxo_de_Caixa_Janeiro34591171012151619[[#This Row],[% ACUMULADO DEZ/2026]]<=Fluxo_de_Caixa_Janeiro34591171012151619[[#This Row],[% Acum no Ano Comparação]],"Verd","Fals") -> Fals
B92: =Fluxo_de_Caixa_Janeiro[[#This Row],[Fluxo de Caixa 2026 CTR]] -> 3.1.04.DIARIAS E DESPESAS COM VENDEDOR (passagem ônibus, hotel. Etc) | C92: =H92+I92+J92 -> 0 | D92: =IFERROR(C92/$C$27,"0,00%") -> 0 | E92: 8.9915448e-05 | F92: =IF(Fluxo_de_Caixa_Janeiro34591171012151619[[#This Row],[% ACUMULADO DEZ/2026]]<=Fluxo_de_Caixa_Janeiro34591171012151619[[#This Row],[% Acum no Ano Comparação]],"Verd","Fals") -> Fals
B93: =Fluxo_de_Caixa_Janeiro[[#This Row],[Fluxo de Caixa 2026 CTR]] -> 3.1.05. Comissão Representente Comercial | C93: =H93+I93+J93 -> 57815.85 | D93: =IFERROR(C93/$C$27,"0,00%") -> 0.055667685 | E93: 0.012983049 | F93: =IF(Fluxo_de_Caixa_Janeiro34591171012151619[[#This Row],[% ACUMULADO DEZ/2026]]<=Fluxo_de_Caixa_Janeiro34591171012151619[[#This Row],[% Acum no Ano Comparação]],"Verd","Fals") -> Fals | H93: 57815.85
B94: =Fluxo_de_Caixa_Janeiro[[#This Row],[Fluxo de Caixa 2026 CTR]] -> 3.1.06. Frete com entrega de vendas | C94: =H94+I94+J94 -> 5208.04 | D94: =IFERROR(C94/$C$27,"0,00%") -> 0.0050145337 | E94: 0.013626993 | F94: =IF(Fluxo_de_Caixa_Janeiro34591171012151619[[#This Row],[% ACUMULADO DEZ/2026]]<=Fluxo_de_Caixa_Janeiro34591171012151619[[#This Row],[% Acum no Ano Comparação]],"Verd","Fals") -> Fals | H94: 3528.04 | I94: 160 | J94: 1520
B95: =Fluxo_de_Caixa_Janeiro[[#This Row],[Fluxo de Caixa 2026 CTR]] -> 3.1.07. TAXAS C/ CART CRÉD/DÉBIT | C95: =H95+I95+J95 -> 8832.21 | D95: =IFERROR(C95/$C$27,"0,00%") -> 0.0085040466 | E95: 0.0013544651 | F95: =IF(Fluxo_de_Caixa_Janeiro34591171012151619[[#This Row],[% ACUMULADO DEZ/2026]]<=Fluxo_de_Caixa_Janeiro34591171012151619[[#This Row],[% Acum no Ano Comparação]],"Verd","Fals") -> Fals | H95: 5054.39 | I95: 10.5 | J95: 3767.32
B96: =Fluxo_de_Caixa_Janeiro[[#This Row],[Fluxo de Caixa 2026 CTR]] -> 3.1.08. Serviço Motoboy Entrega Vendas | C96: =H96+I96+J96 -> 0 | D96: =IFERROR(C96/$C$27,"0,00%") -> 0 | E96: 0.0013544651 | F96: =IF(Fluxo_de_Caixa_Janeiro34591171012151619[[#This Row],[% ACUMULADO DEZ/2026]]<=Fluxo_de_Caixa_Janeiro34591171012151619[[#This Row],[% Acum no Ano Comparação]],"Verd","Fals") -> Fals
B97: =Fluxo_de_Caixa_Janeiro[[#This Row],[Fluxo de Caixa 2026 CTR]] -> 3.1.09. PGTO DISTRATO REPRES COMERCIAL | C97: =H97+I97+J97 -> 0 | D97: =IFERROR(C97/$C$27,"0,00%") -> 0 | E97: 0.0013544651 | F97: =IF(Fluxo_de_Caixa_Janeiro34591171012151619[[#This Row],[% ACUMULADO DEZ/2026]]<=Fluxo_de_Caixa_Janeiro34591171012151619[[#This Row],[% Acum no Ano Comparação]],"Verd","Fals") -> Fals
B98: =Fluxo_de_Caixa_Janeiro[[#This Row],[Fluxo de Caixa 2026 CTR]] -> 3.1.10. TARIFA PIX RECEBIDO | C98: =H98+I98+J98 -> 57 | D98: =IFERROR(C98/$C$27,"0,00%") -> 5.4882148e-05 | E98: 0.0013544651 | F98: =IF(Fluxo_de_Caixa_Janeiro34591171012151619[[#This Row],[% ACUMULADO DEZ/2026]]<=Fluxo_de_Caixa_Janeiro34591171012151619[[#This Row],[% Acum no Ano Comparação]],"Verd","Fals") -> Fals | H98: 57
B99: =Fluxo_de_Caixa_Janeiro[[#This Row],[Fluxo de Caixa 2026 CTR]] -> 0 | D99: =IFERROR(C99/$C$27,"0,00%") -> 0 | E99: =#REF! -> #REF! | F99: =IF(Fluxo_de_Caixa_Janeiro34591171012151619[[#This Row],[% ACUMULADO DEZ/2026]]<=Fluxo_de_Caixa_Janeiro34591171012151619[[#This Row],[% Acum no Ano Comparação]],"Verd","Fals") -> #REF!
A100: 3.2. FUNCIONÁRIO | B100: =Fluxo_de_Caixa_Janeiro[[#This Row],[Fluxo de Caixa 2026 CTR]] -> 3.2. DESPESA COM FUNCIONÁRIO | C100: =-SUBTOTAL(109,C101:C130) -> -65616.5 | D100: =-IFERROR(C100/$C$27,"0,00") -> 0.063178499 | E100: 0.067282262 | F100: =IF(Fluxo_de_Caixa_Janeiro34591171012151619[[#This Row],[% ACUMULADO DEZ/2026]]<=Fluxo_de_Caixa_Janeiro34591171012151619[[#This Row],[% Acum no Ano Comparação]],"Verd","Fals") -> Verd | H100: =-SUBTOTAL(109,H101:H130) -> -65258.7 | I100: =-SUBTOTAL(109,I101:I130) -> -357.8 | J100: =-SUBTOTAL(109,J101:J130) -> 0
...

Sheet MARÇO
B1: Fluxo de Caixa 2026 CTR | C1: Março | D1: % ACUMULADO MAR/2026 | E1: % Acum no Ano Comparação | H1: Matriz | I1: Filia Porto | J1: Filia Palmas
A2: Disponíveis Nas Contas Movimento | B2: =Fluxo_de_Caixa_Janeiro[[#This Row],[Fluxo de Caixa 2026 CTR]] -> Disponíveis Nas Contas Movimento inicial | C2: =SUBTOTAL(109,C3:C26) -> 8957.59 | D2: =SUM(D3:D26) -> 1
B3: =Fluxo_de_Caixa_Janeiro[[#This Row],[Fluxo de Caixa 2026 CTR]] -> 1.0 - TESOURARIA MATRIZ PALMAS | C3: =FEVEREIRO!C337 -> 337.58 | D3: =IF(C3=0,"0,00%",C3/$C$2) -> 0.037686476 | G3: 1
B4: =Fluxo_de_Caixa_Janeiro[[#This Row],[Fluxo de Caixa 2026 CTR]] -> 1.1 - BANCO DO BRASIL C.C.60409-7 MATRIZ | C4: =FEVEREIRO!C338 -> 55.77 | D4: =IF(C4=0,"0,00%",C4/$C$2) -> 0.006226005 | E4: =#REF! -> #REF! | G4: 2
B5: =Fluxo_de_Caixa_Janeiro[[#This Row],[Fluxo de Caixa 2026 CTR]] -> 0 | C5: =FEVEREIRO!C339 -> 0 | D5: =IF(C5=0,"0,00%",C5/$C$2) -> 0,00% | E5: =#REF! -> #REF! | G5: 3
B6: =Fluxo_de_Caixa_Janeiro[[#This Row],[Fluxo de Caixa 2026 CTR]] -> 1.2-BRADESCO 15232-3 MATRIZ | C6: =FEVEREIRO!C340 -> 25.97 | D6: =IF(C6=0,"0,00%",C6/$C$2) -> 0.0028992173 | E6: =#REF! -> #REF! | G6: 3
B7: =Fluxo_de_Caixa_Janeiro[[#This Row],[Fluxo de Caixa 2026 CTR]] -> 0 | C7: =FEVEREIRO!C341 -> 0 | D7: =IF(C7=0,"0,00%",C7/$C$2) -> 0,00% | E7: =#REF! -> #REF! | G7: 5
B8: =Fluxo_de_Caixa_Janeiro[[#This Row],[Fluxo de Caixa 2026 CTR]] -> 1.3 - BANCO STONE MATRIZ C.C 40256726-7 | C8: =FEVEREIRO!C342 -> 0 | D8: =IF(C8=0,"0,00%",C8/$C$2) -> 0,00% | E8: =#REF! -> #REF! | G8: 4
B9: =Fluxo_de_Caixa_Janeiro[[#This Row],[Fluxo de Caixa 2026 CTR]] -> 1.4 - BANCO DA AMAZONIA 071730-7 MATRIZ | C9: =FEVEREIRO!C343 -> 1900.51 | D9: =IF(C9=0,"0,00%",C9/$C$2) -> 0.21216756 | E9: =#REF! -> #REF! | G9: 7
B10: =Fluxo_de_Caixa_Janeiro[[#This Row],[Fluxo de Caixa 2026 CTR]] -> 1.4.1.INVESTIMENTO CDBORE RCP TXFL | C10: =FEVEREIRO!C344 -> 0 | D10: =IF(C10=0,"0,00%",C10/$C$2) -> 0,00% | E10: =#REF! -> #REF! | G10: 5
B11: =Fluxo_de_Caixa_Janeiro[[#This Row],[Fluxo de Caixa 2026 CTR]] -> 1.5 - ITAU C.C.98671-6 MATRIZ | C11: =FEVEREIRO!C345 -> 33831.3 | D11: =IF(C11=0,"0,00%",C11/$C$2) -> 3.7768306 | E11: =#REF! -> #REF! | G11: 6
B12: =Fluxo_de_Caixa_Janeiro[[#This Row],[Fluxo de Caixa 2026 CTR]] -> 1.5.03. ITAU C.C 83290-2 GARANTIDA | C12: =FEVEREIRO!C346 -> 5399.76 | D12: =IF(C12=0,"0,00%",C12/$C$2) -> 0.60281393 | E12: =#REF! -> #REF! | G12: 7
B13: =Fluxo_de_Caixa_Janeiro[[#This Row],[Fluxo de Caixa 2026 CTR]] -> 1.9 - CONTA PERDA/ROUBO/BONIFICAÇÃO E DOAÇÃO | C13: =FEVEREIRO!C347 -> -20953.13 | D13: =IF(C13=0,"0,00%",C13/$C$2) -> -2.3391481 | G13: 8
B14: =Fluxo_de_Caixa_Janeiro[[#This Row],[Fluxo de Caixa 2026 CTR]] -> 0 | C14: =FEVEREIRO!C348 -> 0 | D14: =IF(C14=0,"0,00%",C14/$C$2) -> 0,00% | G14: 12
B15: =Fluxo_de_Caixa_Janeiro[[#This Row],[Fluxo de Caixa 2026 CTR]] -> 2.1 - BANCO DO BRASIL C.C.60638-3 FILIAL PALMAS | C15: =FEVEREIRO!C349 -> 65.56 | D15: =IF(C15=0,"0,00%",C15/$C$2) -> 0.0073189329 | G15: 9
B16: =Fluxo_de_Caixa_Janeiro[[#This Row],[Fluxo de Caixa 2026 CTR]] -> 0 | C16: =FEVEREIRO!C350 -> 0 | D16: =IF(C16=0,"0,00%",C16/$C$2) -> 0,00% | G16: 14
B17: =Fluxo_de_Caixa_Janeiro[[#This Row],[Fluxo de Caixa 2026 CTR]] -> 0 | C17: =FEVEREIRO!C351 -> 0 | D17: =IF(C17=0,"0,00%",C17/$C$2) -> 0,00% | G17: 15
B18: =Fluxo_de_Caixa_Janeiro[[#This Row],[Fluxo de Caixa 2026 CTR]] -> 2.4 - ITAU C.C.98669-0 FILIAL PALMAS | C18: =FEVEREIRO!C352 -> 37.73 | D18: =IF(C18=0,"0,00%",C18/$C$2) -> 0.0042120704 | G18: 10
B19: =Fluxo_de_Caixa_Janeiro[[#This Row],[Fluxo de Caixa 2026 CTR]] -> 2.9 - CONTA PERDA/ROUBO E BONIFICAÇÃO FILIAL | C19: =FEVEREIRO!C353 -> -8598.58 | D19: =IF(C19=0,"0,00%",C19/$C$2) -> -0.95992114 | G19: 11
B20: =Fluxo_de_Caixa_Janeiro[[#This Row],[Fluxo de Caixa 2026 CTR]] -> 4.0 - TESOURARIA FILIAL PORTO | C20: =FEVEREIRO!C354 -> 1327.43 | D20: =IF(C20=0,"0,00%",C20/$C$2) -> 0.14819053 | G20: 12
B21: =Fluxo_de_Caixa_Janeiro[[#This Row],[Fluxo de Caixa 2026 CTR]] -> 4.1 - BANCO DO BRASIL C.C.61105-0 FILIAL PORTO | C21: =FEVEREIRO!C355 -> 111.93 | D21: =IF(C21=0,"0,00%",C21/$C$2) -> 0.012495548 | G21: 13
B22: =Fluxo_de_Caixa_Janeiro[[#This Row],[Fluxo de Caixa 2026 CTR]] -> 0 | C22: =FEVEREIRO!C356 -> 0 | D22: =IF(C22=0,"0,00%",C22/$C$2) -> 0,00% | G22: 20
B23: =Fluxo_de_Caixa_Janeiro[[#This Row],[Fluxo de Caixa 2026 CTR]] -> 4.4 - MERCADO PAGO PIX FILIAL PORTO | C23: =FEVEREIRO!C357 -> 22539.57 | D23: =IF(C23=0,"0,00%",C23/$C$2) -> 2.5162538 | G23: 14
B24: =Fluxo_de_Caixa_Janeiro[[#This Row],[Fluxo de Caixa 2026 CTR]] -> 4.9 - CONTA PERDA/ROUBO E BONIFICAÇÃO FILIAL | C24: =FEVEREIRO!C358 -> -29071.86 | D24: =IF(C24=0,"0,00%",C24/$C$2) -> -3.2455002 | G24: 15
... B26: =Fluxo_de_Caixa_Janeiro[[#This Row],[Fluxo de Caixa 2026 CTR]] -> 0 | C26: =FEVEREIRO!C360 -> 0 | D26: =IF(C26=0,"0,00%",C26/$C$2) -> 0,00% | G26: 24
B27: =Fluxo_de_Caixa_Janeiro[[#This Row],[Fluxo de Caixa 2026 CTR]] -> Total Receitas Operacionais / Vendas | C27: =SUBTOTAL(109,C29:C51) -> 1087750 | D27: =IFERROR(C27/C332,"") -> 0.56707334 | E27: 0.88526119 | H27: =H28+I28 -> 516141.03
A28: 1.1. Receita com Vendas | B28: =Fluxo_de_Caixa_Janeiro[[#This Row],[Fluxo de Caixa 2026 CTR]] -> 1.1. Receita com Vendas | C28: =SUBTOTAL(109,C29:C47) -> 1087750 | D28: =SUM(D29:D47) -> 0.56707334 | E28: 0.88251933 | H28: =SUM(H29:H36) -> 47356.86 | I28: =SUM(I29:I36) -> 468784.17 | J28: =SUM(J29:J36) -> 571608.96
B29: =Fluxo_de_Caixa_Janeiro[[#This Row],[Fluxo de Caixa 2026 CTR]] -> 1.1.01. Receita em Dinheiro | C29: =H29+I29+J29 -> 2754.35 | D29: =IF(C29=0,"0,00%",C29/$C$332) -> 0.0014359168 | E29: 0.079252981 | F29: =IF(Fluxo_de_Caixa_Janeiro34591171012151619[[#This Row],[% ACUMULADO DEZ/2026]]>=Fluxo_de_Caixa_Janeiro34591171012151619[[#This Row],[% Acum no Ano Comparação]],"Verd","Fals") -> Verd | H29: 0 | I29: 2262.35 | J29: 492
B30: =Fluxo_de_Caixa_Janeiro[[#This Row],[Fluxo de Caixa 2026 CTR]] -> 1.1.01. Receita em Cartão (Crédito e Débito) | C30: =H30+I30+J30 -> 110371.17 | D30: =IF(C30=0,"0,00%",C30/$C$332) -> 0.057539461 | E30: 0.092740536 | F30: =IF(Fluxo_de_Caixa_Janeiro34591171012151619[[#This Row],[% ACUMULADO DEZ/2026]]>=Fluxo_de_Caixa_Janeiro34591171012151619[[#This Row],[% Acum no Ano Comparação]],"Verd","Fals") -> Verd | H30: 22.79 | I30: 41662.34 | J30: 68686.04
B31: =Fluxo_de_Caixa_Janeiro[[#This Row],[Fluxo de Caixa 2026 CTR]] -> 1.1.01. Receita de Cheque A Vista | C31: =H31+I31+J31 -> 0 | D31: =IF(C31=0,"0,00%",C31/$C$332) -> 0,00% | E31: 0.00028628486 | F31: =IF(Fluxo_de_Caixa_Janeiro34591171012151619[[#This Row],[% ACUMULADO DEZ/2026]]>=Fluxo_de_Caixa_Janeiro34591171012151619[[#This Row],[% Acum no Ano Comparação]],"Verd","Fals") -> Verd | H31: 0 | I31: 0 | J31: 0
B32: =Fluxo_de_Caixa_Janeiro[[#This Row],[Fluxo de Caixa 2026 CTR]] -> 1.1.01. Receita de Cheque Pré | C32: =H32+I32+J32 -> 0 | D32: =IF(C32=0,"0,00%",C32/$C$332) -> 0,00% | E32: 0.0063111634 | F32: =IF(Fluxo_de_Caixa_Janeiro34591171012151619[[#This Row],[% ACUMULADO DEZ/2026]]>=Fluxo_de_Caixa_Janeiro34591171012151619[[#This Row],[% Acum no Ano Comparação]],"Verd","Fals") -> Verd | H32: 0 | I32: 0 | J32: 0
B33: =Fluxo_de_Caixa_Janeiro[[#This Row],[Fluxo de Caixa 2026 CTR]] -> 1.1.01. Recebimento de Carteira (Notinha) | C33: =H33+I33+J33 -> 190040.35 | D33: =IF(C33=0,"0,00%",C33/$C$332) -> 0.099073148 | E33: 0.0001318638 | F33: =IF(Fluxo_de_Caixa_Janeiro34591171012151619[[#This Row],[% ACUMULADO DEZ/2026]]>=Fluxo_de_Caixa_Janeiro34591171012151619[[#This Row],[% Acum no Ano Comparação]],"Verd","Fals") -> Verd | G33: =C361 -> 220.66 | H33: 0 | I33: 158995.12 | J33: 31045.23
B34: =Fluxo_de_Caixa_Janeiro[[#This Row],[Fluxo de Caixa 2026 CTR]] -> 1.1.01. Recebimento de Boletos | C34: =H34+I34+J34 -> 395244.86 | D34: =IF(C34=0,"0,00%",C34/$C$332) -> 0.20605178 | E34: 0.66745712 | F34: =IF(Fluxo_de_Caixa_Janeiro34591171012151619[[#This Row],[% ACUMULADO DEZ/2026]]>=Fluxo_de_Caixa_Janeiro34591171012151619[[#This Row],[% Acum no Ano Comparação]],"Verd","Fals") -> Verd | H34: 46254.07 | I34: 122115.09 | J34: 226875.7
B35: =Fluxo_de_Caixa_Janeiro[[#This Row],[Fluxo de Caixa 2026 CTR]] -> 1.1.01. Recebimento em Depósito e Dep. PIX | C35: =H35+I35+J35 -> 389339.26 | D35: =IF(C35=0,"0,00%",C35/$C$332) -> 0.20297303 | E35: 0.036171198 | F35: =IF(Fluxo_de_Caixa_Janeiro34591171012151619[[#This Row],[% ACUMULADO DEZ/2026]]>=Fluxo_de_Caixa_Janeiro34591171012151619[[#This Row],[% Acum no Ano Comparação]],"Verd","Fals") -> Verd | H35: 1080 | I35: =143749.27 -> 143749.27 | J35: 244509.99
B36: =Fluxo_de_Caixa_Janeiro[[#This Row],[Fluxo de Caixa 2026 CTR]] -> 1.1.02. Recebimento Cheque Devolvido | C36: =H36+I36+J36 -> 0 | D36: =IF(C36=0,"0,00%",C36/$C$332) -> 0,00% | E36: 0.00016817802 | F36: =IF(Fluxo_de_Caixa_Janeiro34591171012151619[[#This Row],[% ACUMULADO DEZ/2026]]>=Fluxo_de_Caixa_Janeiro34591171012151619[[#This Row],[% Acum no Ano Comparação]],"Verd","Fals") -> Verd
B37: =Fluxo_de_Caixa_Janeiro[[#This Row],[Fluxo de Caixa 2026 CTR]] -> 0 | D37: =IF(C37=0,"0,00%",C37/$C$332) -> 0,00% | E37: =#REF! -> #REF! | F37: =IF(Fluxo_de_Caixa_Janeiro34591171012151619[[#This Row],[% ACUMULADO DEZ/2026]]>=Fluxo_de_Caixa_Janeiro34591171012151619[[#This Row],[% Acum no Ano Comparação]],"Verd","Fals") -> #REF!
B38: =Fluxo_de_Caixa_Janeiro[[#This Row],[Fluxo de Caixa 2026 CTR]] -> 0 | D38: =IF(C38=0,"0,00%",C38/$C$332) -> 0,00% | E38: =#REF! -> #REF! | F38: =IF(Fluxo_de_Caixa_Janeiro34591171012151619[[#This Row],[% ACUMULADO DEZ/2026]]>=Fluxo_de_Caixa_Janeiro34591171012151619[[#This Row],[% Acum no Ano Comparação]],"Verd","Fals") -> #REF!
B39: =Fluxo_de_Caixa_Janeiro[[#This Row],[Fluxo de Caixa 2026 CTR]] -> 0 | D39: =IF(C39=0,"0,00%",C39/$C$332) -> 0,00% | E39: =#REF! -> #REF! | F39: =IF(Fluxo_de_Caixa_Janeiro34591171012151619[[#This Row],[% ACUMULADO DEZ/2026]]>=Fluxo_de_Caixa_Janeiro34591171012151619[[#This Row],[% Acum no Ano Comparação]],"Verd","Fals") -> #REF!
B40: =Fluxo_de_Caixa_Janeiro[[#This Row],[Fluxo de Caixa 2026 CTR]] -> 0 | D40: =IF(C40=0,"0,00%",C40/$C$332) -> 0,00% | E40: =#REF! -> #REF! | F40: =IF(Fluxo_de_Caixa_Janeiro34591171012151619[[#This Row],[% ACUMULADO DEZ/2026]]>=Fluxo_de_Caixa_Janeiro34591171012151619[[#This Row],[% Acum no Ano Comparação]],"Verd","Fals") -> #REF!
B41: =Fluxo_de_Caixa_Janeiro[[#This Row],[Fluxo de Caixa 2026 CTR]] -> 0 | D41: =IF(C41=0,"0,00%",C41/$C$332) -> 0,00% | E41: =#REF! -> #REF! | F41: =IF(Fluxo_de_Caixa_Janeiro34591171012151619[[#This Row],[% ACUMULADO DEZ/2026]]>=Fluxo_de_Caixa_Janeiro34591171012151619[[#This Row],[% Acum no Ano Comparação]],"Verd","Fals") -> #REF!
B42: =Fluxo_de_Caixa_Janeiro[[#This Row],[Fluxo de Caixa 2026 CTR]] -> 0 | D42: =IF(C42=0,"0,00%",C42/$C$332) -> 0,00% | E42: =#REF! -> #REF! | F42: =IF(Fluxo_de_Caixa_Janeiro34591171012151619[[#This Row],[% ACUMULADO DEZ/2026]]>=Fluxo_de_Caixa_Janeiro34591171012151619[[#This Row],[% Acum no Ano Comparação]],"Verd","Fals") -> #REF!
B43: =Fluxo_de_Caixa_Janeiro[[#This Row],[Fluxo de Caixa 2026 CTR]] -> 0 | D43: =IF(C43=0,"0,00%",C43/$C$332) -> 0,00% | E43: =#REF! -> #REF! | F43: =IF(Fluxo_de_Caixa_Janeiro34591171012151619[[#This Row],[% ACUMULADO DEZ/2026]]>=Fluxo_de_Caixa_Janeiro34591171012151619[[#This Row],[% Acum no Ano Comparação]],"Verd","Fals") -> #REF!
B44: =Fluxo_de_Caixa_Janeiro[[#This Row],[Fluxo de Caixa 2026 CTR]] -> 0 | D44: =IF(C44=0,"0,00%",C44/$C$332) -> 0,00% | E44: =#REF! -> #REF! | F44: =IF(Fluxo_de_Caixa_Janeiro34591171012151619[[#This Row],[% ACUMULADO DEZ/2026]]>=Fluxo_de_Caixa_Janeiro34591171012151619[[#This Row],[% Acum no Ano Comparação]],"Verd","Fals") -> #REF!
B45: =Fluxo_de_Caixa_Janeiro[[#This Row],[Fluxo de Caixa 2026 CTR]] -> 0 | D45: =IF(C45=0,"0,00%",C45/$C$332) -> 0,00% | E45: =#REF! -> #REF! | F45: =IF(Fluxo_de_Caixa_Janeiro34591171012151619[[#This Row],[% ACUMULADO DEZ/2026]]>=Fluxo_de_Caixa_Janeiro34591171012151619[[#This Row],[% Acum no Ano Comparação]],"Verd","Fals") -> #REF!
B46: =Fluxo_de_Caixa_Janeiro[[#This Row],[Fluxo de Caixa 2026 CTR]] -> 0 | C46: 0 | D46: =IF(C46=0,"0,00%",C46/$C$332) -> 0,00% | E46: =#REF! -> #REF! | F46: =IF(Fluxo_de_Caixa_Janeiro34591171012151619[[#This Row],[% ACUMULADO DEZ/2026]]>=Fluxo_de_Caixa_Janeiro34591171012151619[[#This Row],[% Acum no Ano Comparação]],"Verd","Fals") -> #REF!
B47: =Fluxo_de_Caixa_Janeiro[[#This Row],[Fluxo de Caixa 2026 CTR]] -> 0 | D47: =IF(C47=0,"0,00%",C47/$C$332) -> 0,00% | E47: =#REF! -> #REF! | F47: =IF(Fluxo_de_Caixa_Janeiro34591171012151619[[#This Row],[% ACUMULADO DEZ/2026]]>=Fluxo_de_Caixa_Janeiro34591171012151619[[#This Row],[% Acum no Ano Comparação]],"Verd","Fals") -> #REF!
A48: 1.5. Receita de Garantias | B48: =Fluxo_de_Caixa_Janeiro[[#This Row],[Fluxo de Caixa 2026 CTR]] -> 1.5. Receita de Garantias | C48: =+SUBTOTAL(109,C49:C51) -> 0 | D48: =SUM(D49:D51) -> 0 | E48: 0.0027418655 | H48: =SUM(H49:H51) -> 0 | I48: =SUM(I49:I51) -> 0 | J48: =SUM(J49:J51) -> 0
B49: =Fluxo_de_Caixa_Janeiro[[#This Row],[Fluxo de Caixa 2026 CTR]] -> 1.2.01. RECEITA EM DINHEIRO | C49: =H49+I49 -> 0 | D49: =IF(C49=0,"0,00%",C49/$C$332) -> 0,00% | E49: 0.0024323151 | F49: =IF(Fluxo_de_Caixa_Janeiro34591171012151619[[#This Row],[% ACUMULADO DEZ/2026]]>=Fluxo_de_Caixa_Janeiro34591171012151619[[#This Row],[% Acum no Ano Comparação]],"Verd","Fals") -> Verd
B50: =Fluxo_de_Caixa_Janeiro[[#This Row],[Fluxo de Caixa 2026 CTR]] -> 1.2.02. RECEITA EM MERCADORIA | C50: =H50+I50 -> 0 | D50: =IF(C50=0,"0,00%",C50/$C$332) -> 0,00% | E50: 0.00030955038 | F50: =IF(Fluxo_de_Caixa_Janeiro34591171012151619[[#This Row],[% ACUMULADO DEZ/2026]]>=Fluxo_de_Caixa_Janeiro34591171012151619[[#This Row],[% Acum no Ano Comparação]],"Verd","Fals") -> Verd
B51: =Fluxo_de_Caixa_Janeiro[[#This Row],[Fluxo de Caixa 2026 CTR]] -> 0 | C51: =H51+I51 -> 0 | D51: =IF(C51=0,"0,00%",C51/$C$332) -> 0,00% | E51: =#REF! -> #REF! | F51: =IF(Fluxo_de_Caixa_Janeiro34591171012151619[[#This Row],[% ACUMULADO DEZ/2026]]>=Fluxo_de_Caixa_Janeiro34591171012151619[[#This Row],[% Acum no Ano Comparação]],"Verd","Fals") -> #REF!
A52: 2.1. Despesa Com Custo de Aquisição | B52: =Fluxo_de_Caixa_Janeiro[[#This Row],[Fluxo de Caixa 2026 CTR]] -> 2.1. Despesa Com Custo de Aquisição | C52: =-SUBTOTAL(109,C53:C59) -> -456490.45 | D52: =-IFERROR(C52/$C$27,"0,00") -> 0.41966486 | E52: 0.7032551 | F52: =IF(Fluxo_de_Caixa_Janeiro34591171012151619[[#This Row],[% ACUMULADO DEZ/2026]]<=Fluxo_de_Caixa_Janeiro34591171012151619[[#This Row],[% Acum no Ano Comparação]],"Verd","Fals") -> Verd | H52: =-SUBTOTAL(109,H53:H59) -> -434948.8 | I52: =-SUBTOTAL(109,I53:I59) -> -21541.65 | J52: =-SUBTOTAL(109,J53:J59) -> 0
B53: =Fluxo_de_Caixa_Janeiro[[#This Row],[Fluxo de Caixa 2026 CTR]] -> 2.1.01.FORNECEDORES DE MERCADORIAS REVENDA | C53: =H53+I53+J53 -> 449846.92 | D53: =IFERROR(C53/$C$27,"0,00%") -> 0.41355727 | E53: 0.70044704 | F53: =IF(Fluxo_de_Caixa_Janeiro34591171012151619[[#This Row],[% ACUMULADO DEZ/2026]]<=Fluxo_de_Caixa_Janeiro34591171012151619[[#This Row],[% Acum no Ano Comparação]],"Verd","Fals") -> Fals | H53: 428385.27 | I53: 21461.65
B54: =Fluxo_de_Caixa_Janeiro[[#This Row],[Fluxo de Caixa 2026 CTR]] -> 2.1.02.ADIANT. FORNEC. MERCA. REVENDA | C54: =H54+I54+J54 -> 0 | D54: =IFERROR(C54/$C$27,"0,00%") -> 0 | E54: 0.0028080664 | F54: =IF(Fluxo_de_Caixa_Janeiro34591171012151619[[#This Row],[% ACUMULADO DEZ/2026]]<=Fluxo_de_Caixa_Janeiro34591171012151619[[#This Row],[% Acum no Ano Comparação]],"Verd","Fals") -> Fals
B55: =Fluxo_de_Caixa_Janeiro[[#This Row],[Fluxo de Caixa 2026 CTR]] -> 2.1.03.TRANSPORTADORA MERCA. REVENDA | C55: =H55+I55+J55 -> 6643.53 | D55: =IFERROR(C55/$C$27,"0,00%") -> 0.0061075891 | E55: 0 | F55: =IF(Fluxo_de_Caixa_Janeiro34591171012151619[[#This Row],[% ACUMULADO DEZ/2026]]<=Fluxo_de_Caixa_Janeiro34591171012151619[[#This Row],[% Acum no Ano Comparação]],"Verd","Fals") -> Fals | H55: 6563.53 | I55: 80
B56: =Fluxo_de_Caixa_Janeiro[[#This Row],[Fluxo de Caixa 2026 CTR]] -> 2.1.04.OUTROS CUSTOS DE MERC.REVENDA | C56: =H56+I56+J56 -> 0 | D56: =IFERROR(C56/$C$27,"0,00%") -> 0 | E56: =#REF! -> #REF! | F56: =IF(Fluxo_de_Caixa_Janeiro34591171012151619[[#This Row],[% ACUMULADO DEZ/2026]]<=Fluxo_de_Caixa_Janeiro34591171012151619[[#This Row],[% Acum no Ano Comparação]],"Verd","Fals") -> #REF!
B57: =Fluxo_de_Caixa_Janeiro[[#This Row],[Fluxo de Caixa 2026 CTR]] -> 2.1.05.TRANSFE DE MERCAD REVENDA MATRIZ | C57: =H57+I57+J57 -> 0 | D57: =IFERROR(C57/$C$27,"0,00%") -> 0 | E57: =#REF! -> #REF! | F57: =IF(Fluxo_de_Caixa_Janeiro34591171012151619[[#This Row],[% ACUMULADO DEZ/2026]]<=Fluxo_de_Caixa_Janeiro34591171012151619[[#This Row],[% Acum no Ano Comparação]],"Verd","Fals") -> #REF!
B58: =Fluxo_de_Caixa_Janeiro[[#This Row],[Fluxo de Caixa 2026 CTR]] -> 0 | D58: =IFERROR(C58/$C$27,"0,00%") -> 0 | E58: =#REF! -> #REF! | F58: =IF(Fluxo_de_Caixa_Janeiro34591171012151619[[#This Row],[% ACUMULADO DEZ/2026]]<=Fluxo_de_Caixa_Janeiro34591171012151619[[#This Row],[% Acum no Ano Comparação]],"Verd","Fals") -> #REF!
B59: =Fluxo_de_Caixa_Janeiro[[#This Row],[Fluxo de Caixa 2026 CTR]] -> 0 | D59: =IFERROR(C59/$C$27,"0,00%") -> 0 | E59: =#REF! -> #REF! | F59: =IF(Fluxo_de_Caixa_Janeiro34591171012151619[[#This Row],[% ACUMULADO DEZ/2026]]<=Fluxo_de_Caixa_Janeiro34591171012151619[[#This Row],[% Acum no Ano Comparação]],"Verd","Fals") -> #REF!
A60: 2.2. Inadimplência e Perdas | B60: =Fluxo_de_Caixa_Janeiro[[#This Row],[Fluxo de Caixa 2026 CTR]] -> 2.2. Inadimplência e Perdas | C60: =-SUBTOTAL(109,C61:C69) -> 0 | D60: =-IFERROR(C60/$C$27,"0,00") -> 0 | E60: 0.0013173948 | F60: =IF(Fluxo_de_Caixa_Janeiro34591171012151619[[#This Row],[% ACUMULADO DEZ/2026]]<=Fluxo_de_Caixa_Janeiro34591171012151619[[#This Row],[% Acum no Ano Comparação]],"Verd","Fals") -> Verd | H60: =-SUBTOTAL(109,H61:H69) -> 0 | I60: =-SUBTOTAL(109,I61:I69) -> 0 | J60: =-SUBTOTAL(109,J61:J69) -> 0
B61: =Fluxo_de_Caixa_Janeiro[[#This Row],[Fluxo de Caixa 2026 CTR]] -> 2.2.01.CONTAS PERDIDAS/NÃO PAGAS | C61: =H61+I61+J61 -> 0 | D61: =IFERROR(C61/$C$27,"0,00%") -> 0 | E61: 0 | F61: =IF(Fluxo_de_Caixa_Janeiro34591171012151619[[#This Row],[% ACUMULADO DEZ/2026]]<=Fluxo_de_Caixa_Janeiro34591171012151619[[#This Row],[% Acum no Ano Comparação]],"Verd","Fals") -> Fals
B62: =Fluxo_de_Caixa_Janeiro[[#This Row],[Fluxo de Caixa 2026 CTR]] -> 2.2.02.BOLETOS DESCONTADOS DEVOLVIDOS | C62: =H62+I62+J62 -> 0 | D62: =IFERROR(C62/$C$27,"0,00%") -> 0 | E62: 0 | F62: =IF(Fluxo_de_Caixa_Janeiro34591171012151619[[#This Row],[% ACUMULADO DEZ/2026]]<=Fluxo_de_Caixa_Janeiro34591171012151619[[#This Row],[% Acum no Ano Comparação]],"Verd","Fals") -> Fals
B63: =Fluxo_de_Caixa_Janeiro[[#This Row],[Fluxo de Caixa 2026 CTR]] -> 2.2.03.CHEQUES DEVOLVIDOS | C63: =H63+I63+J63 -> 0 | D63: =IFERROR(C63/$C$27,"0,00%") -> 0 | E63: 0 | F63: =IF(Fluxo_de_Caixa_Janeiro34591171012151619[[#This Row],[% ACUMULADO DEZ/2026]]<=Fluxo_de_Caixa_Janeiro34591171012151619[[#This Row],[% Acum no Ano Comparação]],"Verd","Fals") -> Fals
B64: =Fluxo_de_Caixa_Janeiro[[#This Row],[Fluxo de Caixa 2026 CTR]] -> 2.2.04.BOLETOS DESCONTADOS DEVOLVIDOS | C64: =H64+I64+J64 -> 0 | D64: =IFERROR(C64/$C$27,"0,00%") -> 0 | E64: 0.0012728671 | F64: =IF(Fluxo_de_Caixa_Janeiro34591171012151619[[#This Row],[% ACUMULADO DEZ/2026]]<=Fluxo_de_Caixa_Janeiro34591171012151619[[#This Row],[% Acum no Ano Comparação]],"Verd","Fals") -> Fals
B65: =Fluxo_de_Caixa_Janeiro[[#This Row],[Fluxo de Caixa 2026 CTR]] -> 2.2.05.PERDA, ROUBO E DETERIORAÇÃO | C65: =H65+I65+J65 -> 0 | D65: =IFERROR(C65/$C$27,"0,00%") -> 0 | E65: 4.4527688e-05 | F65: =IF(Fluxo_de_Caixa_Janeiro34591171012151619[[#This Row],[% ACUMULADO DEZ/2026]]<=Fluxo_de_Caixa_Janeiro34591171012151619[[#This Row],[% Acum no Ano Comparação]],"Verd","Fals") -> Fals
B66: =Fluxo_de_Caixa_Janeiro[[#This Row],[Fluxo de Caixa 2026 CTR]] -> 0 | C66: =H66+I66+J66 -> 0 | D66: =IFERROR(C66/$C$27,"0,00%") -> 0 | E66: =#REF! -> #REF! | F66: =IF(Fluxo_de_Caixa_Janeiro34591171012151619[[#This Row],[% ACUMULADO DEZ/2026]]<=Fluxo_de_Caixa_Janeiro34591171012151619[[#This Row],[% Acum no Ano Comparação]],"Verd","Fals") -> #REF!
B67: =Fluxo_de_Caixa_Janeiro[[#This Row],[Fluxo de Caixa 2026 CTR]] -> 0 | C67: =H67+I67+J67 -> 0 | D67: =IFERROR(C67/$C$27,"0,00%") -> 0 | E67: =#REF! -> #REF! | F67: =IF(Fluxo_de_Caixa_Janeiro34591171012151619[[#This Row],[% ACUMULADO DEZ/2026]]<=Fluxo_de_Caixa_Janeiro34591171012151619[[#This Row],[% Acum no Ano Comparação]],"Verd","Fals") -> #REF!
B68: =Fluxo_de_Caixa_Janeiro[[#This Row],[Fluxo de Caixa 2026 CTR]] -> 0 | C68: =H68+I68+J68 -> 0 | D68: =IFERROR(C68/$C$27,"0,00%") -> 0 | E68: =#REF! -> #REF! | F68: =IF(Fluxo_de_Caixa_Janeiro34591171012151619[[#This Row],[% ACUMULADO DEZ/2026]]<=Fluxo_de_Caixa_Janeiro34591171012151619[[#This Row],[% Acum no Ano Comparação]],"Verd","Fals") -> #REF!
B69: =Fluxo_de_Caixa_Janeiro[[#This Row],[Fluxo de Caixa 2026 CTR]] -> 0 | C69: =H69+I69+J69 -> 0 | D69: =IFERROR(C69/$C$27,"0,00%") -> 0 | E69: =#REF! -> #REF! | F69: =IF(Fluxo_de_Caixa_Janeiro34591171012151619[[#This Row],[% ACUMULADO DEZ/2026]]<=Fluxo_de_Caixa_Janeiro34591171012151619[[#This Row],[% Acum no Ano Comparação]],"Verd","Fals") -> #REF!
A70: 2.3. Impostos | B70: =Fluxo_de_Caixa_Janeiro[[#This Row],[Fluxo de Caixa 2026 CTR]] -> 2.3. Impostos | C70: =-SUBTOTAL(109,C71:C84) -> -73559.85 | D70: =-IFERROR(C70/$C$27,"0,00") -> 0.067625696 | E70: 0.12754151 | F70: =IF(Fluxo_de_Caixa_Janeiro34591171012151619[[#This Row],[% ACUMULADO DEZ/2026]]<=Fluxo_de_Caixa_Janeiro34591171012151619[[#This Row],[% Acum no Ano Comparação]],"Verd","Fals") -> Verd | H70: =-SUBTOTAL(109,H71:H84) -> -40855.68 | I70: =-SUBTOTAL(109,I71:I84) -> -23183.71 | J70: =-SUBTOTAL(109,J71:J84) -> -9520.46
B71: =Fluxo_de_Caixa_Janeiro[[#This Row],[Fluxo de Caixa 2026 CTR]] -> 0 | D71: =IFERROR(C71/$C$27,"0,00%") -> 0 | E71: 0.0010503863 | F71: =IF(Fluxo_de_Caixa_Janeiro34591171012151619[[#This Row],[% ACUMULADO DEZ/2026]]<=Fluxo_de_Caixa_Janeiro34591171012151619[[#This Row],[% Acum no Ano Comparação]],"Verd","Fals") -> Fals
B72: =Fluxo_de_Caixa_Janeiro[[#This Row],[Fluxo de Caixa 2026 CTR]] -> 2.3.02.IRPJ (SE ESTIVER NO CMV) | C72: =H72+I72+J72 -> 0 | D72: =IFERROR(C72/$C$27,"0,00%") -> 0 | E72: 0.00062053498 | F72: =IF(Fluxo_de_Caixa_Janeiro34591171012151619[[#This Row],[% ACUMULADO DEZ/2026]]<=Fluxo_de_Caixa_Janeiro34591171012151619[[#This Row],[% Acum no Ano Comparação]],"Verd","Fals") -> Fals | H72: 0
B73: =Fluxo_de_Caixa_Janeiro[[#This Row],[Fluxo de Caixa 2026 CTR]] -> 2.3.03.CSSL (SE ESTIVER NO CMV) | C73: =H73+I73+J73 -> 0 | D73: =IFERROR(C73/$C$27,"0,00%") -> 0 | E73: 0.003344374 | F73: =IF(Fluxo_de_Caixa_Janeiro34591171012151619[[#This Row],[% ACUMULADO DEZ/2026]]<=Fluxo_de_Caixa_Janeiro34591171012151619[[#This Row],[% Acum no Ano Comparação]],"Verd","Fals") -> Fals | H73: 0
B74: =Fluxo_de_Caixa_Janeiro[[#This Row],[Fluxo de Caixa 2026 CTR]] -> 2.3.04.COFINS (SE ESTIVER NO CMV) | C74: =H74+I74+J74 -> 0 | D74: =IFERROR(C74/$C$27,"0,00%") -> 0 | E74: 0.00072605477 | F74: =IF(Fluxo_de_Caixa_Janeiro34591171012151619[[#This Row],[% ACUMULADO DEZ/2026]]<=Fluxo_de_Caixa_Janeiro34591171012151619[[#This Row],[% Acum no Ano Comparação]],"Verd","Fals") -> Fals | H74: 0
B75: =Fluxo_de_Caixa_Janeiro[[#This Row],[Fluxo de Caixa 2026 CTR]] -> 2.3.05.PIS (SE ESTIVER NO CMV) | C75: =H75+I75+J75 -> 0 | D75: =IFERROR(C75/$C$27,"0,00%") -> 0 | E75: 0.051721948 | F75: =IF(Fluxo_de_Caixa_Janeiro34591171012151619[[#This Row],[% ACUMULADO DEZ/2026]]<=Fluxo_de_Caixa_Janeiro34591171012151619[[#This Row],[% Acum no Ano Comparação]],"Verd","Fals") -> Fals | H75: 0
B76: =Fluxo_de_Caixa_Janeiro[[#This Row],[Fluxo de Caixa 2026 CTR]] -> 2.3.06.ICMS – Normal (SE ESTIVER NO CMV) | C76: =H76+I76+J76 -> 43499.63 | D76: =IFERROR(C76/$C$27,"0,00%") -> 0.039990467 | E76: 0.067027605 | F76: =IF(Fluxo_de_Caixa_Janeiro34591171012151619[[#This Row],[% ACUMULADO DEZ/2026]]<=Fluxo_de_Caixa_Janeiro34591171012151619[[#This Row],[% Acum no Ano Comparação]],"Verd","Fals") -> Fals | H76: 11456.54 | I76: 23183.71 | J76: 8859.38
B77: =Fluxo_de_Caixa_Janeiro[[#This Row],[Fluxo de Caixa 2026 CTR]] -> 2.3.07. SUBSTITUIÇÃO TRIBUTARIA SAÍDA (TARE) | C77: =H77+I77+J77 -> 14279.93 | D77: =IFERROR(C77/$C$27,"0,00%") -> 0.013127952 | E77: 0.0030506108 | F77: =IF(Fluxo_de_Caixa_Janeiro34591171012151619[[#This Row],[% ACUMULADO DEZ/2026]]<=Fluxo_de_Caixa_Janeiro34591171012151619[[#This Row],[% Acum no Ano Comparação]],"Verd","Fals") -> Fals | H77: 14279.93
B78: =Fluxo_de_Caixa_Janeiro[[#This Row],[Fluxo de Caixa 2026 CTR]] -> 2.3.08.SUBSTITUIÇÃO TRIBUTÁRIA NA ENTRADA | C78: =H78+I78+J78 -> 0 | D78: =IFERROR(C78/$C$27,"0,00%") -> 0 | E78: =#REF! -> #REF! | F78: =IF(Fluxo_de_Caixa_Janeiro34591171012151619[[#This Row],[% ACUMULADO DEZ/2026]]<=Fluxo_de_Caixa_Janeiro34591171012151619[[#This Row],[% Acum no Ano Comparação]],"Verd","Fals") -> #REF!
B79: =Fluxo_de_Caixa_Janeiro[[#This Row],[Fluxo de Caixa 2026 CTR]] -> 2.3.09.FUNDO DESENVOLVIMENTO ECONOMICO (TARE) | C79: =H79+I79+J79 -> 163.42 | D79: =IFERROR(C79/$C$27,"0,00%") -> 0.00015023673 | E79: =#REF! -> #REF! | F79: =IF(Fluxo_de_Caixa_Janeiro34591171012151619[[#This Row],[% ACUMULADO DEZ/2026]]<=Fluxo_de_Caixa_Janeiro34591171012151619[[#This Row],[% Acum no Ano Comparação]],"Verd","Fals") -> #REF! | H79: 163.42
B80: =Fluxo_de_Caixa_Janeiro[[#This Row],[Fluxo de Caixa 2026 CTR]] -> 0 | C80: =H80+I80+J80 -> 0 | D80: =IFERROR(C80/$C$27,"0,00%") -> 0 | E80: =#REF! -> #REF! | F80: =IF(Fluxo_de_Caixa_Janeiro34591171012151619[[#This Row],[% ACUMULADO DEZ/2026]]<=Fluxo_de_Caixa_Janeiro34591171012151619[[#This Row],[% Acum no Ano Comparação]],"Verd","Fals") -> #REF!
B81: =Fluxo_de_Caixa_Janeiro[[#This Row],[Fluxo de Caixa 2026 CTR]] -> 0 | C81: =H81+I81+J81 -> 0 | D81: =IFERROR(C81/$C$27,"0,00%") -> 0 | E81: =#REF! -> #REF! | F81: =IF(Fluxo_de_Caixa_Janeiro34591171012151619[[#This Row],[% ACUMULADO DEZ/2026]]<=Fluxo_de_Caixa_Janeiro34591171012151619[[#This Row],[% Acum no Ano Comparação]],"Verd","Fals") -> #REF!
B82: =Fluxo_de_Caixa_Janeiro[[#This Row],[Fluxo de Caixa 2026 CTR]] -> 2.3.11. Impostos Parcelado | C82: =H82+I82+J82 -> 15616.87 | D82: =IFERROR(C82/$C$27,"0,00%") -> 0.01435704 | E82: =#REF! -> #REF! | F82: =IF(Fluxo_de_Caixa_Janeiro34591171012151619[[#This Row],[% ACUMULADO DEZ/2026]]<=Fluxo_de_Caixa_Janeiro34591171012151619[[#This Row],[% Acum no Ano Comparação]],"Verd","Fals") -> #REF! | H82: 14955.79 | J82: 661.08
B83: =Fluxo_de_Caixa_Janeiro[[#This Row],[Fluxo de Caixa 2026 CTR]] -> 0 | D83: =IFERROR(C83/$C$27,"0,00%") -> 0 | E83: =#REF! -> #REF! | F83: =IF(Fluxo_de_Caixa_Janeiro34591171012151619[[#This Row],[% ACUMULADO DEZ/2026]]<=Fluxo_de_Caixa_Janeiro34591171012151619[[#This Row],[% Acum no Ano Comparação]],"Verd","Fals") -> #REF!
B84: =Fluxo_de_Caixa_Janeiro[[#This Row],[Fluxo de Caixa 2026 CTR]] -> 0 | D84: =IFERROR(C84/$C$27,"0,00%") -> 0 | E84: =#REF! -> #REF! | F84: =IF(Fluxo_de_Caixa_Janeiro34591171012151619[[#This Row],[% ACUMULADO DEZ/2026]]<=Fluxo_de_Caixa_Janeiro34591171012151619[[#This Row],[% Acum no Ano Comparação]],"Verd","Fals") -> #REF!
B85: =Fluxo_de_Caixa_Janeiro[[#This Row],[Fluxo de Caixa 2026 CTR]] -> Total dos Custos | C85: =-SUBTOTAL(109,C52:C84) -> -530050.3 | D85: =IFERROR(C85/C27,"0,00%") -> -0.48729056 | E85: =#REF! -> #REF! | F85: =IF(Fluxo_de_Caixa_Janeiro34591171012151619[[#This Row],[% ACUMULADO DEZ/2026]]<=Fluxo_de_Caixa_Janeiro34591171012151619[[#This Row],[% Acum no Ano Comparação]],"Verd","Fals") -> #REF! | H85: =-SUBTOTAL(109,H52:H84) -> -475804.48 | I85: =-SUBTOTAL(109,I52:I84) -> -44725.36 | J85: =-SUBTOTAL(109,J52:J84) -> -9520.46
B86: =Fluxo_de_Caixa_Janeiro[[#This Row],[Fluxo de Caixa 2026 CTR]] -> Receita Operacional Bruta | C86: =SUM(C27,C85) -> 557699.69 | D86: =IFERROR(C86/C27,"0,00%") -> 0.51270944 | E86: =#REF! -> #REF! | F86: =IF(Fluxo_de_Caixa_Janeiro34591171012151619[[#This Row],[% ACUMULADO DEZ/2026]]>=Fluxo_de_Caixa_Janeiro34591171012151619[[#This Row],[% Acum no Ano Comparação]],"Verd","Fals") -> #REF!
B87: =Fluxo_de_Caixa_Janeiro[[#This Row],[Fluxo de Caixa 2026 CTR]] -> 300. Despesas Operac. Fixas e Variáveis
A88: 3.1. DESPESA COM VENDAS | B88: =Fluxo_de_Caixa_Janeiro[[#This Row],[Fluxo de Caixa 2026 CTR]] -> 3.1. DESPESA COM VENDAS | C88: =-SUBTOTAL(109,C89:C99) -> -50419.47 | D88: =-IFERROR(C88/$C$27,"0,00") -> 0.046352076 | E88: 0.030857534 | F88: =IF(Fluxo_de_Caixa_Janeiro34591171012151619[[#This Row],[% ACUMULADO DEZ/2026]]<=Fluxo_de_Caixa_Janeiro34591171012151619[[#This Row],[% Acum no Ano Comparação]],"Verd","Fals") -> Verd | H88: =-SUBTOTAL(109,H89:H99) -> -46621.16 | I88: =-SUBTOTAL(109,I89:I99) -> -2450.21 | J88: =-SUBTOTAL(109,J89:J99) -> -1348.1
B89: =Fluxo_de_Caixa_Janeiro[[#This Row],[Fluxo de Caixa 2026 CTR]] -> 3.1.01. Marketing e Propaganda | C89: =H89+I89+J89 -> 2535 | D89: =IFERROR(C89/$C$27,"0,00%") -> 0.0023304988 | E89: 0.0010458541 | F89: =IF(Fluxo_de_Caixa_Janeiro34591171012151619[[#This Row],[% ACUMULADO DEZ/2026]]<=Fluxo_de_Caixa_Janeiro34591171012151619[[#This Row],[% Acum no Ano Comparação]],"Verd","Fals") -> Fals | H89: 2535
B90: =Fluxo_de_Caixa_Janeiro[[#This Row],[Fluxo de Caixa 2026 CTR]] -> 3.1.02. Promoções e Eventos(Brindes/Café da Manhã p clientes/etc) | C90: =H90+I90+J90 -> 0 | D90: =IFERROR(C90/$C$27,"0,00%") -> 0 | E90: 0.0011119768 | F90: =IF(Fluxo_de_Caixa_Janeiro34591171012151619[[#This Row],[% ACUMULADO DEZ/2026]]<=Fluxo_de_Caixa_Janeiro34591171012151619[[#This Row],[% Acum no Ano Comparação]],"Verd","Fals") -> Fals
B91: =Fluxo_de_Caixa_Janeiro[[#This Row],[Fluxo de Caixa 2026 CTR]] -> 3.1.03. Sacolas e Embalagens | C91: =H91+I91+J91 -> 303.29 | D91: =IFERROR(C91/$C$27,"0,00%") -> 0.00027882326 | E91: 0.00064528103 | F91: =IF(Fluxo_de_Caixa_Janeiro34591171012151619[[#This Row],[% ACUMULADO DEZ/2026]]<=Fluxo_de_Caixa_Janeiro34591171012151619[[#This Row],[% Acum no Ano Comparação]],"Verd","Fals") -> Fals | H91: 303.29
B92: =Fluxo_de_Caixa_Janeiro[[#This Row],[Fluxo de Caixa 2026 CTR]] -> 3.1.04.DIARIAS E DESPESAS COM VENDEDOR (passagem ônibus, hotel. Etc) | C92: =H92+I92+J92 -> 0 | D92: =IFERROR(C92/$C$27,"0,00%") -> 0 | E92: 8.9915448e-05 | F92: =IF(Fluxo_de_Caixa_Janeiro34591171012151619[[#This Row],[% ACUMULADO DEZ/2026]]<=Fluxo_de_Caixa_Janeiro34591171012151619[[#This Row],[% Acum no Ano Comparação]],"Verd","Fals") -> Fals
B93: =Fluxo_de_Caixa_Janeiro[[#This Row],[Fluxo de Caixa 2026 CTR]] -> 3.1.05. Comissão Representente Comercial | C93: =H93+I93+J93 -> 34661.59 | D93: =IFERROR(C93/$C$27,"0,00%") -> 0.031865401 | E93: 0.012983049 | F93: =IF(Fluxo_de_Caixa_Janeiro34591171012151619[[#This Row],[% ACUMULADO DEZ/2026]]<=Fluxo_de_Caixa_Janeiro34591171012151619[[#This Row],[% Acum no Ano Comparação]],"Verd","Fals") -> Fals | H93: 34661.59
B94: =Fluxo_de_Caixa_Janeiro[[#This Row],[Fluxo de Caixa 2026 CTR]] -> 3.1.06. Frete com entrega de vendas | C94: =H94+I94+J94 -> 5007.88 | D94: =IFERROR(C94/$C$27,"0,00%") -> 0.0046038888 | E94: 0.013626993 | F94: =IF(Fluxo_de_Caixa_Janeiro34591171012151619[[#This Row],[% ACUMULADO DEZ/2026]]<=Fluxo_de_Caixa_Janeiro34591171012151619[[#This Row],[% Acum no Ano Comparação]],"Verd","Fals") -> Fals | H94: 4662.99 | I94: 30 | J94: 314.89
B95: =Fluxo_de_Caixa_Janeiro[[#This Row],[Fluxo de Caixa 2026 CTR]] -> 3.1.07. TAXAS C/ CART CRÉD/DÉBIT | C95: =H95+I95+J95 -> 7791.25 | D95: =IFERROR(C95/$C$27,"0,00%") -> 0.0071627213 | E95: 0.0013544651 | F95: =IF(Fluxo_de_Caixa_Janeiro34591171012151619[[#This Row],[% ACUMULADO DEZ/2026]]<=Fluxo_de_Caixa_Janeiro34591171012151619[[#This Row],[% Acum no Ano Comparação]],"Verd","Fals") -> Fals | H95: 4337.83 | I95: 2420.21 | J95: 1033.21
B96: =Fluxo_de_Caixa_Janeiro[[#This Row],[Fluxo de Caixa 2026 CTR]] -> 3.1.08. Serviço Motoboy Entrega Vendas | C96: =H96+I96+J96 -> 0 | D96: =IFERROR(C96/$C$27,"0,00%") -> 0 | E96: 0.0013544651 | F96: =IF(Fluxo_de_Caixa_Janeiro34591171012151619[[#This Row],[% ACUMULADO DEZ/2026]]<=Fluxo_de_Caixa_Janeiro34591171012151619[[#This Row],[% Acum no Ano Comparação]],"Verd","Fals") -> Fals
B97: =Fluxo_de_Caixa_Janeiro[[#This Row],[Fluxo de Caixa 2026 CTR]] -> 3.1.09. PGTO DISTRATO REPRES COMERCIAL | C97: =H97+I97+J97 -> 0 | D97: =IFERROR(C97/$C$27,"0,00%") -> 0 | E97: 0.0013544651 | F97: =IF(Fluxo_de_Caixa_Janeiro34591171012151619[[#This Row],[% ACUMULADO DEZ/2026]]<=Fluxo_de_Caixa_Janeiro34591171012151619[[#This Row],[% Acum no Ano Comparação]],"Verd","Fals") -> Fals
B98: =Fluxo_de_Caixa_Janeiro[[#This Row],[Fluxo de Caixa 2026 CTR]] -> 3.1.10. TARIFA PIX RECEBIDO | C98: =H98+I98+J98 -> 120.46 | D98: =IFERROR(C98/$C$27,"0,00%") -> 0.00011074236 | E98: 0.0013544651 | F98: =IF(Fluxo_de_Caixa_Janeiro34591171012151619[[#This Row],[% ACUMULADO DEZ/2026]]<=Fluxo_de_Caixa_Janeiro34591171012151619[[#This Row],[% Acum no Ano Comparação]],"Verd","Fals") -> Fals | H98: 120.46
B99: =Fluxo_de_Caixa_Janeiro[[#This Row],[Fluxo de Caixa 2026 CTR]] -> 0 | D99: =IFERROR(C99/$C$27,"0,00%") -> 0 | E99: =#REF! -> #REF! | F99: =IF(Fluxo_de_Caixa_Janeiro34591171012151619[[#This Row],[% ACUMULADO DEZ/2026]]<=Fluxo_de_Caixa_Janeiro34591171012151619[[#This Row],[% Acum no Ano Comparação]],"Verd","Fals") -> #REF!
A100: 3.2. FUNCIONÁRIO | B100: =Fluxo_de_Caixa_Janeiro[[#This Row],[Fluxo de Caixa 2026 CTR]] -> 3.2. DESPESA COM FUNCIONÁRIO | C100: =-SUBTOTAL(109,C101:C130) -> -99956.93 | D100: =-IFERROR(C100/$C$27,"0,00") -> 0.091893294 | E100: 0.067282262 | F100: =IF(Fluxo_de_Caixa_Janeiro34591171012151619[[#This Row],[% ACUMULADO DEZ/2026]]<=Fluxo_de_Caixa_Janeiro34591171012151619[[#This Row],[% Acum no Ano Comparação]],"Verd","Fals") -> Verd | H100: =-SUBTOTAL(109,H101:H130) -> -98490.38 | I100: =-SUBTOTAL(109,I101:I130) -> -1466.55 | J100: =-SUBTOTAL(109,J101:J130) -> 0
B101: =Fluxo_de_Caixa_Janeiro[[#This Row],[Fluxo de Caixa 2026 CTR]] -> 3.2.01. Salário (CLT) | C101: =H101+I101+J101 -> 33411.65 | D101: =IFERROR(C101/$C$27,"0,00%") -> 0.030716295 | E101: 0.016373046 | F101: =IF(Fluxo_de_Caixa_Janeiro34591171012151619[[#This Row],[% ACUMULADO DEZ/2026]]<=Fluxo_de_Caixa_Janeiro34591171012151619[[#This Row],[% Acum no Ano Comparação]],"Verd","Fals") -> Fals | H101: 33411.65
...

Sheet 1 Tri 2026
B1: Fluxo de Caixa 2026 CTR | C1: Janeiro | D1: Fevereiro | E1: Março | F1: Abril | G1: Maio | H1: Junho | I1: Julho | J1: Agosto | K1: Setembro | L1: Outubro | M1: Novembro | N1: Dezembro | O1: Total | P1: % ACUMULADO 1º Trimes 2026 | Q1: % ACUMULADO 1º Trimes 2025 | V1: Total | W1: % ACUMULADO 1º SEMEST 2025
A2: Disponíveis Nas Contas Movimento | B2: =Fluxo_de_Caixa_Janeiro[[#This Row],[Fluxo de Caixa 2026 CTR]] -> Disponíveis Nas Contas Movimento inicial | C2: =Fluxo_de_Caixa_Janeiro[[#This Row],[Janeiro]] -> 67410.42 | D2: =Fluxo_de_Caixa_Janeiro3[[#This Row],[Fevereiro]] -> 31847.63 | E2: =Fluxo_de_Caixa_Janeiro34[[#This Row],[Março]] -> 8957.59 | O2: =Fluxo_de_Caixa_Janeiro31020[[#This Row],[Janeiro]] -> 67410.42 | P2: =SUM(P3:P26) -> 0.8770647 | V2: 192641.1 | W2: 1.0452093
B3: =Fluxo_de_Caixa_Janeiro[[#This Row],[Fluxo de Caixa 2026 CTR]] -> 1.0 - TESOURARIA MATRIZ PALMAS | C3: =Fluxo_de_Caixa_Janeiro[[#This Row],[Janeiro]] -> 148.53 | D3: =Fluxo_de_Caixa_Janeiro3[[#This Row],[Fevereiro]] -> 40.53 | E3: =Fluxo_de_Caixa_Janeiro34[[#This Row],[Março]] -> 337.58 | O3: =Fluxo_de_Caixa_Janeiro31020[[#This Row],[Janeiro]] -> 148.53 | P3: =IF(O3=0,"0,00%",O3/$O$2) -> 0.0022033686 | V3: 375.53 | W3: 0.0019493763
B4: =Fluxo_de_Caixa_Janeiro[[#This Row],[Fluxo de Caixa 2026 CTR]] -> 1.1 - BANCO DO BRASIL C.C.60409-7 MATRIZ | C4: =Fluxo_de_Caixa_Janeiro[[#This Row],[Janeiro]] -> 15268.12 | D4: =Fluxo_de_Caixa_Janeiro3[[#This Row],[Fevereiro]] -> 108.85 | E4: =Fluxo_de_Caixa_Janeiro34[[#This Row],[Março]] -> 55.77 | I4: =#REF! -> #REF! | J4: =#REF! -> #REF! | K4: =#REF! -> #REF! | L4: =#REF! -> #REF! | M4: =#REF! -> #REF! | N4: =#REF! -> #REF! | O4: =Fluxo_de_Caixa_Janeiro31020[[#This Row],[Janeiro]] -> 15268.12 | P4: =IF(O4=0,"0,00%",O4/$O$2) -> 0.22649495 | V4: 0 | W4: 0,00%
B5: =Fluxo_de_Caixa_Janeiro[[#This Row],[Fluxo de Caixa 2026 CTR]] -> 0 | C5: =Fluxo_de_Caixa_Janeiro[[#This Row],[Janeiro]] -> 0 | D5: =Fluxo_de_Caixa_Janeiro3[[#This Row],[Fevereiro]] -> 0 | E5: =Fluxo_de_Caixa_Janeiro34[[#This Row],[Março]] -> 0 | I5: =#REF! -> #REF! | J5: =#REF! -> #REF! | K5: =#REF! -> #REF! | L5: =#REF! -> #REF! | M5: =#REF! -> #REF! | N5: =#REF! -> #REF! | O5: =Fluxo_de_Caixa_Janeiro31020[[#This Row],[Janeiro]] -> 0 | P5: =IF(O5=0,"0,00%",O5/$O$2) -> 0,00% | V5: 0 | W5: 0,00%
B6: =Fluxo_de_Caixa_Janeiro[[#This Row],[Fluxo de Caixa 2026 CTR]] -> 1.2-BRADESCO 15232-3 MATRIZ | C6: =Fluxo_de_Caixa_Janeiro[[#This Row],[Janeiro]] -> 8.62 | D6: =Fluxo_de_Caixa_Janeiro3[[#This Row],[Fevereiro]] -> 3332.91 | E6: =Fluxo_de_Caixa_Janeiro34[[#This Row],[Março]] -> 25.97 | I6: =#REF! -> #REF! | J6: =#REF! -> #REF! | K6: =#REF! -> #REF! | L6: =#REF! -> #REF! | M6: =#REF! -> #REF! | N6: =#REF! -> #REF! | O6: =Fluxo_de_Caixa_Janeiro31020[[#This Row],[Janeiro]] -> 8.62 | P6: =IF(O6=0,"0,00%",O6/$O$2) -> 0.00012787341 | V6: 134596.86 | W6: 0.69869234
B7: =Fluxo_de_Caixa_Janeiro[[#This Row],[Fluxo de Caixa 2026 CTR]] -> 0 | C7: =Fluxo_de_Caixa_Janeiro[[#This Row],[Janeiro]] -> 0 | D7: =Fluxo_de_Caixa_Janeiro3[[#This Row],[Fevereiro]] -> 0 | E7: =Fluxo_de_Caixa_Janeiro34[[#This Row],[Março]] -> 0 | I7: =#REF! -> #REF! | J7: =#REF! -> #REF! | K7: =#REF! -> #REF! | L7: =#REF! -> #REF! | M7: =#REF! -> #REF! | N7: =#REF! -> #REF! | O7: =Fluxo_de_Caixa_Janeiro31020[[#This Row],[Janeiro]] -> 0 | P7: =IF(O7=0,"0,00%",O7/$O$2) -> 0,00% | V7: 0 | W7: 0,00%
B8: =Fluxo_de_Caixa_Janeiro[[#This Row],[Fluxo de Caixa 2026 CTR]] -> 1.3 - BANCO STONE MATRIZ C.C 40256726-7 | C8: =Fluxo_de_Caixa_Janeiro[[#This Row],[Janeiro]] -> 0 | D8: =Fluxo_de_Caixa_Janeiro3[[#This Row],[Fevereiro]] -> 2671 | E8: =Fluxo_de_Caixa_Janeiro34[[#This Row],[Março]] -> 0 | I8: =#REF! -> #REF! | J8: =#REF! -> #REF! | K8: =#REF! -> #REF! | L8: =#REF! -> #REF! | M8: =#REF! -> #REF! | N8: =#REF! -> #REF! | O8: =Fluxo_de_Caixa_Janeiro31020[[#This Row],[Janeiro]] -> 0 | P8: =IF(O8=0,"0,00%",O8/$O$2) -> 0,00% | V8: 26517.91 | W8: 0.13765448
B9: =Fluxo_de_Caixa_Janeiro[[#This Row],[Fluxo de Caixa 2026 CTR]] -> 1.4 - BANCO DA AMAZONIA 071730-7 MATRIZ | C9: =Fluxo_de_Caixa_Janeiro[[#This Row],[Janeiro]] -> 124.56 | D9: =Fluxo_de_Caixa_Janeiro3[[#This Row],[Fevereiro]] -> 281.78 | E9: =Fluxo_de_Caixa_Janeiro34[[#This Row],[Março]] -> 1900.51 | I9: =#REF! -> #REF! | J9: =#REF! -> #REF! | K9: =#REF! -> #REF! | L9: =#REF! -> #REF! | M9: =#REF! -> #REF! | N9: =#REF! -> #REF! | O9: =Fluxo_de_Caixa_Janeiro31020[[#This Row],[Janeiro]] -> 124.56 | P9: =IF(O9=0,"0,00%",O9/$O$2) -> 0.0018477856 | V9: 0 | W9: 0,00%
B10: =Fluxo_de_Caixa_Janeiro[[#This Row],[Fluxo de Caixa 2026 CTR]] -> 1.4.1.INVESTIMENTO CDBORE RCP TXFL | C10: =Fluxo_de_Caixa_Janeiro[[#This Row],[Janeiro]] -> 0 | D10: =Fluxo_de_Caixa_Janeiro3[[#This Row],[Fevereiro]] -> 0 | E10: =Fluxo_de_Caixa_Janeiro34[[#This Row],[Março]] -> 0 | I10: =#REF! -> #REF! | J10: =#REF! -> #REF! | K10: =#REF! -> #REF! | L10: =#REF! -> #REF! | M10: =#REF! -> #REF! | N10: =#REF! -> #REF! | O10: =Fluxo_de_Caixa_Janeiro31020[[#This Row],[Janeiro]] -> 0 | P10: =IF(O10=0,"0,00%",O10/$O$2) -> 0,00% | V10: 5717.64 | W10: 0.029680271
B11: =Fluxo_de_Caixa_Janeiro[[#This Row],[Fluxo de Caixa 2026 CTR]] -> 1.5 - ITAU C.C.98671-6 MATRIZ | C11: =Fluxo_de_Caixa_Janeiro[[#This Row],[Janeiro]] -> 40443.69 | D11: =Fluxo_de_Caixa_Janeiro3[[#This Row],[Fevereiro]] -> 18153.73 | E11: =Fluxo_de_Caixa_Janeiro34[[#This Row],[Março]] -> 33831.3 | I11: =#REF! -> #REF! | J11: =#REF! -> #REF! | K11: =#REF! -> #REF! | L11: =#REF! -> #REF! | M11: =#REF! -> #REF! | N11: =#REF! -> #REF! | O11: =Fluxo_de_Caixa_Janeiro31020[[#This Row],[Janeiro]] -> 40443.69 | P11: =IF(O11=0,"0,00%",O11/$O$2) -> 0.59996199 | V11: 0 | W11: 0,00%
B12: =Fluxo_de_Caixa_Janeiro[[#This Row],[Fluxo de Caixa 2026 CTR]] -> 1.5.03. ITAU C.C 83290-2 GARANTIDA | C12: =Fluxo_de_Caixa_Janeiro[[#This Row],[Janeiro]] -> 902.73 | D12: =Fluxo_de_Caixa_Janeiro3[[#This Row],[Fevereiro]] -> 1286.28 | E12: =Fluxo_de_Caixa_Janeiro34[[#This Row],[Março]] -> 5399.76 | I12: =#REF! -> #REF! | J12: =#REF! -> #REF! | K12: =#REF! -> #REF! | L12: =#REF! -> #REF! | M12: =#REF! -> #REF! | N12: =#REF! -> #REF! | O12: =Fluxo_de_Caixa_Janeiro31020[[#This Row],[Janeiro]] -> 902.73 | P12: =IF(O12=0,"0,00%",O12/$O$2) -> 0.01339155 | V12: 0 | W12: 0,00%
B13: =Fluxo_de_Caixa_Janeiro[[#This Row],[Fluxo de Caixa 2026 CTR]] -> 1.9 - CONTA PERDA/ROUBO/BONIFICAÇÃO E DOAÇÃO | C13: =Fluxo_de_Caixa_Janeiro[[#This Row],[Janeiro]] -> 0 | D13: =Fluxo_de_Caixa_Janeiro3[[#This Row],[Fevereiro]] -> 0 | E13: =Fluxo_de_Caixa_Janeiro34[[#This Row],[Março]] -> -20953.13 | O13: =Fluxo_de_Caixa_Janeiro31020[[#This Row],[Janeiro]] -> 0 | P13: =IF(O13=0,"0,00%",O13/$O$2) -> 0,00% | V13: -2553.05 | W13: -0.013252883
B14: =Fluxo_de_Caixa_Janeiro[[#This Row],[Fluxo de Caixa 2026 CTR]] -> 0 | C14: =Fluxo_de_Caixa_Janeiro[[#This Row],[Janeiro]] -> 0 | D14: =Fluxo_de_Caixa_Janeiro3[[#This Row],[Fevereiro]] -> 0 | E14: =Fluxo_de_Caixa_Janeiro34[[#This Row],[Março]] -> 0 | O14: =Fluxo_de_Caixa_Janeiro31020[[#This Row],[Janeiro]] -> 0 | P14: =IF(O14=0,"0,00%",O14/$O$2) -> 0,00% | V14: 0 | W14: 0
B15: =Fluxo_de_Caixa_Janeiro[[#This Row],[Fluxo de Caixa 2026 CTR]] -> 2.1 - BANCO DO BRASIL C.C.60638-3 FILIAL PALMAS | C15: =Fluxo_de_Caixa_Janeiro[[#This Row],[Janeiro]] -> 1415.61 | D15: =Fluxo_de_Caixa_Janeiro3[[#This Row],[Fevereiro]] -> 1829.48 | E15: =Fluxo_de_Caixa_Janeiro34[[#This Row],[Março]] -> 65.56 | O15: =Fluxo_de_Caixa_Janeiro31020[[#This Row],[Janeiro]] -> 1415.61 | P15: =IF(O15=0,"0,00%",O15/$O$2) -> 0.020999869 | V15: 158.24 | W15: 0.00082142388
B16: =Fluxo_de_Caixa_Janeiro[[#This Row],[Fluxo de Caixa 2026 CTR]] -> 0 | C16: =Fluxo_de_Caixa_Janeiro[[#This Row],[Janeiro]] -> 0 | D16: =Fluxo_de_Caixa_Janeiro3[[#This Row],[Fevereiro]] -> 0 | E16: =Fluxo_de_Caixa_Janeiro34[[#This Row],[Março]] -> 0 | O16: =Fluxo_de_Caixa_Janeiro31020[[#This Row],[Janeiro]] -> 0 | P16: =IF(O16=0,"0,00%",O16/$O$2) -> 0,00% | V16: -1.79 | W16: -9.2918905e-06
B17: =Fluxo_de_Caixa_Janeiro[[#This Row],[Fluxo de Caixa 2026 CTR]] -> 0 | C17: =Fluxo_de_Caixa_Janeiro[[#This Row],[Janeiro]] -> 0 | D17: =Fluxo_de_Caixa_Janeiro3[[#This Row],[Fevereiro]] -> 0 | E17: =Fluxo_de_Caixa_Janeiro34[[#This Row],[Março]] -> 0 | O17: =Fluxo_de_Caixa_Janeiro31020[[#This Row],[Janeiro]] -> 0 | P17: =IF(O17=0,"0,00%",O17/$O$2) -> 0,00% | V17: 0 | W17: 0
B18: =Fluxo_de_Caixa_Janeiro[[#This Row],[Fluxo de Caixa 2026 CTR]] -> 2.4 - ITAU C.C.98669-0 FILIAL PALMAS | C18: =Fluxo_de_Caixa_Janeiro[[#This Row],[Janeiro]] -> 536.72 | D18: =Fluxo_de_Caixa_Janeiro3[[#This Row],[Fevereiro]] -> 536.72 | E18: =Fluxo_de_Caixa_Janeiro34[[#This Row],[Março]] -> 37.73 | O18: =Fluxo_de_Caixa_Janeiro31020[[#This Row],[Janeiro]] -> 536.72 | P18: =IF(O18=0,"0,00%",O18/$O$2) -> 0.0079619738 | V18: 26883.69 | W18: 0.13955324
B19: =Fluxo_de_Caixa_Janeiro[[#This Row],[Fluxo de Caixa 2026 CTR]] -> 2.9 - CONTA PERDA/ROUBO E BONIFICAÇÃO FILIAL | C19: =Fluxo_de_Caixa_Janeiro[[#This Row],[Janeiro]] -> 0 | D19: =Fluxo_de_Caixa_Janeiro3[[#This Row],[Fevereiro]] -> -219.15 | E19: =Fluxo_de_Caixa_Janeiro34[[#This Row],[Março]] -> -8598.58 | O19: =SUM(Fluxo_de_Caixa_Janeiro31020[[#This Row],[Janeiro]:[Dezembro]]) -> -8817.73 | P19: =IF(O19=0,"0,00%",O19/$O$2) -> -0.13080663 | V19: 2838.21 | W19: 0.014733149
B20: =Fluxo_de_Caixa_Janeiro[[#This Row],[Fluxo de Caixa 2026 CTR]] -> 4.0 - TESOURARIA FILIAL PORTO | C20: =Fluxo_de_Caixa_Janeiro[[#This Row],[Janeiro]] -> 1409.97 | D20: =Fluxo_de_Caixa_Janeiro3[[#This Row],[Fevereiro]] -> 385.51 | E20: =Fluxo_de_Caixa_Janeiro34[[#This Row],[Março]] -> 1327.43 | O20: =SUM(Fluxo_de_Caixa_Janeiro31020[[#This Row],[Janeiro]:[Dezembro]]) -> 3122.91 | P20: =IF(O20=0,"0,00%",O20/$O$2) -> 0.046326814 | V20: 0 | W20: 0,00%
B21: =Fluxo_de_Caixa_Janeiro[[#This Row],[Fluxo de Caixa 2026 CTR]] -> 4.1 - BANCO DO BRASIL C.C.61105-0 FILIAL PORTO | C21: =Fluxo_de_Caixa_Janeiro[[#This Row],[Janeiro]] -> 57.34 | D21: =Fluxo_de_Caixa_Janeiro3[[#This Row],[Fevereiro]] -> 16.83 | E21: =Fluxo_de_Caixa_Janeiro34[[#This Row],[Março]] -> 111.93 | O21: =SUM(Fluxo_de_Caixa_Janeiro31020[[#This Row],[Janeiro]:[Dezembro]]) -> 186.1 | P21: =IF(O21=0,"0,00%",O21/$O$2) -> 0.0027607008 | V21: 0 | W21: 0,00%
B22: =Fluxo_de_Caixa_Janeiro[[#This Row],[Fluxo de Caixa 2026 CTR]] -> 0 | C22: =Fluxo_de_Caixa_Janeiro[[#This Row],[Janeiro]] -> 0 | D22: =Fluxo_de_Caixa_Janeiro3[[#This Row],[Fevereiro]] -> 0 | E22: =Fluxo_de_Caixa_Janeiro34[[#This Row],[Março]] -> 0 | O22: =SUM(Fluxo_de_Caixa_Janeiro31020[[#This Row],[Janeiro]:[Dezembro]]) -> 0 | P22: =IF(O22=0,"0,00%",O22/$O$2) -> 0,00% | V22: 0 | W22: 0,00%
B23: =Fluxo_de_Caixa_Janeiro[[#This Row],[Fluxo de Caixa 2026 CTR]] -> 4.4 - MERCADO PAGO PIX FILIAL PORTO | C23: =Fluxo_de_Caixa_Janeiro[[#This Row],[Janeiro]] -> 5412.19 | D23: =Fluxo_de_Caixa_Janeiro3[[#This Row],[Fevereiro]] -> 2060.42 | E23: =Fluxo_de_Caixa_Janeiro34[[#This Row],[Março]] -> 22539.57 | O23: =SUM(Fluxo_de_Caixa_Janeiro31020[[#This Row],[Janeiro]:[Dezembro]]) -> 30012.18 | P23: =IF(O23=0,"0,00%",O23/$O$2) -> 0.44521574 | V23: 5332.04 | W23: 0.027678621
B24: =Fluxo_de_Caixa_Janeiro[[#This Row],[Fluxo de Caixa 2026 CTR]] -> 4.9 - CONTA PERDA/ROUBO E BONIFICAÇÃO FILIAL | C24: =Fluxo_de_Caixa_Janeiro[[#This Row],[Janeiro]] -> 0 | D24: =Fluxo_de_Caixa_Janeiro3[[#This Row],[Fevereiro]] -> 0 | E24: =Fluxo_de_Caixa_Janeiro34[[#This Row],[Março]] -> -29071.86 | O24: =SUM(Fluxo_de_Caixa_Janeiro31020[[#This Row],[Janeiro]:[Dezembro]]) -> -29071.86 | P24: =IF(O24=0,"0,00%",O24/$O$2) -> -0.43126656 | V24: 770.18 | W24: 0.0039980046
B25: =Fluxo_de_Caixa_Janeiro[[#This Row],[Fluxo de Caixa 2026 CTR]] -> 91.CARTÃO ENDERED 5099+4596+6933+8072 - ESCRITORIO | C25: =Fluxo_de_Caixa_Janeiro[[#This Row],[Janeiro]] -> 1682.34 | D25: =Fluxo_de_Caixa_Janeiro3[[#This Row],[Fevereiro]] -> 1362.74 | E25: =Fluxo_de_Caixa_Janeiro34[[#This Row],[Março]] -> 1948.05 | O25: =SUM(Fluxo_de_Caixa_Janeiro31020[[#This Row],[Janeiro]:[Dezembro]]) -> 4993.13 | P25: =IF(O25=0,"0,00%",O25/$O$2) -> 0.074070596 | V25: 714.8 | W25: 0.003710527
B26: =Fluxo_de_Caixa_Janeiro[[#This Row],[Fluxo de Caixa 2026 CTR]] -> 0 | C26: =Fluxo_de_Caixa_Janeiro[[#This Row],[Janeiro]] -> 0 | D26: =Fluxo_de_Caixa_Janeiro3[[#This Row],[Fevereiro]] -> -150.01 | E26: =Fluxo_de_Caixa_Janeiro34[[#This Row],[Março]] -> 0 | O26: =SUM(Fluxo_de_Caixa_Janeiro31020[[#This Row],[Janeiro]:[Dezembro]]) -> -150.01 | P26: =IF(O26=0,"0,00%",O26/$O$2) -> -0.0022253236 | V26: 1.7462298e-10 | W26: 9.0646795e-16
B27: =Fluxo_de_Caixa_Janeiro[[#This Row],[Fluxo de Caixa 2026 CTR]] -> Total Receitas Operacionais / Vendas | C27: =Fluxo_de_Caixa_Janeiro[[#This Row],[Janeiro]] -> 749632.93 | D27: =Fluxo_de_Caixa_Janeiro3[[#This Row],[Fevereiro]] -> 1038589.1 | E27: =Fluxo_de_Caixa_Janeiro34[[#This Row],[Março]] -> 1087750 | O27: =SUM(Fluxo_de_Caixa_Janeiro31020[[#This Row],[Janeiro]:[Dezembro]]) -> 2875972 | P27: =IFERROR(O27/O332,"0,00%") -> 0.7756588 | Q27: 0.98042161 | R27: =IF(Fluxo_de_Caixa_Janeiro31020[[#This Row],[% ACUMULADO 1º Trimes 2026]]>=Fluxo_de_Caixa_Janeiro31020[[#This Row],[% ACUMULADO 1º Trimes 2025]],"VERDADEIRO","FALSO") -> FALSO | T27: =V27-Fluxo_de_Caixa_Janeiro31020[[#This Row],[Total]] -> -185520.07 | V27: 2690451.9 | W27: 0.98042161
A28: 1.1. Receita com Vendas | B28: =Fluxo_de_Caixa_Janeiro[[#This Row],[Fluxo de Caixa 2026 CTR]] -> 1.1. Receita com Vendas | C28: =Fluxo_de_Caixa_Janeiro[[#This Row],[Janeiro]] -> 749632.93 | D28: =Fluxo_de_Caixa_Janeiro3[[#This Row],[Fevereiro]] -> 1038589.1 | E28: =Fluxo_de_Caixa_Janeiro34[[#This Row],[Março]] -> 1087750 | O28: =SUM(Fluxo_de_Caixa_Janeiro31020[[#This Row],[Janeiro]:[Dezembro]]) -> 2875972 | P28: =SUM(P29:P47) -> 0.7756588 | Q28: 0.98042161 | R28: =IF(Fluxo_de_Caixa_Janeiro31020[[#This Row],[% ACUMULADO 1º Trimes 2026]]>=Fluxo_de_Caixa_Janeiro31020[[#This Row],[% ACUMULADO 1º Trimes 2025]],"VERDADEIRO","FALSO") -> FALSO | V28: 2690451.9 | W28: 0.98042161
B29: =Fluxo_de_Caixa_Janeiro[[#This Row],[Fluxo de Caixa 2026 CTR]] -> 1.1.01. Receita em Dinheiro | C29: =Fluxo_de_Caixa_Janeiro[[#This Row],[Janeiro]] -> 2199.78 | D29: =Fluxo_de_Caixa_Janeiro3[[#This Row],[Fevereiro]] -> 4660.37 | E29: =Fluxo_de_Caixa_Janeiro34[[#This Row],[Março]] -> 2754.35 | O29: =SUM(Fluxo_de_Caixa_Janeiro31020[[#This Row],[Janeiro]:[Dezembro]]) -> 9614.5 | P29: =IF(O29=0,"0,00%",O29/$O$332) -> 0.0025930612 | Q29: 0.0080947211 | R29: =IF(Fluxo_de_Caixa_Janeiro31020[[#This Row],[% ACUMULADO 1º Trimes 2026]]>=Fluxo_de_Caixa_Janeiro31020[[#This Row],[% ACUMULADO 1º Trimes 2025]],"VERDADEIRO","FALSO") -> FALSO | V29: 22213.36 | W29: 0.0080947211
B30: =Fluxo_de_Caixa_Janeiro[[#This Row],[Fluxo de Caixa 2026 CTR]] -> 1.1.01. Receita em Cartão (Crédito e Débito) | C30: =Fluxo_de_Caixa_Janeiro[[#This Row],[Janeiro]] -> 328505.72 | D30: =Fluxo_de_Caixa_Janeiro3[[#This Row],[Fevereiro]] -> 221053.51 | E30: =Fluxo_de_Caixa_Janeiro34[[#This Row],[Março]] -> 110371.17 | O30: =SUM(Fluxo_de_Caixa_Janeiro31020[[#This Row],[Janeiro]:[Dezembro]]) -> 659930.4 | P30: =IF(O30=0,"0,00%",O30/$O$332) -> 0.17798533 | Q30: 0.060278818 | R30: =IF(Fluxo_de_Caixa_Janeiro31020[[#This Row],[% ACUMULADO 1º Trimes 2026]]>=Fluxo_de_Caixa_Janeiro31020[[#This Row],[% ACUMULADO 1º Trimes 2025]],"VERDADEIRO","FALSO") -> VERDADEIRO | V30: 165415.84 | W30: 0.060278818
B31: =Fluxo_de_Caixa_Janeiro[[#This Row],[Fluxo de Caixa 2026 CTR]] -> 1.1.01. Receita de Cheque A Vista | C31: =Fluxo_de_Caixa_Janeiro[[#This Row],[Janeiro]] -> 15000 | D31: =Fluxo_de_Caixa_Janeiro3[[#This Row],[Fevereiro]] -> 26907.75 | E31: =Fluxo_de_Caixa_Janeiro34[[#This Row],[Março]] -> 0 | O31: =SUM(Fluxo_de_Caixa_Janeiro31020[[#This Row],[Janeiro]:[Dezembro]]) -> 41907.75 | P31: =IF(O31=0,"0,00%",O31/$O$332) -> 0.011302653 | Q31: 0,00% | R31: =IF(Fluxo_de_Caixa_Janeiro31020[[#This Row],[% ACUMULADO 1º Trimes 2026]]>=Fluxo_de_Caixa_Janeiro31020[[#This Row],[% ACUMULADO 1º Trimes 2025]],"VERDADEIRO","FALSO") -> FALSO | V31: 0 | W31: 0,00%
B32: =Fluxo_de_Caixa_Janeiro[[#This Row],[Fluxo de Caixa 2026 CTR]] -> 1.1.01. Receita de Cheque Pré | C32: =Fluxo_de_Caixa_Janeiro[[#This Row],[Janeiro]] -> 0 | D32: =Fluxo_de_Caixa_Janeiro3[[#This Row],[Fevereiro]] -> 0 | E32: =Fluxo_de_Caixa_Janeiro34[[#This Row],[Março]] -> 0 | O32: =SUM(Fluxo_de_Caixa_Janeiro31020[[#This Row],[Janeiro]:[Dezembro]]) -> 0 | P32: =IF(O32=0,"0,00%",O32/$O$332) -> 0,00% | Q32: 0,00% | R32: =IF(Fluxo_de_Caixa_Janeiro31020[[#This Row],[% ACUMULADO 1º Trimes 2026]]>=Fluxo_de_Caixa_Janeiro31020[[#This Row],[% ACUMULADO 1º Trimes 2025]],"VERDADEIRO","FALSO") -> VERDADEIRO | V32: 0 | W32: 0,00%
B33: =Fluxo_de_Caixa_Janeiro[[#This Row],[Fluxo de Caixa 2026 CTR]] -> 1.1.01. Recebimento de Carteira (Notinha) | C33: =Fluxo_de_Caixa_Janeiro[[#This Row],[Janeiro]] -> 0 | D33: =Fluxo_de_Caixa_Janeiro3[[#This Row],[Fevereiro]] -> 0 | E33: =Fluxo_de_Caixa_Janeiro34[[#This Row],[Março]] -> 190040.35 | O33: =SUM(Fluxo_de_Caixa_Janeiro31020[[#This Row],[Janeiro]:[Dezembro]]) -> 190040.35 | P33: =IF(O33=0,"0,00%",O33/$O$332) -> 0.051254487 | Q33: 0.28301373 | R33: =IF(Fluxo_de_Caixa_Janeiro31020[[#This Row],[% ACUMULADO 1º Trimes 2026]]>=Fluxo_de_Caixa_Janeiro31020[[#This Row],[% ACUMULADO 1º Trimes 2025]],"VERDADEIRO","FALSO") -> FALSO | V33: 776640.22 | W33: 0.28301373
B34: =Fluxo_de_Caixa_Janeiro[[#This Row],[Fluxo de Caixa 2026 CTR]] -> 1.1.01. Recebimento de Boletos | C34: =Fluxo_de_Caixa_Janeiro[[#This Row],[Janeiro]] -> 144411.43 | D34: =Fluxo_de_Caixa_Janeiro3[[#This Row],[Fevereiro]] -> 317162.15 | E34: =Fluxo_de_Caixa_Janeiro34[[#This Row],[Março]] -> 395244.86 | O34: =SUM(Fluxo_de_Caixa_Janeiro31020[[#This Row],[Janeiro]:[Dezembro]]) -> 856818.44 | P34: =IF(O34=0,"0,00%",O34/$O$332) -> 0.23108666 | Q34: 0.40013718 | R34: =IF(Fluxo_de_Caixa_Janeiro31020[[#This Row],[% ACUMULADO 1º Trimes 2026]]>=Fluxo_de_Caixa_Janeiro31020[[#This Row],[% ACUMULADO 1º Trimes 2025]],"VERDADEIRO","FALSO") -> FALSO | V34: 1098047.9 | W34: 0.40013718
B35: =Fluxo_de_Caixa_Janeiro[[#This Row],[Fluxo de Caixa 2026 CTR]] -> 1.1.01. Recebimento em Depósito e Dep. PIX | C35: =Fluxo_de_Caixa_Janeiro[[#This Row],[Janeiro]] -> 259516 | D35: =Fluxo_de_Caixa_Janeiro3[[#This Row],[Fevereiro]] -> 468805.31 | E35: =Fluxo_de_Caixa_Janeiro34[[#This Row],[Março]] -> 389339.26 | O35: =SUM(Fluxo_de_Caixa_Janeiro31020[[#This Row],[Janeiro]:[Dezembro]]) -> 1117660.6 | P35: =IF(O35=0,"0,00%",O35/$O$332) -> 0.30143661 | Q35: 0.22889715 | R35: =IF(Fluxo_de_Caixa_Janeiro31020[[#This Row],[% ACUMULADO 1º Trimes 2026]]>=Fluxo_de_Caixa_Janeiro31020[[#This Row],[% ACUMULADO 1º Trimes 2025]],"VERDADEIRO","FALSO") -> VERDADEIRO | V35: 628134.64 | W35: 0.22889715
B36: =Fluxo_de_Caixa_Janeiro[[#This Row],[Fluxo de Caixa 2026 CTR]] -> 1.1.02. Recebimento Cheque Devolvido | C36: =Fluxo_de_Caixa_Janeiro[[#This Row],[Janeiro]] -> 0 | D36: =Fluxo_de_Caixa_Janeiro3[[#This Row],[Fevereiro]] -> 0 | E36: =Fluxo_de_Caixa_Janeiro34[[#This Row],[Março]] -> 0 | O36: =SUM(Fluxo_de_Caixa_Janeiro31020[[#This Row],[Janeiro]:[Dezembro]]) -> 0 | P36: =IF(O36=0,"0,00%",O36/$O$332) -> 0,00% | Q36: 0,00% | R36: =IF(Fluxo_de_Caixa_Janeiro31020[[#This Row],[% ACUMULADO 1º Trimes 2026]]>=Fluxo_de_Caixa_Janeiro31020[[#This Row],[% ACUMULADO 1º Trimes 2025]],"VERDADEIRO","FALSO") -> VERDADEIRO | V36: 0 | W36: 0,00%
B37: =Fluxo_de_Caixa_Janeiro[[#This Row],[Fluxo de Caixa 2026 CTR]] -> 0 | C37: =Fluxo_de_Caixa_Janeiro[[#This Row],[Janeiro]] -> 0 | D37: =Fluxo_de_Caixa_Janeiro3[[#This Row],[Fevereiro]] -> 0 | E37: =Fluxo_de_Caixa_Janeiro34[[#This Row],[Março]] -> 0 | O37: =SUM(Fluxo_de_Caixa_Janeiro31020[[#This Row],[Janeiro]:[Dezembro]]) -> 0 | P37: =IF(O37=0,"0,00%",O37/$O$332) -> 0,00% | Q37: 0,00% | R37: =IF(Fluxo_de_Caixa_Janeiro31020[[#This Row],[% ACUMULADO 1º Trimes 2026]]>=Fluxo_de_Caixa_Janeiro31020[[#This Row],[% ACUMULADO 1º Trimes 2025]],"VERDADEIRO","FALSO") -> VERDADEIRO | V37: 0 | W37: 0,00%
B38: =Fluxo_de_Caixa_Janeiro[[#This Row],[Fluxo de Caixa 2026 CTR]] -> 0 | C38: =Fluxo_de_Caixa_Janeiro[[#This Row],[Janeiro]] -> 0 | D38: =Fluxo_de_Caixa_Janeiro3[[#This Row],[Fevereiro]] -> 0 | E38: =Fluxo_de_Caixa_Janeiro34[[#This Row],[Março]] -> 0 | O38: =SUM(Fluxo_de_Caixa_Janeiro31020[[#This Row],[Janeiro]:[Dezembro]]) -> 0 | P38: =IF(O38=0,"0,00%",O38/$O$332) -> 0,00% | Q38: 0,00% | R38: =IF(Fluxo_de_Caixa_Janeiro31020[[#This Row],[% ACUMULADO 1º Trimes 2026]]>=Fluxo_de_Caixa_Janeiro31020[[#This Row],[% ACUMULADO 1º Trimes 2025]],"VERDADEIRO","FALSO") -> VERDADEIRO | V38: 0 | W38: 0,00%
B39: =Fluxo_de_Caixa_Janeiro[[#This Row],[Fluxo de Caixa 2026 CTR]] -> 0 | C39: =Fluxo_de_Caixa_Janeiro[[#This Row],[Janeiro]] -> 0 | D39: =Fluxo_de_Caixa_Janeiro3[[#This Row],[Fevereiro]] -> 0 | E39: =Fluxo_de_Caixa_Janeiro34[[#This Row],[Março]] -> 0 | O39: =SUM(Fluxo_de_Caixa_Janeiro31020[[#This Row],[Janeiro]:[Dezembro]]) -> 0 | P39: =IF(O39=0,"0,00%",O39/$O$332) -> 0,00% | Q39: 0,00% | R39: =IF(Fluxo_de_Caixa_Janeiro31020[[#This Row],[% ACUMULADO 1º Trimes 2026]]>=Fluxo_de_Caixa_Janeiro31020[[#This Row],[% ACUMULADO 1º Trimes 2025]],"VERDADEIRO","FALSO") -> VERDADEIRO | V39: 0 | W39: 0,00%
B40: =Fluxo_de_Caixa_Janeiro[[#This Row],[Fluxo de Caixa 2026 CTR]] -> 0 | C40: =Fluxo_de_Caixa_Janeiro[[#This Row],[Janeiro]] -> 0 | D40: =Fluxo_de_Caixa_Janeiro3[[#This Row],[Fevereiro]] -> 0 | E40: =Fluxo_de_Caixa_Janeiro34[[#This Row],[Março]] -> 0 | O40: =SUM(Fluxo_de_Caixa_Janeiro31020[[#This Row],[Janeiro]:[Dezembro]]) -> 0 | P40: =IF(O40=0,"0,00%",O40/$O$332) -> 0,00% | Q40: 0,00% | R40: =IF(Fluxo_de_Caixa_Janeiro31020[[#This Row],[% ACUMULADO 1º Trimes 2026]]>=Fluxo_de_Caixa_Janeiro31020[[#This Row],[% ACUMULADO 1º Trimes 2025]],"VERDADEIRO","FALSO") -> VERDADEIRO | V40: 0 | W40: 0,00%
B41: =Fluxo_de_Caixa_Janeiro[[#This Row],[Fluxo de Caixa 2026 CTR]] -> 0 | C41: =Fluxo_de_Caixa_Janeiro[[#This Row],[Janeiro]] -> 0 | D41: =Fluxo_de_Caixa_Janeiro3[[#This Row],[Fevereiro]] -> 0 | E41: =Fluxo_de_Caixa_Janeiro34[[#This Row],[Março]] -> 0 | O41: =SUM(Fluxo_de_Caixa_Janeiro31020[[#This Row],[Janeiro]:[Dezembro]]) -> 0 | P41: =IF(O41=0,"0,00%",O41/$O$332) -> 0,00% | Q41: 0,00% | R41: =IF(Fluxo_de_Caixa_Janeiro31020[[#This Row],[% ACUMULADO 1º Trimes 2026]]>=Fluxo_de_Caixa_Janeiro31020[[#This Row],[% ACUMULADO 1º Trimes 2025]],"VERDADEIRO","FALSO") -> VERDADEIRO | V41: 0 | W41: 0,00%
B42: =Fluxo_de_Caixa_Janeiro[[#This Row],[Fluxo de Caixa 2026 CTR]] -> 0 | C42: =Fluxo_de_Caixa_Janeiro[[#This Row],[Janeiro]] -> 0 | D42: =Fluxo_de_Caixa_Janeiro3[[#This Row],[Fevereiro]] -> 0 | E42: =Fluxo_de_Caixa_Janeiro34[[#This Row],[Março]] -> 0 | O42: =SUM(Fluxo_de_Caixa_Janeiro31020[[#This Row],[Janeiro]:[Dezembro]]) -> 0 | P42: =IF(O42=0,"0,00%",O42/$O$332) -> 0,00% | Q42: 0,00% | R42: =IF(Fluxo_de_Caixa_Janeiro31020[[#This Row],[% ACUMULADO 1º Trimes 2026]]>=Fluxo_de_Caixa_Janeiro31020[[#This Row],[% ACUMULADO 1º Trimes 2025]],"VERDADEIRO","FALSO") -> VERDADEIRO | V42: 0 | W42: 0,00%
B43: =Fluxo_de_Caixa_Janeiro[[#This Row],[Fluxo de Caixa 2026 CTR]] -> 0 | C43: =Fluxo_de_Caixa_Janeiro[[#This Row],[Janeiro]] -> 0 | D43: =Fluxo_de_Caixa_Janeiro3[[#This Row],[Fevereiro]] -> 0 | E43: =Fluxo_de_Caixa_Janeiro34[[#This Row],[Março]] -> 0 | O43: =SUM(Fluxo_de_Caixa_Janeiro31020[[#This Row],[Janeiro]:[Dezembro]]) -> 0 | P43: =IF(O43=0,"0,00%",O43/$O$332) -> 0,00% | Q43: 0,00% | R43: =IF(Fluxo_de_Caixa_Janeiro31020[[#This Row],[% ACUMULADO 1º Trimes 2026]]>=Fluxo_de_Caixa_Janeiro31020[[#This Row],[% ACUMULADO 1º Trimes 2025]],"VERDADEIRO","FALSO") -> VERDADEIRO | V43: 0 | W43: 0,00%
B44: =Fluxo_de_Caixa_Janeiro[[#This Row],[Fluxo de Caixa 2026 CTR]] -> 0 | C44: =Fluxo_de_Caixa_Janeiro[[#This Row],[Janeiro]] -> 0 | D44: =Fluxo_de_Caixa_Janeiro3[[#This Row],[Fevereiro]] -> 0 | E44: =Fluxo_de_Caixa_Janeiro34[[#This Row],[Março]] -> 0 | O44: =SUM(Fluxo_de_Caixa_Janeiro31020[[#This Row],[Janeiro]:[Dezembro]]) -> 0 | P44: =IF(O44=0,"0,00%",O44/$O$332) -> 0,00% | Q44: 0,00% | R44: =IF(Fluxo_de_Caixa_Janeiro31020[[#This Row],[% ACUMULADO 1º Trimes 2026]]>=Fluxo_de_Caixa_Janeiro31020[[#This Row],[% ACUMULADO 1º Trimes 2025]],"VERDADEIRO","FALSO") -> VERDADEIRO | V44: 0 | W44: 0,00%
B45: =Fluxo_de_Caixa_Janeiro[[#This Row],[Fluxo de Caixa 2026 CTR]] -> 0 | C45: =Fluxo_de_Caixa_Janeiro[[#This Row],[Janeiro]] -> 0 | D45: =Fluxo_de_Caixa_Janeiro3[[#This Row],[Fevereiro]] -> 0 | E45: =Fluxo_de_Caixa_Janeiro34[[#This Row],[Março]] -> 0 | O45: =SUM(Fluxo_de_Caixa_Janeiro31020[[#This Row],[Janeiro]:[Dezembro]]) -> 0 | P45: =IF(O45=0,"0,00%",O45/$O$332) -> 0,00% | Q45: 0,00% | R45: =IF(Fluxo_de_Caixa_Janeiro31020[[#This Row],[% ACUMULADO 1º Trimes 2026]]>=Fluxo_de_Caixa_Janeiro31020[[#This Row],[% ACUMULADO 1º Trimes 2025]],"VERDADEIRO","FALSO") -> VERDADEIRO | V45: 0 | W45: 0,00%
B46: =Fluxo_de_Caixa_Janeiro[[#This Row],[Fluxo de Caixa 2026 CTR]] -> 0 | C46: =Fluxo_de_Caixa_Janeiro[[#This Row],[Janeiro]] -> 0 | D46: =Fluxo_de_Caixa_Janeiro3[[#This Row],[Fevereiro]] -> 0 | E46: =Fluxo_de_Caixa_Janeiro34[[#This Row],[Março]] -> 0 | O46: =SUM(Fluxo_de_Caixa_Janeiro31020[[#This Row],[Janeiro]:[Dezembro]]) -> 0 | P46: =IF(O46=0,"0,00%",O46/$O$332) -> 0,00% | Q46: 0,00% | R46: =IF(Fluxo_de_Caixa_Janeiro31020[[#This Row],[% ACUMULADO 1º Trimes 2026]]>=Fluxo_de_Caixa_Janeiro31020[[#This Row],[% ACUMULADO 1º Trimes 2025]],"VERDADEIRO","FALSO") -> VERDADEIRO | V46: 0 | W46: 0,00%
B47: =Fluxo_de_Caixa_Janeiro[[#This Row],[Fluxo de Caixa 2026 CTR]] -> 0 | C47: =Fluxo_de_Caixa_Janeiro[[#This Row],[Janeiro]] -> 0 | D47: =Fluxo_de_Caixa_Janeiro3[[#This Row],[Fevereiro]] -> 0 | E47: =Fluxo_de_Caixa_Janeiro34[[#This Row],[Março]] -> 0 | O47: =SUM(Fluxo_de_Caixa_Janeiro31020[[#This Row],[Janeiro]:[Dezembro]]) -> 0 | P47: =IF(O47=0,"0,00%",O47/$O$332) -> 0,00% | Q47: 0,00% | R47: =IF(Fluxo_de_Caixa_Janeiro31020[[#This Row],[% ACUMULADO 1º Trimes 2026]]>=Fluxo_de_Caixa_Janeiro31020[[#This Row],[% ACUMULADO 1º Trimes 2025]],"VERDADEIRO","FALSO") -> VERDADEIRO | V47: 0 | W47: 0,00%
A48: 1.5. Receita de Garantias | B48: =Fluxo_de_Caixa_Janeiro[[#This Row],[Fluxo de Caixa 2026 CTR]] -> 1.5. Receita de Garantias | C48: =Fluxo_de_Caixa_Janeiro[[#This Row],[Janeiro]] -> 0 | D48: =Fluxo_de_Caixa_Janeiro3[[#This Row],[Fevereiro]] -> 0 | E48: =Fluxo_de_Caixa_Janeiro34[[#This Row],[Março]] -> 0 | O48: =SUM(Fluxo_de_Caixa_Janeiro31020[[#This Row],[Janeiro]:[Dezembro]]) -> 0 | P48: =SUM(P49:P51) -> 0 | Q48: 0 | R48: =IF(Fluxo_de_Caixa_Janeiro31020[[#This Row],[% ACUMULADO 1º Trimes 2026]]>=Fluxo_de_Caixa_Janeiro31020[[#This Row],[% ACUMULADO 1º Trimes 2025]],"VERDADEIRO","FALSO") -> VERDADEIRO | V48: 0 | W48: 0
B49: =Fluxo_de_Caixa_Janeiro[[#This Row],[Fluxo de Caixa 2026 CTR]] -> 1.2.01. RECEITA EM DINHEIRO | C49: =Fluxo_de_Caixa_Janeiro[[#This Row],[Janeiro]] -> 0 | D49: =Fluxo_de_Caixa_Janeiro3[[#This Row],[Fevereiro]] -> 0 | E49: =Fluxo_de_Caixa_Janeiro34[[#This Row],[Março]] -> 0 | O49: =SUM(Fluxo_de_Caixa_Janeiro31020[[#This Row],[Janeiro]:[Dezembro]]) -> 0 | P49: =IF(O49=0,"0,00%",O49/$O$332) -> 0,00% | Q49: 0,00% | R49: =IF(Fluxo_de_Caixa_Janeiro31020[[#This Row],[% ACUMULADO 1º Trimes 2026]]>=Fluxo_de_Caixa_Janeiro31020[[#This Row],[% ACUMULADO 1º Trimes 2025]],"VERDADEIRO","FALSO") -> VERDADEIRO | V49: 0 | W49: 0,00%
B50: =Fluxo_de_Caixa_Janeiro[[#This Row],[Fluxo de Caixa 2026 CTR]] -> 1.2.02. RECEITA EM MERCADORIA | C50: =Fluxo_de_Caixa_Janeiro[[#This Row],[Janeiro]] -> 0 | D50: =Fluxo_de_Caixa_Janeiro3[[#This Row],[Fevereiro]] -> 0 | E50: =Fluxo_de_Caixa_Janeiro34[[#This Row],[Março]] -> 0 | O50: =SUM(Fluxo_de_Caixa_Janeiro31020[[#This Row],[Janeiro]:[Dezembro]]) -> 0 | P50: =IF(O50=0,"0,00%",O50/$O$332) -> 0,00% | Q50: 0,00% | R50: =IF(Fluxo_de_Caixa_Janeiro31020[[#This Row],[% ACUMULADO 1º Trimes 2026]]>=Fluxo_de_Caixa_Janeiro31020[[#This Row],[% ACUMULADO 1º Trimes 2025]],"VERDADEIRO","FALSO") -> VERDADEIRO | V50: 0 | W50: 0,00%
B51: =Fluxo_de_Caixa_Janeiro[[#This Row],[Fluxo de Caixa 2026 CTR]] -> 0 | C51: =Fluxo_de_Caixa_Janeiro[[#This Row],[Janeiro]] -> 0 | D51: =Fluxo_de_Caixa_Janeiro3[[#This Row],[Fevereiro]] -> 0 | E51: =Fluxo_de_Caixa_Janeiro34[[#This Row],[Março]] -> 0 | O51: =SUM(Fluxo_de_Caixa_Janeiro31020[[#This Row],[Janeiro]:[Dezembro]]) -> 0 | P51: =IF(O51=0,"0,00%",O51/$O$332) -> 0,00% | Q51: 0,00% | R51: =IF(Fluxo_de_Caixa_Janeiro31020[[#This Row],[% ACUMULADO 1º Trimes 2026]]>=Fluxo_de_Caixa_Janeiro31020[[#This Row],[% ACUMULADO 1º Trimes 2025]],"VERDADEIRO","FALSO") -> VERDADEIRO | V51: 0 | W51: 0,00%
A52: 2.1. Despesa Com Custo de Aquisição | B52: =Fluxo_de_Caixa_Janeiro[[#This Row],[Fluxo de Caixa 2026 CTR]] -> 2.1. Despesa Com Custo de Aquisição | C52: =Fluxo_de_Caixa_Janeiro[[#This Row],[Janeiro]] -> -460642.66 | D52: =Fluxo_de_Caixa_Janeiro3[[#This Row],[Fevereiro]] -> -419540.11 | E52: =Fluxo_de_Caixa_Janeiro34[[#This Row],[Março]] -> -456490.45 | O52: =SUM(Fluxo_de_Caixa_Janeiro31020[[#This Row],[Janeiro]:[Dezembro]]) -> -1336673.2 | P52: =-IFERROR(O52/$O$27,"0,00") -> 0.46477268 | Q52: 0.65979289 | R52: =IF(Fluxo_de_Caixa_Janeiro31020[[#This Row],[% ACUMULADO 1º Trimes 2026]]<=Fluxo_de_Caixa_Janeiro31020[[#This Row],[% ACUMULADO 1º Trimes 2025]],"VERDADEIRO","FALSO") -> VERDADEIRO | V52: -1775141.1 | W52: 0.65979289
B53: =Fluxo_de_Caixa_Janeiro[[#This Row],[Fluxo de Caixa 2026 CTR]] -> 2.1.01.FORNECEDORES DE MERCADORIAS REVENDA | C53: =Fluxo_de_Caixa_Janeiro[[#This Row],[Janeiro]] -> 450059.19 | D53: =Fluxo_de_Caixa_Janeiro3[[#This Row],[Fevereiro]] -> 400361.57 | E53: =Fluxo_de_Caixa_Janeiro34[[#This Row],[Março]] -> 449846.92 | O53: =SUM(Fluxo_de_Caixa_Janeiro31020[[#This Row],[Janeiro]:[Dezembro]]) -> 1300267.7 | P53: =IFERROR(O53/$O$27,"0,00%") -> 0.45211416 | Q53: 0.63534819 | R53: =IF(Fluxo_de_Caixa_Janeiro31020[[#This Row],[% ACUMULADO 1º Trimes 2026]]<=Fluxo_de_Caixa_Janeiro31020[[#This Row],[% ACUMULADO 1º Trimes 2025]],"VERDADEIRO","FALSO") -> VERDADEIRO | V53: 1709373.8 | W53: 0.63534819
B54: =Fluxo_de_Caixa_Janeiro[[#This Row],[Fluxo de Caixa 2026 CTR]] -> 2.1.02.ADIANT. FORNEC. MERCA. REVENDA | C54: =Fluxo_de_Caixa_Janeiro[[#This Row],[Janeiro]] -> 0 | D54: =Fluxo_de_Caixa_Janeiro3[[#This Row],[Fevereiro]] -> 0 | E54: =Fluxo_de_Caixa_Janeiro34[[#This Row],[Março]] -> 0 | O54: =SUM(Fluxo_de_Caixa_Janeiro31020[[#This Row],[Janeiro]:[Dezembro]]) -> 0 | P54: =IFERROR(O54/$O$27,"0,00%") -> 0 | Q54: 0 | R54: =IF(Fluxo_de_Caixa_Janeiro31020[[#This Row],[% ACUMULADO 1º Trimes 2026]]<=Fluxo_de_Caixa_Janeiro31020[[#This Row],[% ACUMULADO 1º Trimes 2025]],"VERDADEIRO","FALSO") -> VERDADEIRO | V54: 0 | W54: 0
B55: =Fluxo_de_Caixa_Janeiro[[#This Row],[Fluxo de Caixa 2026 CTR]] -> 2.1.03.TRANSPORTADORA MERCA. REVENDA | C55: =Fluxo_de_Caixa_Janeiro[[#This Row],[Janeiro]] -> 10103.47 | D55: =Fluxo_de_Caixa_Janeiro3[[#This Row],[Fevereiro]] -> 19178.54 | E55: =Fluxo_de_Caixa_Janeiro34[[#This Row],[Março]] -> 6643.53 | O55: =SUM(Fluxo_de_Caixa_Janeiro31020[[#This Row],[Janeiro]:[Dezembro]]) -> 35925.54 | P55: =IFERROR(O55/$O$27,"0,00%") -> 0.012491617 | Q55: 0.024186791 | R55: =IF(Fluxo_de_Caixa_Janeiro31020[[#This Row],[% ACUMULADO 1º Trimes 2026]]<=Fluxo_de_Caixa_Janeiro31020[[#This Row],[% ACUMULADO 1º Trimes 2025]],"VERDADEIRO","FALSO") -> VERDADEIRO | V55: 65073.4 | W55: 0.024186791
B56: =Fluxo_de_Caixa_Janeiro[[#This Row],[Fluxo de Caixa 2026 CTR]] -> 2.1.04.OUTROS CUSTOS DE MERC.REVENDA | C56: =Fluxo_de_Caixa_Janeiro[[#This Row],[Janeiro]] -> 480 | D56: =Fluxo_de_Caixa_Janeiro3[[#This Row],[Fevereiro]] -> 0 | E56: =Fluxo_de_Caixa_Janeiro34[[#This Row],[Março]] -> 0 | O56: =SUM(Fluxo_de_Caixa_Janeiro31020[[#This Row],[Janeiro]:[Dezembro]]) -> 480 | P56: =IFERROR(O56/$O$27,"0,00%") -> 0.00016690009 | Q56: 0.00025791206 | R56: =IF(Fluxo_de_Caixa_Janeiro31020[[#This Row],[% ACUMULADO 1º Trimes 2026]]<=Fluxo_de_Caixa_Janeiro31020[[#This Row],[% ACUMULADO 1º Trimes 2025]],"VERDADEIRO","FALSO") -> VERDADEIRO | V56: 693.9 | W56: 0.00025791206
B57: =Fluxo_de_Caixa_Janeiro[[#This Row],[Fluxo de Caixa 2026 CTR]] -> 2.1.05.TRANSFE DE MERCAD REVENDA MATRIZ | C57: =Fluxo_de_Caixa_Janeiro[[#This Row],[Janeiro]] -> 0 | D57: =Fluxo_de_Caixa_Janeiro3[[#This Row],[Fevereiro]] -> 0 | E57: =Fluxo_de_Caixa_Janeiro34[[#This Row],[Março]] -> 0 | O57: =SUM(Fluxo_de_Caixa_Janeiro31020[[#This Row],[Janeiro]:[Dezembro]]) -> 0 | P57: =IFERROR(O57/$O$27,"0,00%") -> 0 | Q57: 0 | R57: =IF(Fluxo_de_Caixa_Janeiro31020[[#This Row],[% ACUMULADO 1º Trimes 2026]]<=Fluxo_de_Caixa_Janeiro31020[[#This Row],[% ACUMULADO 1º Trimes 2025]],"VERDADEIRO","FALSO") -> VERDADEIRO | V57: 0 | W57: 0
B58: =Fluxo_de_Caixa_Janeiro[[#This Row],[Fluxo de Caixa 2026 CTR]] -> 0 | C58: =Fluxo_de_Caixa_Janeiro[[#This Row],[Janeiro]] -> 0 | D58: =Fluxo_de_Caixa_Janeiro3[[#This Row],[Fevereiro]] -> 0 | E58: =Fluxo_de_Caixa_Janeiro34[[#This Row],[Março]] -> 0 | O58: =SUM(Fluxo_de_Caixa_Janeiro31020[[#This Row],[Janeiro]:[Dezembro]]) -> 0 | P58: =IFERROR(O58/$O$27,"0,00%") -> 0 | Q58: 0 | R58: =IF(Fluxo_de_Caixa_Janeiro31020[[#This Row],[% ACUMULADO 1º Trimes 2026]]<=Fluxo_de_Caixa_Janeiro31020[[#This Row],[% ACUMULADO 1º Trimes 2025]],"VERDADEIRO","FALSO") -> VERDADEIRO | V58: 0 | W58: 0
B59: =Fluxo_de_Caixa_Janeiro[[#This Row],[Fluxo de Caixa 2026 CTR]] -> 0 | C59: =Fluxo_de_Caixa_Janeiro[[#This Row],[Janeiro]] -> 0 | D59: =Fluxo_de_Caixa_Janeiro3[[#This Row],[Fevereiro]] -> 0 | E59: =Fluxo_de_Caixa_Janeiro34[[#This Row],[Março]] -> 0 | O59: =SUM(Fluxo_de_Caixa_Janeiro31020[[#This Row],[Janeiro]:[Dezembro]]) -> 0 | P59: =IFERROR(O59/$O$27,"0,00%") -> 0 | Q59: 0 | R59: =IF(Fluxo_de_Caixa_Janeiro31020[[#This Row],[% ACUMULADO 1º Trimes 2026]]<=Fluxo_de_Caixa_Janeiro31020[[#This Row],[% ACUMULADO 1º Trimes 2025]],"VERDADEIRO","FALSO") -> VERDADEIRO | V59: 0 | W59: 0
A60: 2.2. Inadimplência e Perdas | B60: =Fluxo_de_Caixa_Janeiro[[#This Row],[Fluxo de Caixa 2026 CTR]] -> 2.2. Inadimplência e Perdas | C60: =Fluxo_de_Caixa_Janeiro[[#This Row],[Janeiro]] -> 0 | D60: =Fluxo_de_Caixa_Janeiro3[[#This Row],[Fevereiro]] -> -57235.67 | E60: =Fluxo_de_Caixa_Janeiro34[[#This Row],[Março]] -> 0 | O60: =SUM(Fluxo_de_Caixa_Janeiro31020[[#This Row],[Janeiro]:[Dezembro]]) -> -57235.67 | P60: =-IFERROR(O60/$O$27,"0,00") -> 0.019901331 | Q60: 0 | R60: =IF(Fluxo_de_Caixa_Janeiro31020[[#This Row],[% ACUMULADO 1º Trimes 2026]]<=Fluxo_de_Caixa_Janeiro31020[[#This Row],[% ACUMULADO 1º Trimes 2025]],"VERDADEIRO","FALSO") -> FALSO | V60: 0 | W60: 0
B61: =Fluxo_de_Caixa_Janeiro[[#This Row],[Fluxo de Caixa 2026 CTR]] -> 2.2.01.CONTAS PERDIDAS/NÃO PAGAS | C61: =Fluxo_de_Caixa_Janeiro[[#This Row],[Janeiro]] -> 0 | D61: =Fluxo_de_Caixa_Janeiro3[[#This Row],[Fevereiro]] -> 57235.67 | E61: =Fluxo_de_Caixa_Janeiro34[[#This Row],[Março]] -> 0 | O61: =SUM(Fluxo_de_Caixa_Janeiro31020[[#This Row],[Janeiro]:[Dezembro]]) -> 57235.67 | P61: =IFERROR(O61/$O$27,"0,00%") -> 0.019901331 | Q61: 0 | R61: =IF(Fluxo_de_Caixa_Janeiro31020[[#This Row],[% ACUMULADO 1º Trimes 2026]]<=Fluxo_de_Caixa_Janeiro31020[[#This Row],[% ACUMULADO 1º Trimes 2025]],"VERDADEIRO","FALSO") -> FALSO | V61: 0 | W61: 0
B62: =Fluxo_de_Caixa_Janeiro[[#This Row],[Fluxo de Caixa 2026 CTR]] -> 2.2.02.BOLETOS DESCONTADOS DEVOLVIDOS | C62: =Fluxo_de_Caixa_Janeiro[[#This Row],[Janeiro]] -> 0 | D62: =Fluxo_de_Caixa_Janeiro3[[#This Row],[Fevereiro]] -> 0 | E62: =Fluxo_de_Caixa_Janeiro34[[#This Row],[Março]] -> 0 | O62: =SUM(Fluxo_de_Caixa_Janeiro31020[[#This Row],[Janeiro]:[Dezembro]]) -> 0 | P62: =IFERROR(O62/$O$27,"0,00%") -> 0 | Q62: 0 | R62: =IF(Fluxo_de_Caixa_Janeiro31020[[#This Row],[% ACUMULADO 1º Trimes 2026]]<=Fluxo_de_Caixa_Janeiro31020[[#This Row],[% ACUMULADO 1º Trimes 2025]],"VERDADEIRO","FALSO") -> VERDADEIRO | V62: 0 | W62: 0
B63: =Fluxo_de_Caixa_Janeiro[[#This Row],[Fluxo de Caixa 2026 CTR]] -> 2.2.03.CHEQUES DEVOLVIDOS | C63: =Fluxo_de_Caixa_Janeiro[[#This Row],[Janeiro]] -> 0 | D63: =Fluxo_de_Caixa_Janeiro3[[#This Row],[Fevereiro]] -> 0 | E63: =Fluxo_de_Caixa_Janeiro34[[#This Row],[Março]] -> 0 | O63: =SUM(Fluxo_de_Caixa_Janeiro31020[[#This Row],[Janeiro]:[Dezembro]]) -> 0 | P63: =IFERROR(O63/$O$27,"0,00%") -> 0 | Q63: 0 | R63: =IF(Fluxo_de_Caixa_Janeiro31020[[#This Row],[% ACUMULADO 1º Trimes 2026]]<=Fluxo_de_Caixa_Janeiro31020[[#This Row],[% ACUMULADO 1º Trimes 2025]],"VERDADEIRO","FALSO") -> VERDADEIRO | V63: 0 | W63: 0
B64: =Fluxo_de_Caixa_Janeiro[[#This Row],[Fluxo de Caixa 2026 CTR]] -> 2.2.04.BOLETOS DESCONTADOS DEVOLVIDOS | C64: =Fluxo_de_Caixa_Janeiro[[#This Row],[Janeiro]] -> 0 | D64: =Fluxo_de_Caixa_Janeiro3[[#This Row],[Fevereiro]] -> 0 | E64: =Fluxo_de_Caixa_Janeiro34[[#This Row],[Março]] -> 0 | O64: =SUM(Fluxo_de_Caixa_Janeiro31020[[#This Row],[Janeiro]:[Dezembro]]) -> 0 | P64: =IFERROR(O64/$O$27,"0,00%") -> 0 | Q64: 0 | R64: =IF(Fluxo_de_Caixa_Janeiro31020[[#This Row],[% ACUMULADO 1º Trimes 2026]]<=Fluxo_de_Caixa_Janeiro31020[[#This Row],[% ACUMULADO 1º Trimes 2025]],"VERDADEIRO","FALSO") -> VERDADEIRO | V64: 0 | W64: 0
B65: =Fluxo_de_Caixa_Janeiro[[#This Row],[Fluxo de Caixa 2026 CTR]] -> 2.2.05.PERDA, ROUBO E DETERIORAÇÃO | C65: =Fluxo_de_Caixa_Janeiro[[#This Row],[Janeiro]] -> 0 | D65: =Fluxo_de_Caixa_Janeiro3[[#This Row],[Fevereiro]] -> 0 | E65: =Fluxo_de_Caixa_Janeiro34[[#This Row],[Março]] -> 0 | O65: =SUM(Fluxo_de_Caixa_Janeiro31020[[#This Row],[Janeiro]:[Dezembro]]) -> 0 | P65: =IFERROR(O65/$O$27,"0,00%") -> 0 | Q65: 0 | R65: =IF(Fluxo_de_Caixa_Janeiro31020[[#This Row],[% ACUMULADO 1º Trimes 2026]]<=Fluxo_de_Caixa_Janeiro31020[[#This Row],[% ACUMULADO 1º Trimes 2025]],"VERDADEIRO","FALSO") -> VERDADEIRO | V65: 0 | W65: 0
B66: =Fluxo_de_Caixa_Janeiro[[#This Row],[Fluxo de Caixa 2026 CTR]] -> 0 | C66: =Fluxo_de_Caixa_Janeiro[[#This Row],[Janeiro]] -> 0 | D66: =Fluxo_de_Caixa_Janeiro3[[#This Row],[Fevereiro]] -> 0 | E66: =Fluxo_de_Caixa_Janeiro34[[#This Row],[Março]] -> 0 | O66: =SUM(Fluxo_de_Caixa_Janeiro31020[[#This Row],[Janeiro]:[Dezembro]]) -> 0 | P66: =IFERROR(O66/$O$27,"0,00%") -> 0 | Q66: 0 | R66: =IF(Fluxo_de_Caixa_Janeiro31020[[#This Row],[% ACUMULADO 1º Trimes 2026]]<=Fluxo_de_Caixa_Janeiro31020[[#This Row],[% ACUMULADO 1º Trimes 2025]],"VERDADEIRO","FALSO") -> VERDADEIRO | V66: 0 | W66: 0
B67: =Fluxo_de_Caixa_Janeiro[[#This Row],[Fluxo de Caixa 2026 CTR]] -> 0 | C67: =Fluxo_de_Caixa_Janeiro[[#This Row],[Janeiro]] -> 0 | D67: =Fluxo_de_Caixa_Janeiro3[[#This Row],[Fevereiro]] -> 0 | E67: =Fluxo_de_Caixa_Janeiro34[[#This Row],[Março]] -> 0 | O67: =SUM(Fluxo_de_Caixa_Janeiro31020[[#This Row],[Janeiro]:[Dezembro]]) -> 0 | P67: =IFERROR(O67/$O$27,"0,00%") -> 0 | Q67: 0 | R67: =IF(Fluxo_de_Caixa_Janeiro31020[[#This Row],[% ACUMULADO 1º Trimes 2026]]<=Fluxo_de_Caixa_Janeiro31020[[#This Row],[% ACUMULADO 1º Trimes 2025]],"VERDADEIRO","FALSO") -> VERDADEIRO | V67: 0 | W67: 0
B68: =Fluxo_de_Caixa_Janeiro[[#This Row],[Fluxo de Caixa 2026 CTR]] -> 0 | C68: =Fluxo_de_Caixa_Janeiro[[#This Row],[Janeiro]] -> 0 | D68: =Fluxo_de_Caixa_Janeiro3[[#This Row],[Fevereiro]] -> 0 | E68: =Fluxo_de_Caixa_Janeiro34[[#This Row],[Março]] -> 0 | O68: =SUM(Fluxo_de_Caixa_Janeiro31020[[#This Row],[Janeiro]:[Dezembro]]) -> 0 | P68: =IFERROR(O68/$O$27,"0,00%") -> 0 | Q68: 0 | R68: =IF(Fluxo_de_Caixa_Janeiro31020[[#This Row],[% ACUMULADO 1º Trimes 2026]]<=Fluxo_de_Caixa_Janeiro31020[[#This Row],[% ACUMULADO 1º Trimes 2025]],"VERDADEIRO","FALSO") -> VERDADEIRO | V68: 0 | W68: 0
B69: =Fluxo_de_Caixa_Janeiro[[#This Row],[Fluxo de Caixa 2026 CTR]] -> 0 | C69: =Fluxo_de_Caixa_Janeiro[[#This Row],[Janeiro]] -> 0 | D69: =Fluxo_de_Caixa_Janeiro3[[#This Row],[Fevereiro]] -> 0 | E69: =Fluxo_de_Caixa_Janeiro34[[#This Row],[Março]] -> 0 | O69: =SUM(Fluxo_de_Caixa_Janeiro31020[[#This Row],[Janeiro]:[Dezembro]]) -> 0 | P69: =IFERROR(O69/$O$27,"0,00%") -> 0 | Q69: 0 | R69: =IF(Fluxo_de_Caixa_Janeiro31020[[#This Row],[% ACUMULADO 1º Trimes 2026]]<=Fluxo_de_Caixa_Janeiro31020[[#This Row],[% ACUMULADO 1º Trimes 2025]],"VERDADEIRO","FALSO") -> VERDADEIRO | V69: 0 | W69: 0
A70: 2.3. Impostos | B70: =Fluxo_de_Caixa_Janeiro[[#This Row],[Fluxo de Caixa 2026 CTR]] -> 2.3. Impostos | C70: =Fluxo_de_Caixa_Janeiro[[#This Row],[Janeiro]] -> -57986.56 | D70: =Fluxo_de_Caixa_Janeiro3[[#This Row],[Fevereiro]] -> -176996.86 | E70: =Fluxo_de_Caixa_Janeiro34[[#This Row],[Março]] -> -73559.85 | O70: =SUM(Fluxo_de_Caixa_Janeiro31020[[#This Row],[Janeiro]:[Dezembro]]) -> -308543.27 | P70: =-IFERROR(O70/$O$27,"0,00") -> 0.10728313 | Q70: 0.073746792 | R70: =IF(Fluxo_de_Caixa_Janeiro31020[[#This Row],[% ACUMULADO 1º Trimes 2026]]<=Fluxo_de_Caixa_Janeiro31020[[#This Row],[% ACUMULADO 1º Trimes 2025]],"VERDADEIRO","FALSO") -> FALSO | V70: -198412.2 | W70: 0.073746792
B71: =Fluxo_de_Caixa_Janeiro[[#This Row],[Fluxo de Caixa 2026 CTR]] -> 0 | C71: =Fluxo_de_Caixa_Janeiro[[#This Row],[Janeiro]] -> 0 | D71: =Fluxo_de_Caixa_Janeiro3[[#This Row],[Fevereiro]] -> 0 | E71: =Fluxo_de_Caixa_Janeiro34[[#This Row],[Março]] -> 0 | O71: =SUM(Fluxo_de_Caixa_Janeiro31020[[#This Row],[Janeiro]:[Dezembro]]) -> 0 | P71: =IFERROR(O71/$O$27,"0,00%") -> 0 | Q71: 0 | R71: =IF(Fluxo_de_Caixa_Janeiro31020[[#This Row],[% ACUMULADO 1º Trimes 2026]]<=Fluxo_de_Caixa_Janeiro31020[[#This Row],[% ACUMULADO 1º Trimes 2025]],"VERDADEIRO","FALSO") -> VERDADEIRO | V71: 0 | W71: 0
B72: =Fluxo_de_Caixa_Janeiro[[#This Row],[Fluxo de Caixa 2026 CTR]] -> 2.3.02.IRPJ (SE ESTIVER NO CMV) | C72: =Fluxo_de_Caixa_Janeiro[[#This Row],[Janeiro]] -> 0 | D72: =Fluxo_de_Caixa_Janeiro3[[#This Row],[Fevereiro]] -> 50219.25 | E72: =Fluxo_de_Caixa_Janeiro34[[#This Row],[Março]] -> 0 | O72: =SUM(Fluxo_de_Caixa_Janeiro31020[[#This Row],[Janeiro]:[Dezembro]]) -> 50219.25 | P72: =IFERROR(O72/$O$27,"0,00%") -> 0.017461662 | Q72: 0.0049610178 | R72: =IF(Fluxo_de_Caixa_Janeiro31020[[#This Row],[% ACUMULADO 1º Trimes 2026]]<=Fluxo_de_Caixa_Janeiro31020[[#This Row],[% ACUMULADO 1º Trimes 2025]],"VERDADEIRO","FALSO") -> FALSO | V72: 13347.38 | W72: 0.0049610178
B73: =Fluxo_de_Caixa_Janeiro[[#This Row],[Fluxo de Caixa 2026 CTR]] -> 2.3.03.CSSL (SE ESTIVER NO CMV) | C73: =Fluxo_de_Caixa_Janeiro[[#This Row],[Janeiro]] -> 0 | D73: =Fluxo_de_Caixa_Janeiro3[[#This Row],[Fevereiro]] -> 30668.76 | E73: =Fluxo_de_Caixa_Janeiro34[[#This Row],[Março]] -> 0 | O73: =SUM(Fluxo_de_Caixa_Janeiro31020[[#This Row],[Janeiro]:[Dezembro]]) -> 30668.76 | P73: =IFERROR(O73/$O$27,"0,00%") -> 0.010663789 | Q73: 0.0030803672 | R73: =IF(Fluxo_de_Caixa_Janeiro31020[[#This Row],[% ACUMULADO 1º Trimes 2026]]<=Fluxo_de_Caixa_Janeiro31020[[#This Row],[% ACUMULADO 1º Trimes 2025]],"VERDADEIRO","FALSO") -> FALSO | V73: 8287.58 | W73: 0.0030803672
B74: =Fluxo_de_Caixa_Janeiro[[#This Row],[Fluxo de Caixa 2026 CTR]] -> 2.3.04.COFINS (SE ESTIVER NO CMV) | C74: =Fluxo_de_Caixa_Janeiro[[#This Row],[Janeiro]] -> 12167.71 | D74: =Fluxo_de_Caixa_Janeiro3[[#This Row],[Fevereiro]] -> 0 | E74: =Fluxo_de_Caixa_Janeiro34[[#This Row],[Março]] -> 0 | O74: =SUM(Fluxo_de_Caixa_Janeiro31020[[#This Row],[Janeiro]:[Dezembro]]) -> 12167.71 | P74: =IFERROR(O74/$O$27,"0,00%") -> 0.0042308166 | Q74: 0.015811686 | R74: =IF(Fluxo_de_Caixa_Janeiro31020[[#This Row],[% ACUMULADO 1º Trimes 2026]]<=Fluxo_de_Caixa_Janeiro31020[[#This Row],[% ACUMULADO 1º Trimes 2025]],"VERDADEIRO","FALSO") -> VERDADEIRO | V74: 42540.58 | W74: 0.015811686
B75: =Fluxo_de_Caixa_Janeiro[[#This Row],[Fluxo de Caixa 2026 CTR]] -> 2.3.05.PIS (SE ESTIVER NO CMV) | C75: =Fluxo_de_Caixa_Janeiro[[#This Row],[Janeiro]] -> 2636.34 | D75: =Fluxo_de_Caixa_Janeiro3[[#This Row],[Fevereiro]] -> 0 | E75: =Fluxo_de_Caixa_Janeiro34[[#This Row],[Março]] -> 0 | O75: =SUM(Fluxo_de_Caixa_Janeiro31020[[#This Row],[Janeiro]:[Dezembro]]) -> 2636.34 | P75: =IFERROR(O75/$O$27,"0,00%") -> 0.00091667791 | Q75: 0.0034258668 | R75: =IF(Fluxo_de_Caixa_Janeiro31020[[#This Row],[% ACUMULADO 1º Trimes 2026]]<=Fluxo_de_Caixa_Janeiro31020[[#This Row],[% ACUMULADO 1º Trimes 2025]],"VERDADEIRO","FALSO") -> VERDADEIRO | V75: 9217.13 | W75: 0.0034258668
B76: =Fluxo_de_Caixa_Janeiro[[#This Row],[Fluxo de Caixa 2026 CTR]] -> 2.3.06.ICMS – Normal (SE ESTIVER NO CMV) | C76: =Fluxo_de_Caixa_Janeiro[[#This Row],[Janeiro]] -> 20443.12 | D76: =Fluxo_de_Caixa_Janeiro3[[#This Row],[Fevereiro]] -> 66402.54 | E76: =Fluxo_de_Caixa_Janeiro34[[#This Row],[Março]] -> 43499.63 | O76: =SUM(Fluxo_de_Caixa_Janeiro31020[[#This Row],[Janeiro]:[Dezembro]]) -> 130345.29 | P76: =IFERROR(O76/$O$27,"0,00%") -> 0.045322169 | Q76: 0.026927346 | R76: =IF(Fluxo_de_Caixa_Janeiro31020[[#This Row],[% ACUMULADO 1º Trimes 2026]]<=Fluxo_de_Caixa_Janeiro31020[[#This Row],[% ACUMULADO 1º Trimes 2025]],"VERDADEIRO","FALSO") -> FALSO | V76: 72446.73 | W76: 0.026927346
B77: =Fluxo_de_Caixa_Janeiro[[#This Row],[Fluxo de Caixa 2026 CTR]] -> 2.3.07. SUBSTITUIÇÃO TRIBUTARIA SAÍDA (TARE) | C77: =Fluxo_de_Caixa_Janeiro[[#This Row],[Janeiro]] -> 10059.1 | D77: =Fluxo_de_Caixa_Janeiro3[[#This Row],[Fevereiro]] -> 13988.27 | E77: =Fluxo_de_Caixa_Janeiro34[[#This Row],[Março]] -> 14279.93 | O77: =SUM(Fluxo_de_Caixa_Janeiro31020[[#This Row],[Janeiro]:[Dezembro]]) -> 38327.3 | P77: =IFERROR(O77/$O$27,"0,00%") -> 0.013326729 | Q77: 0.0065528991 | R77: =IF(Fluxo_de_Caixa_Janeiro31020[[#This Row],[% ACUMULADO 1º Trimes 2026]]<=Fluxo_de_Caixa_Janeiro31020[[#This Row],[% ACUMULADO 1º Trimes 2025]],"VERDADEIRO","FALSO") -> FALSO | V77: 17630.26 | W77: 0.0065528991
B78: =Fluxo_de_Caixa_Janeiro[[#This Row],[Fluxo de Caixa 2026 CTR]] -> 2.3.08.SUBSTITUIÇÃO TRIBUTÁRIA NA ENTRADA | C78: =Fluxo_de_Caixa_Janeiro[[#This Row],[Janeiro]] -> 0 | D78: =Fluxo_de_Caixa_Janeiro3[[#This Row],[Fevereiro]] -> 0 | E78: =Fluxo_de_Caixa_Janeiro34[[#This Row],[Março]] -> 0 | O78: =SUM(Fluxo_de_Caixa_Janeiro31020[[#This Row],[Janeiro]:[Dezembro]]) -> 0 | P78: =IFERROR(O78/$O$27,"0,00%") -> 0 | Q78: 0 | R78: =IF(Fluxo_de_Caixa_Janeiro31020[[#This Row],[% ACUMULADO 1º Trimes 2026]]<=Fluxo_de_Caixa_Janeiro31020[[#This Row],[% ACUMULADO 1º Trimes 2025]],"VERDADEIRO","FALSO") -> VERDADEIRO | V78: 0 | W78: 0
B79: =Fluxo_de_Caixa_Janeiro[[#This Row],[Fluxo de Caixa 2026 CTR]] -> 2.3.09.FUNDO DESENVOLVIMENTO ECONOMICO (TARE) | C79: =Fluxo_de_Caixa_Janeiro[[#This Row],[Janeiro]] -> 117.55 | D79: =Fluxo_de_Caixa_Janeiro3[[#This Row],[Fevereiro]] -> 204.79 | E79: =Fluxo_de_Caixa_Janeiro34[[#This Row],[Março]] -> 163.42 | O79: =SUM(Fluxo_de_Caixa_Janeiro31020[[#This Row],[Janeiro]:[Dezembro]]) -> 485.76 | P79: =IFERROR(O79/$O$27,"0,00%") -> 0.0001689029 | Q79: 0.00017588123 | R79: =IF(Fluxo_de_Caixa_Janeiro31020[[#This Row],[% ACUMULADO 1º Trimes 2026]]<=Fluxo_de_Caixa_Janeiro31020[[#This Row],[% ACUMULADO 1º Trimes 2025]],"VERDADEIRO","FALSO") -> VERDADEIRO | V79: 473.2 | W79: 0.00017588123
B80: =Fluxo_de_Caixa_Janeiro[[#This Row],[Fluxo de Caixa 2026 CTR]] -> 0 | C80: =Fluxo_de_Caixa_Janeiro[[#This Row],[Janeiro]] -> 0 | D80: =Fluxo_de_Caixa_Janeiro3[[#This Row],[Fevereiro]] -> 0 | E80: =Fluxo_de_Caixa_Janeiro34[[#This Row],[Março]] -> 0 | O80: =SUM(Fluxo_de_Caixa_Janeiro31020[[#This Row],[Janeiro]:[Dezembro]]) -> 0 | P80: =IFERROR(O80/$O$27,"0,00%") -> 0 | Q80: 0 | R80: =IF(Fluxo_de_Caixa_Janeiro31020[[#This Row],[% ACUMULADO 1º Trimes 2026]]<=Fluxo_de_Caixa_Janeiro31020[[#This Row],[% ACUMULADO 1º Trimes 2025]],"VERDADEIRO","FALSO") -> VERDADEIRO | V80: 0 | W80: 0
B81: =Fluxo_de_Caixa_Janeiro[[#This Row],[Fluxo de Caixa 2026 CTR]] -> 0 | C81: =Fluxo_de_Caixa_Janeiro[[#This Row],[Janeiro]] -> 0 | D81: =Fluxo_de_Caixa_Janeiro3[[#This Row],[Fevereiro]] -> 0 | E81: =Fluxo_de_Caixa_Janeiro34[[#This Row],[Março]] -> 0 | O81: =SUM(Fluxo_de_Caixa_Janeiro31020[[#This Row],[Janeiro]:[Dezembro]]) -> 0 | P81: =IFERROR(O81/$O$27,"0,00%") -> 0 | Q81: 0 | R81: =IF(Fluxo_de_Caixa_Janeiro31020[[#This Row],[% ACUMULADO 1º Trimes 2026]]<=Fluxo_de_Caixa_Janeiro31020[[#This Row],[% ACUMULADO 1º Trimes 2025]],"VERDADEIRO","FALSO") -> VERDADEIRO | V81: 0 | W81: 0
B82: =Fluxo_de_Caixa_Janeiro[[#This Row],[Fluxo de Caixa 2026 CTR]] -> 2.3.11. Impostos Parcelado | C82: =Fluxo_de_Caixa_Janeiro[[#This Row],[Janeiro]] -> 12562.74 | D82: =Fluxo_de_Caixa_Janeiro3[[#This Row],[Fevereiro]] -> 15513.25 | E82: =Fluxo_de_Caixa_Janeiro34[[#This Row],[Março]] -> 15616.87 | O82: =SUM(Fluxo_de_Caixa_Janeiro31020[[#This Row],[Janeiro]:[Dezembro]]) -> 43692.86 | P82: =IFERROR(O82/$O$27,"0,00%") -> 0.01519238 | Q82: 0.012811729 | R82: =IF(Fluxo_de_Caixa_Janeiro31020[[#This Row],[% ACUMULADO 1º Trimes 2026]]<=Fluxo_de_Caixa_Janeiro31020[[#This Row],[% ACUMULADO 1º Trimes 2025]],"VERDADEIRO","FALSO") -> FALSO | V82: 34469.34 | W82: 0.012811729
... B84: =Fluxo_de_Caixa_Janeiro[[#This Row],[Fluxo de Caixa 2026 CTR]] -> 0 | C84: =Fluxo_de_Caixa_Janeiro[[#This Row],[Janeiro]] -> 0 | D84: =Fluxo_de_Caixa_Janeiro3[[#This Row],[Fevereiro]] -> 0 | E84: =Fluxo_de_Caixa_Janeiro34[[#This Row],[Março]] -> 0 | O84: =SUM(Fluxo_de_Caixa_Janeiro31020[[#This Row],[Janeiro]:[Dezembro]]) -> 0 | P84: =IFERROR(O84/$O$27,"0,00%") -> 0 | Q84: 0 | R84: =IF(Fluxo_de_Caixa_Janeiro31020[[#This Row],[% ACUMULADO 1º Trimes 2026]]<=Fluxo_de_Caixa_Janeiro31020[[#This Row],[% ACUMULADO 1º Trimes 2025]],"VERDADEIRO","FALSO") -> VERDADEIRO | V84: 0 | W84: 0
B85: =Fluxo_de_Caixa_Janeiro[[#This Row],[Fluxo de Caixa 2026 CTR]] -> Total dos Custos | C85: =Fluxo_de_Caixa_Janeiro[[#This Row],[Janeiro]] -> -518629.22 | D85: =Fluxo_de_Caixa_Janeiro3[[#This Row],[Fevereiro]] -> -653772.64 | E85: =Fluxo_de_Caixa_Janeiro34[[#This Row],[Março]] -> -530050.3 | O85: =SUM(Fluxo_de_Caixa_Janeiro31020[[#This Row],[Janeiro]:[Dezembro]]) -> -1702452.2 | P85: =IFERROR(O85/O27,"0,00%") -> -0.59195714 | Q85: -0.73353968 | R85: =IF(Fluxo_de_Caixa_Janeiro31020[[#This Row],[% ACUMULADO 1º Trimes 2026]]>=Fluxo_de_Caixa_Janeiro31020[[#This Row],[% ACUMULADO 1º Trimes 2025]],"VERDADEIRO","FALSO") -> VERDADEIRO | V85: -1973553.3 | W85: -0.73353968
B86: =Fluxo_de_Caixa_Janeiro[[#This Row],[Fluxo de Caixa 2026 CTR]] -> Receita Operacional Bruta | C86: =Fluxo_de_Caixa_Janeiro[[#This Row],[Janeiro]] -> 231003.71 | D86: =Fluxo_de_Caixa_Janeiro3[[#This Row],[Fevereiro]] -> 384816.45 | E86: =Fluxo_de_Caixa_Janeiro34[[#This Row],[Março]] -> 557699.69 | O86: =SUM(Fluxo_de_Caixa_Janeiro31020[[#This Row],[Janeiro]:[Dezembro]]) -> 1173519.8 | P86: =IFERROR(O86/O27,"0,00%") -> 0.40804286 | Q86: 0.26646032 | R86: =IF(Fluxo_de_Caixa_Janeiro31020[[#This Row],[% ACUMULADO 1º Trimes 2026]]>=Fluxo_de_Caixa_Janeiro31020[[#This Row],[% ACUMULADO 1º Trimes 2025]],"VERDADEIRO","FALSO") -> VERDADEIRO | V86: 716898.68 | W86: 0.26646032
B87: =Fluxo_de_Caixa_Janeiro[[#This Row],[Fluxo de Caixa 2026 CTR]] -> 300. Despesas Operac. Fixas e Variáveis | C87: =Fluxo_de_Caixa_Janeiro[[#This Row],[Janeiro]] -> 0 | D87: =Fluxo_de_Caixa_Janeiro3[[#This Row],[Fevereiro]] -> 0 | E87: =Fluxo_de_Caixa_Janeiro34[[#This Row],[Março]] -> 0 | R87: =IF(Fluxo_de_Caixa_Janeiro31020[[#This Row],[% ACUMULADO 1º Trimes 2026]]<=Fluxo_de_Caixa_Janeiro31020[[#This Row],[% ACUMULADO 1º Trimes 2025]],"VERDADEIRO","FALSO") -> VERDADEIRO
A88: 3.1. DESPESA COM VENDAS | B88: =Fluxo_de_Caixa_Janeiro[[#This Row],[Fluxo de Caixa 2026 CTR]] -> 3.1. DESPESA COM VENDAS | C88: =Fluxo_de_Caixa_Janeiro[[#This Row],[Janeiro]] -> -60045.89 | D88: =Fluxo_de_Caixa_Janeiro3[[#This Row],[Fevereiro]] -> -74448.1 | E88: =Fluxo_de_Caixa_Janeiro34[[#This Row],[Março]] -> -50419.47 | O88: =SUM(Fluxo_de_Caixa_Janeiro31020[[#This Row],[Janeiro]:[Dezembro]]) -> -184913.46 | P88: =-IFERROR(O88/$O$27,"0,00") -> 0.064295987 | Q88: 0.033303609 | R88: =IF(Fluxo_de_Caixa_Janeiro31020[[#This Row],[% ACUMULADO 1º Trimes 2026]]<=Fluxo_de_Caixa_Janeiro31020[[#This Row],[% ACUMULADO 1º Trimes 2025]],"VERDADEIRO","FALSO") -> FALSO | V88: -89601.76 | W88: 0.033303609
B89: =Fluxo_de_Caixa_Janeiro[[#This Row],[Fluxo de Caixa 2026 CTR]] -> 3.1.01. Marketing e Propaganda | C89: =Fluxo_de_Caixa_Janeiro[[#This Row],[Janeiro]] -> 2535 | D89: =Fluxo_de_Caixa_Janeiro3[[#This Row],[Fevereiro]] -> 2535 | E89: =Fluxo_de_Caixa_Janeiro34[[#This Row],[Março]] -> 2535 | O89: =SUM(Fluxo_de_Caixa_Janeiro31020[[#This Row],[Janeiro]:[Dezembro]]) -> 7605 | P89: =IFERROR(O89/$O$27,"0,00%") -> 0.0026443234 | Q89: 0.002656654 | R89: =IF(Fluxo_de_Caixa_Janeiro31020[[#This Row],[% ACUMULADO 1º Trimes 2026]]<=Fluxo_de_Caixa_Janeiro31020[[#This Row],[% ACUMULADO 1º Trimes 2025]],"VERDADEIRO","FALSO") -> VERDADEIRO | V89: 7147.6 | W89: 0.002656654
B90: =Fluxo_de_Caixa_Janeiro[[#This Row],[Fluxo de Caixa 2026 CTR]] -> 3.1.02. Promoções e Eventos(Brindes/Café da Manhã p clientes/etc) | C90: =Fluxo_de_Caixa_Janeiro[[#This Row],[Janeiro]] -> 0 | D90: =Fluxo_de_Caixa_Janeiro3[[#This Row],[Fevereiro]] -> 0 | E90: =Fluxo_de_Caixa_Janeiro34[[#This Row],[Março]] -> 0 | O90: =SUM(Fluxo_de_Caixa_Janeiro31020[[#This Row],[Janeiro]:[Dezembro]]) -> 0 | P90: =IFERROR(O90/$O$27,"0,00%") -> 0 | Q90: 0.0026389618 | R90: =IF(Fluxo_de_Caixa_Janeiro31020[[#This Row],[% ACUMULADO 1º Trimes 2026]]<=Fluxo_de_Caixa_Janeiro31020[[#This Row],[% ACUMULADO 1º Trimes 2025]],"VERDADEIRO","FALSO") -> VERDADEIRO | V90: 7100 | W90: 0.0026389618
B91: =Fluxo_de_Caixa_Janeiro[[#This Row],[Fluxo de Caixa 2026 CTR]] -> 3.1.03. Sacolas e Embalagens | C91: =Fluxo_de_Caixa_Janeiro[[#This Row],[Janeiro]] -> 0 | D91: =Fluxo_de_Caixa_Janeiro3[[#This Row],[Fevereiro]] -> 0 | E91: =Fluxo_de_Caixa_Janeiro34[[#This Row],[Março]] -> 303.29 | O91: =SUM(Fluxo_de_Caixa_Janeiro31020[[#This Row],[Janeiro]:[Dezembro]]) -> 303.29 | P91: =IFERROR(O91/$O$27,"0,00%") -> 0.00010545652 | Q91: 0.00047520269 | R91: =IF(Fluxo_de_Caixa_Janeiro31020[[#This Row],[% ACUMULADO 1º Trimes 2026]]<=Fluxo_de_Caixa_Janeiro31020[[#This Row],[% ACUMULADO 1º Trimes 2025]],"VERDADEIRO","FALSO") -> VERDADEIRO | V91: 1278.51 | W91: 0.00047520269
B92: =Fluxo_de_Caixa_Janeiro[[#This Row],[Fluxo de Caixa 2026 CTR]] -> 3.1.04.DIARIAS E DESPESAS COM VENDEDOR (passagem ônibus, hotel. Etc) | C92: =Fluxo_de_Caixa_Janeiro[[#This Row],[Janeiro]] -> 0 | D92: =Fluxo_de_Caixa_Janeiro3[[#This Row],[Fevereiro]] -> 0 | E92: =Fluxo_de_Caixa_Janeiro34[[#This Row],[Março]] -> 0 | O92: =SUM(Fluxo_de_Caixa_Janeiro31020[[#This Row],[Janeiro]:[Dezembro]]) -> 0 | P92: =IFERROR(O92/$O$27,"0,00%") -> 0 | Q92: 0.001506587 | R92: =IF(Fluxo_de_Caixa_Janeiro31020[[#This Row],[% ACUMULADO 1º Trimes 2026]]<=Fluxo_de_Caixa_Janeiro31020[[#This Row],[% ACUMULADO 1º Trimes 2025]],"VERDADEIRO","FALSO") -> VERDADEIRO | V92: 4053.4 | W92: 0.001506587
B93: =Fluxo_de_Caixa_Janeiro[[#This Row],[Fluxo de Caixa 2026 CTR]] -> 3.1.05. Comissão Representente Comercial | C93: =Fluxo_de_Caixa_Janeiro[[#This Row],[Janeiro]] -> 34232.57 | D93: =Fluxo_de_Caixa_Janeiro3[[#This Row],[Fevereiro]] -> 57815.85 | E93: =Fluxo_de_Caixa_Janeiro34[[#This Row],[Março]] -> 34661.59 | O93: =SUM(Fluxo_de_Caixa_Janeiro31020[[#This Row],[Janeiro]:[Dezembro]]) -> 126710.01 | P93: =IFERROR(O93/$O$27,"0,00%") -> 0.044058151 | Q93: 0.021591941 | R93: =IF(Fluxo_de_Caixa_Janeiro31020[[#This Row],[% ACUMULADO 1º Trimes 2026]]<=Fluxo_de_Caixa_Janeiro31020[[#This Row],[% ACUMULADO 1º Trimes 2025]],"VERDADEIRO","FALSO") -> FALSO | V93: 58092.08 | W93: 0.021591941
B94: =Fluxo_de_Caixa_Janeiro[[#This Row],[Fluxo de Caixa 2026 CTR]] -> 3.1.06. Frete com entrega de vendas | C94: =Fluxo_de_Caixa_Janeiro[[#This Row],[Janeiro]] -> 5767.8 | D94: =Fluxo_de_Caixa_Janeiro3[[#This Row],[Fevereiro]] -> 5208.04 | E94: =Fluxo_de_Caixa_Janeiro34[[#This Row],[Março]] -> 5007.88 | O94: =SUM(Fluxo_de_Caixa_Janeiro31020[[#This Row],[Janeiro]:[Dezembro]]) -> 15983.72 | P94: =IFERROR(O94/$O$27,"0,00%") -> 0.0055576758 | Q94: 0.0029174392 | R94: =IF(Fluxo_de_Caixa_Janeiro31020[[#This Row],[% ACUMULADO 1º Trimes 2026]]<=Fluxo_de_Caixa_Janeiro31020[[#This Row],[% ACUMULADO 1º Trimes 2025]],"VERDADEIRO","FALSO") -> FALSO | V94: 7849.23 | W94: 0.0029174392
B95: =Fluxo_de_Caixa_Janeiro[[#This Row],[Fluxo de Caixa 2026 CTR]] -> 3.1.07. TAXAS C/ CART CRÉD/DÉBIT | C95: =Fluxo_de_Caixa_Janeiro[[#This Row],[Janeiro]] -> 17461.46 | D95: =Fluxo_de_Caixa_Janeiro3[[#This Row],[Fevereiro]] -> 8832.21 | E95: =Fluxo_de_Caixa_Janeiro34[[#This Row],[Março]] -> 7791.25 | O95: =SUM(Fluxo_de_Caixa_Janeiro31020[[#This Row],[Janeiro]:[Dezembro]]) -> 34084.92 | P95: =IFERROR(O95/$O$27,"0,00%") -> 0.011851617 | Q95: 0.0015168232 | R95: =IF(Fluxo_de_Caixa_Janeiro31020[[#This Row],[% ACUMULADO 1º Trimes 2026]]<=Fluxo_de_Caixa_Janeiro31020[[#This Row],[% ACUMULADO 1º Trimes 2025]],"VERDADEIRO","FALSO") -> FALSO | V95: 4080.94 | W95: 0.0015168232
B96: =Fluxo_de_Caixa_Janeiro[[#This Row],[Fluxo de Caixa 2026 CTR]] -> 3.1.08. Serviço Motoboy Entrega Vendas | C96: =Fluxo_de_Caixa_Janeiro[[#This Row],[Janeiro]] -> 0 | D96: =Fluxo_de_Caixa_Janeiro3[[#This Row],[Fevereiro]] -> 0 | E96: =Fluxo_de_Caixa_Janeiro34[[#This Row],[Março]] -> 0 | O96: =SUM(Fluxo_de_Caixa_Janeiro31020[[#This Row],[Janeiro]:[Dezembro]]) -> 0 | P96: =IFERROR(O96/$O$27,"0,00%") -> 0 | Q96: 0 | R96: =IF(Fluxo_de_Caixa_Janeiro31020[[#This Row],[% ACUMULADO 1º Trimes 2026]]<=Fluxo_de_Caixa_Janeiro31020[[#This Row],[% ACUMULADO 1º Trimes 2025]],"VERDADEIRO","FALSO") -> VERDADEIRO | V96: 0 | W96: 0
B97: =Fluxo_de_Caixa_Janeiro[[#This Row],[Fluxo de Caixa 2026 CTR]] -> 3.1.09. PGTO DISTRATO REPRES COMERCIAL | C97: =Fluxo_de_Caixa_Janeiro[[#This Row],[Janeiro]] -> 0 | D97: =Fluxo_de_Caixa_Janeiro3[[#This Row],[Fevereiro]] -> 0 | E97: =Fluxo_de_Caixa_Janeiro34[[#This Row],[Março]] -> 0 | O97: =SUM(Fluxo_de_Caixa_Janeiro31020[[#This Row],[Janeiro]:[Dezembro]]) -> 0 | P97: =IFERROR(O97/$O$27,"0,00%") -> 0 | Q97: 0 | R97: =IF(Fluxo_de_Caixa_Janeiro31020[[#This Row],[% ACUMULADO 1º Trimes 2026]]<=Fluxo_de_Caixa_Janeiro31020[[#This Row],[% ACUMULADO 1º Trimes 2025]],"VERDADEIRO","FALSO") -> VERDADEIRO | V97: 0 | W97: 0
B98: =Fluxo_de_Caixa_Janeiro[[#This Row],[Fluxo de Caixa 2026 CTR]] -> 3.1.10. TARIFA PIX RECEBIDO | C98: =Fluxo_de_Caixa_Janeiro[[#This Row],[Janeiro]] -> 49.06 | D98: =Fluxo_de_Caixa_Janeiro3[[#This Row],[Fevereiro]] -> 57 | E98: =Fluxo_de_Caixa_Janeiro34[[#This Row],[Março]] -> 120.46 | O98: =SUM(Fluxo_de_Caixa_Janeiro31020[[#This Row],[Janeiro]:[Dezembro]]) -> 226.52 | P98: =IFERROR(O98/$O$27,"0,00%") -> 7.8762936e-05 | Q98: 0 | R98: =IF(Fluxo_de_Caixa_Janeiro31020[[#This Row],[% ACUMULADO 1º Trimes 2026]]<=Fluxo_de_Caixa_Janeiro31020[[#This Row],[% ACUMULADO 1º Trimes 2025]],"VERDADEIRO","FALSO") -> FALSO | V98: 0 | W98: 0
B99: =Fluxo_de_Caixa_Janeiro[[#This Row],[Fluxo de Caixa 2026 CTR]] -> 0 | C99: =Fluxo_de_Caixa_Janeiro[[#This Row],[Janeiro]] -> 0 | D99: =Fluxo_de_Caixa_Janeiro3[[#This Row],[Fevereiro]] -> 0 | E99: =Fluxo_de_Caixa_Janeiro34[[#This Row],[Março]] -> 0 | O99: =SUM(Fluxo_de_Caixa_Janeiro31020[[#This Row],[Janeiro]:[Dezembro]]) -> 0 | P99: =IFERROR(O99/$O$27,"0,00%") -> 0 | Q99: 0 | R99: =IF(Fluxo_de_Caixa_Janeiro31020[[#This Row],[% ACUMULADO 1º Trimes 2026]]<=Fluxo_de_Caixa_Janeiro31020[[#This Row],[% ACUMULADO 1º Trimes 2025]],"VERDADEIRO","FALSO") -> VERDADEIRO | V99: 0 | W99: 0
A100: 3.2. FUNCIONÁRIO | B100: =Fluxo_de_Caixa_Janeiro[[#This Row],[Fluxo de Caixa 2026 CTR]] -> 3.2. DESPESA COM FUNCIONÁRIO | C100: =Fluxo_de_Caixa_Janeiro[[#This Row],[Janeiro]] -> -64579.58 | D100: =Fluxo_de_Caixa_Janeiro3[[#This Row],[Fevereiro]] -> -65616.5 | E100: =Fluxo_de_Caixa_Janeiro34[[#This Row],[Março]] -> -99956.93 | O100: =SUM(Fluxo_de_Caixa_Janeiro31020[[#This Row],[Janeiro]:[Dezembro]]) -> -230153.01 | P100: =-IFERROR(O100/$O$27,"0,00") -> 0.080026165 | Q100: 0.089424247 | R100: =IF(Fluxo_de_Caixa_Janeiro31020[[#This Row],[% ACUMULADO 1º Trimes 2026]]<=Fluxo_de_Caixa_Janeiro31020[[#This Row],[% ACUMULADO 1º Trimes 2025]],"VERDADEIRO","FALSO") -> VERDADEIRO | V100: -240591.64 | W100: 0.089424247
B101: =Fluxo_de_Caixa_Janeiro[[#This Row],[Fluxo de Caixa 2026 CTR]] -> 3.2.01. Salário (CLT) | C101: =Fluxo_de_Caixa_Janeiro[[#This Row],[Janeiro]] -> 31184.5 | D101: =Fluxo_de_Caixa_Janeiro3[[#This Row],[Fevereiro]] -> 33069.85 | E101: =Fluxo_de_Caixa_Janeiro34[[#This Row],[Março]] -> 33411.65 | O101: =SUM(Fluxo_de_Caixa_Janeiro31020[[#This Row],[Janeiro]:[Dezembro]]) -> 97666 | P101: =IFERROR(O101/$O$27,"0,00%") -> 0.033959301 | Q101: 0.036087197 | R101: =IF(Fluxo_de_Caixa_Janeiro31020[[#This Row],[% ACUMULADO 1º Trimes 2026]]<=Fluxo_de_Caixa_Janeiro31020[[#This Row],[% ACUMULADO 1º Trimes 2025]],"VERDADEIRO","FALSO") -> VERDADEIRO | V101: 97090.87 | W101: 0.036087197
...

Sheet ABRIL
B1: Fluxo de Caixa 2026 CTR | C1: ABRIL | D1: % ACUMULADO ABR/2026 | E1: % Acum no Ano Comparação | H1: Matriz | I1: Filia Porto | J1: Filia Palmas
A2: Disponíveis Nas Contas Movimento | B2: =Fluxo_de_Caixa_Janeiro[[#This Row],[Fluxo de Caixa 2026 CTR]] -> Disponíveis Nas Contas Movimento inicial | C2: =SUBTOTAL(109,C3:C26) -> 437595.58 | D2: =SUM(D3:D26) -> 1.0005043
B3: =Fluxo_de_Caixa_Janeiro[[#This Row],[Fluxo de Caixa 2026 CTR]] -> 1.0 - TESOURARIA MATRIZ PALMAS | C3: =MARÇO!C337 -> 850.58 | D3: =IF(C3=0,"0,00%",C3/$C$2) -> 0.0019437582 | G3: 1
B4: =Fluxo_de_Caixa_Janeiro[[#This Row],[Fluxo de Caixa 2026 CTR]] -> 1.1 - BANCO DO BRASIL C.C.60409-7 MATRIZ | C4: =MARÇO!C338 -> 36651.07 | D4: =IF(C4=0,"0,00%",C4/$C$2) -> 0.083755576 | G4: 2
B5: =Fluxo_de_Caixa_Janeiro[[#This Row],[Fluxo de Caixa 2026 CTR]] -> 0 | C5: =MARÇO!C339 -> 0 | D5: =IF(C5=0,"0,00%",C5/$C$2) -> 0,00% | G5: 3
B6: =Fluxo_de_Caixa_Janeiro[[#This Row],[Fluxo de Caixa 2026 CTR]] -> 1.2-BRADESCO 15232-3 MATRIZ | C6: =MARÇO!C340 -> 6785.01 | D6: =IF(C6=0,"0,00%",C6/$C$2) -> 0.015505207 | G6: 4
B7: =Fluxo_de_Caixa_Janeiro[[#This Row],[Fluxo de Caixa 2026 CTR]] -> 0 | C7: =MARÇO!C341 -> 0 | D7: =IF(C7=0,"0,00%",C7/$C$2) -> 0,00% | G7: 5
B8: =Fluxo_de_Caixa_Janeiro[[#This Row],[Fluxo de Caixa 2026 CTR]] -> 1.3 - BANCO STONE MATRIZ C.C 40256726-7 | C8: =MARÇO!C342 -> 0 | D8: =IF(C8=0,"0,00%",C8/$C$2) -> 0,00% | G8: 6
B9: =Fluxo_de_Caixa_Janeiro[[#This Row],[Fluxo de Caixa 2026 CTR]] -> 1.4 - BANCO DA AMAZONIA 071730-7 MATRIZ | C9: =MARÇO!C343 -> 304243.92 | D9: =IF(C9=0,"0,00%",C9/$C$2) -> 0.69526278 | G9: 7
B10: =Fluxo_de_Caixa_Janeiro[[#This Row],[Fluxo de Caixa 2026 CTR]] -> 1.4.1.INVESTIMENTO CDBORE RCP TXFL | C10: =MARÇO!C344 -> 0 | D10: =IF(C10=0,"0,00%",C10/$C$2) -> 0,00% | G10: 8
B11: =Fluxo_de_Caixa_Janeiro[[#This Row],[Fluxo de Caixa 2026 CTR]] -> 1.5 - ITAU C.C.98671-6 MATRIZ | C11: =MARÇO!C345 -> 95802.27 | D11: =IF(C11=0,"0,00%",C11/$C$2) -> 0.21892879 | G11: 9
B12: =Fluxo_de_Caixa_Janeiro[[#This Row],[Fluxo de Caixa 2026 CTR]] -> 1.5.03. ITAU C.C 83290-2 GARANTIDA | C12: =MARÇO!C346 -> 0 | D12: =IF(C12=0,"0,00%",C12/$C$2) -> 0,00% | G12: 10
B13: =Fluxo_de_Caixa_Janeiro[[#This Row],[Fluxo de Caixa 2026 CTR]] -> 1.9 - CONTA PERDA/ROUBO/BONIFICAÇÃO E DOAÇÃO | C13: =MARÇO!C347 -> -20953.13 | D13: =IF(C13=0,"0,00%",C13/$C$2) -> -0.047882408 | G13: 11
B14: =Fluxo_de_Caixa_Janeiro[[#This Row],[Fluxo de Caixa 2026 CTR]] -> 0 | C14: =MARÇO!C348 -> 0 | D14: =IF(C14=0,"0,00%",C14/$C$2) -> 0,00% | G14: 12 | I14: =I20-H34-I34-J34 -> -353624.95
B15: =Fluxo_de_Caixa_Janeiro[[#This Row],[Fluxo de Caixa 2026 CTR]] -> 2.1 - BANCO DO BRASIL C.C.60638-3 FILIAL PALMAS | C15: =MARÇO!C349 -> 33375.7 | D15: =IF(C15=0,"0,00%",C15/$C$2) -> 0.076270652 | G15: 13
B16: =Fluxo_de_Caixa_Janeiro[[#This Row],[Fluxo de Caixa 2026 CTR]] -> 0 | C16: =MARÇO!C350 -> 0 | D16: =IF(C16=0,"0,00%",C16/$C$2) -> 0,00% | G16: 14
B17: =Fluxo_de_Caixa_Janeiro[[#This Row],[Fluxo de Caixa 2026 CTR]] -> 0 | C17: =MARÇO!C351 -> 0 | D17: =IF(C17=0,"0,00%",C17/$C$2) -> 0,00% | G17: 15 | I17: 316630.68
B18: =Fluxo_de_Caixa_Janeiro[[#This Row],[Fluxo de Caixa 2026 CTR]] -> 2.4 - ITAU C.C.98669-0 FILIAL PALMAS | C18: =MARÇO!C352 -> 37.73 | D18: =IF(C18=0,"0,00%",C18/$C$2) -> 8.6221163e-05 | E18: =#REF! -> #REF! | G18: 16
B19: =Fluxo_de_Caixa_Janeiro[[#This Row],[Fluxo de Caixa 2026 CTR]] -> 2.9 - CONTA PERDA/ROUBO E BONIFICAÇÃO FILIAL | C19: =MARÇO!C353 -> -8598.58 | D19: =IF(C19=0,"0,00%",C19/$C$2) -> -0.019649604 | E19: =#REF! -> #REF! | G19: 17
B20: =Fluxo_de_Caixa_Janeiro[[#This Row],[Fluxo de Caixa 2026 CTR]] -> 4.0 - TESOURARIA FILIAL PORTO | C20: =MARÇO!C354 -> 534.16 | D20: =IF(C20=0,"0,00%",C20/$C$2) -> 0.0012206705 | E20: =#REF! -> #REF! | G20: 18
B21: =Fluxo_de_Caixa_Janeiro[[#This Row],[Fluxo de Caixa 2026 CTR]] -> 4.1 - BANCO DO BRASIL C.C.61105-0 FILIAL PORTO | C21: =MARÇO!C355 -> 521.92 | D21: =IF(C21=0,"0,00%",C21/$C$2) -> 0.0011926994 | E21: =#REF! -> #REF! | G21: 19
B22: =Fluxo_de_Caixa_Janeiro[[#This Row],[Fluxo de Caixa 2026 CTR]] -> 0 | C22: =MARÇO!C356 -> 0 | D22: =IF(C22=0,"0,00%",C22/$C$2) -> 0,00% | E22: =#REF! -> #REF! | G22: 20
B23: =Fluxo_de_Caixa_Janeiro[[#This Row],[Fluxo de Caixa 2026 CTR]] -> 4.4 - MERCADO PAGO PIX FILIAL PORTO | C23: =MARÇO!C357 -> 13187.1 | D23: =IF(C23=0,"0,00%",C23/$C$2) -> 0.030135359 | E23: =#REF! -> #REF! | G23: 21
B24: =Fluxo_de_Caixa_Janeiro[[#This Row],[Fluxo de Caixa 2026 CTR]] -> 4.9 - CONTA PERDA/ROUBO E BONIFICAÇÃO FILIAL | C24: =MARÇO!C358 -> -29071.86 | D24: =IF(C24=0,"0,00%",C24/$C$2) -> -0.066435452 | E24: =#REF! -> #REF! | G24: 22
B25: =Fluxo_de_Caixa_Janeiro[[#This Row],[Fluxo de Caixa 2026 CTR]] -> 91.CARTÃO ENDERED 5099+4596+6933+8072 - ESCRITORIO | C25: =MARÇO!C359 -> 4229.69 | D25: =IF(C25=0,"0,00%",C25/$C$2) -> 0.0096657512 | E25: =#REF! -> #REF! | G25: 23
B26: =Fluxo_de_Caixa_Janeiro[[#This Row],[Fluxo de Caixa 2026 CTR]] -> 0 | C26: =MARÇO!C361 -> 220.66 | D26: =IF(C26=0,"0,00%",C26/$C$2) -> 0.00050425555 | E26: =#REF! -> #REF! | G26: 24
B27: =Fluxo_de_Caixa_Janeiro[[#This Row],[Fluxo de Caixa 2026 CTR]] -> Total Receitas Operacionais / Vendas | C27: =SUBTOTAL(109,C29:C51) -> 1009247 | D27: =IFERROR(C27/C332,"") -> 0.99891127 | E27: 0.88526119 | H27: =H28+I28+J28 -> 1009247
A28: 1.1. Receita com Vendas | B28: =Fluxo_de_Caixa_Janeiro[[#This Row],[Fluxo de Caixa 2026 CTR]] -> 1.1. Receita com Vendas | C28: =SUBTOTAL(109,C29:C47) -> 1009247 | D28: =SUM(D29:D47) -> 0.99891127 | E28: 0.88251933 | G28: =C361 -> 250.32 | H28: =SUM(H29:H36) -> 46278.25 | I28: =SUM(I29:I36) -> 606271.08 | J28: =SUM(J29:J36) -> 356697.67
B29: =Fluxo_de_Caixa_Janeiro[[#This Row],[Fluxo de Caixa 2026 CTR]] -> 1.1.01. Receita em Dinheiro | C29: =H29+I29+J29 -> 3589.4 | D29: =IF(C29=0,"0,00%",C29/$C$332) -> 0.0035526408 | E29: 0.079252981 | F29: =IF(Fluxo_de_Caixa_Janeiro34591171012151619[[#This Row],[% ACUMULADO DEZ/2026]]>=Fluxo_de_Caixa_Janeiro34591171012151619[[#This Row],[% Acum no Ano Comparação]],"Verd","Fals") -> Verd | H29: 150 | I29: 3264.41 | J29: 174.99
B30: =Fluxo_de_Caixa_Janeiro[[#This Row],[Fluxo de Caixa 2026 CTR]] -> 1.1.01. Receita em Cartão (Crédito e Débito) | C30: =H30+I30+J30 -> 160565.41 | D30: =IF(C30=0,"0,00%",C30/$C$332) -> 0.15892105 | E30: 0.092740536 | F30: =IF(Fluxo_de_Caixa_Janeiro34591171012151619[[#This Row],[% ACUMULADO DEZ/2026]]>=Fluxo_de_Caixa_Janeiro34591171012151619[[#This Row],[% Acum no Ano Comparação]],"Verd","Fals") -> Verd | H30: 0 | I30: 89019.06 | J30: 71546.35
B31: =Fluxo_de_Caixa_Janeiro[[#This Row],[Fluxo de Caixa 2026 CTR]] -> 1.1.01. Receita de Cheque A Vista | C31: =H31+I31+J31 -> 19225.74 | D31: =IF(C31=0,"0,00%",C31/$C$332) -> 0.019028849 | E31: 0.00028628486 | F31: =IF(Fluxo_de_Caixa_Janeiro34591171012151619[[#This Row],[% ACUMULADO DEZ/2026]]>=Fluxo_de_Caixa_Janeiro34591171012151619[[#This Row],[% Acum no Ano Comparação]],"Verd","Fals") -> Verd | I31: 19225.74
B32: =Fluxo_de_Caixa_Janeiro[[#This Row],[Fluxo de Caixa 2026 CTR]] -> 1.1.01. Receita de Cheque Pré | C32: 0 | D32: =IF(C32=0,"0,00%",C32/$C$332) -> 0,00% | E32: 0.0063111634 | F32: =IF(Fluxo_de_Caixa_Janeiro34591171012151619[[#This Row],[% ACUMULADO DEZ/2026]]>=Fluxo_de_Caixa_Janeiro34591171012151619[[#This Row],[% Acum no Ano Comparação]],"Verd","Fals") -> Verd
B33: =Fluxo_de_Caixa_Janeiro[[#This Row],[Fluxo de Caixa 2026 CTR]] -> 1.1.01. Recebimento de Carteira (Notinha) | C33: =H33+I33+J33 -> 30464 | D33: =IF(C33=0,"0,00%",C33/$C$332) -> 0.030152017 | E33: 0.0001318638 | F33: =IF(Fluxo_de_Caixa_Janeiro34591171012151619[[#This Row],[% ACUMULADO DEZ/2026]]>=Fluxo_de_Caixa_Janeiro34591171012151619[[#This Row],[% Acum no Ano Comparação]],"Verd","Fals") -> Verd | H33: 30464 | I33: 0
B34: =Fluxo_de_Caixa_Janeiro[[#This Row],[Fluxo de Caixa 2026 CTR]] -> 1.1.01. Recebimento de Boletos | C34: =H34+I34+J34 -> 353624.95 | D34: =IF(C34=0,"0,00%",C34/$C$332) -> 0.35000346 | E34: 0.66745712 | F34: =IF(Fluxo_de_Caixa_Janeiro34591171012151619[[#This Row],[% ACUMULADO DEZ/2026]]>=Fluxo_de_Caixa_Janeiro34591171012151619[[#This Row],[% Acum no Ano Comparação]],"Verd","Fals") -> Verd | H34: 14934.25 | I34: 194961.89 | J34: 143728.81
B35: =Fluxo_de_Caixa_Janeiro[[#This Row],[Fluxo de Caixa 2026 CTR]] -> 1.1.01. Recebimento em Depósito e Dep. PIX | C35: =H35+I35+J35 -> 441777.5 | D35: =IF(C35=0,"0,00%",C35/$C$332) -> 0.43725324 | E35: 0.036171198 | F35: =IF(Fluxo_de_Caixa_Janeiro34591171012151619[[#This Row],[% ACUMULADO DEZ/2026]]>=Fluxo_de_Caixa_Janeiro34591171012151619[[#This Row],[% Acum no Ano Comparação]],"Verd","Fals") -> Verd | H35: 730 | I35: 299799.98 | J35: 141247.52
B36: =Fluxo_de_Caixa_Janeiro[[#This Row],[Fluxo de Caixa 2026 CTR]] -> 1.1.02. Recebimento Cheque Devolvido | C36: =H36+I36+J36 -> 0 | D36: =IF(C36=0,"0,00%",C36/$C$332) -> 0,00% | E36: 0.00016817802 | F36: =IF(Fluxo_de_Caixa_Janeiro34591171012151619[[#This Row],[% ACUMULADO DEZ/2026]]>=Fluxo_de_Caixa_Janeiro34591171012151619[[#This Row],[% Acum no Ano Comparação]],"Verd","Fals") -> Verd
B37: =Fluxo_de_Caixa_Janeiro[[#This Row],[Fluxo de Caixa 2026 CTR]] -> 0 | D37: =IF(C37=0,"0,00%",C37/$C$332) -> 0,00% | E37: =#REF! -> #REF! | F37: =IF(Fluxo_de_Caixa_Janeiro34591171012151619[[#This Row],[% ACUMULADO DEZ/2026]]>=Fluxo_de_Caixa_Janeiro34591171012151619[[#This Row],[% Acum no Ano Comparação]],"Verd","Fals") -> #REF!
B38: =Fluxo_de_Caixa_Janeiro[[#This Row],[Fluxo de Caixa 2026 CTR]] -> 0 | D38: =IF(C38=0,"0,00%",C38/$C$332) -> 0,00% | E38: =#REF! -> #REF! | F38: =IF(Fluxo_de_Caixa_Janeiro34591171012151619[[#This Row],[% ACUMULADO DEZ/2026]]>=Fluxo_de_Caixa_Janeiro34591171012151619[[#This Row],[% Acum no Ano Comparação]],"Verd","Fals") -> #REF!
B39: =Fluxo_de_Caixa_Janeiro[[#This Row],[Fluxo de Caixa 2026 CTR]] -> 0 | D39: =IF(C39=0,"0,00%",C39/$C$332) -> 0,00% | E39: =#REF! -> #REF! | F39: =IF(Fluxo_de_Caixa_Janeiro34591171012151619[[#This Row],[% ACUMULADO DEZ/2026]]>=Fluxo_de_Caixa_Janeiro34591171012151619[[#This Row],[% Acum no Ano Comparação]],"Verd","Fals") -> #REF!
B40: =Fluxo_de_Caixa_Janeiro[[#This Row],[Fluxo de Caixa 2026 CTR]] -> 0 | D40: =IF(C40=0,"0,00%",C40/$C$332) -> 0,00% | E40: =#REF! -> #REF! | F40: =IF(Fluxo_de_Caixa_Janeiro34591171012151619[[#This Row],[% ACUMULADO DEZ/2026]]>=Fluxo_de_Caixa_Janeiro34591171012151619[[#This Row],[% Acum no Ano Comparação]],"Verd","Fals") -> #REF!
B41: =Fluxo_de_Caixa_Janeiro[[#This Row],[Fluxo de Caixa 2026 CTR]] -> 0 | D41: =IF(C41=0,"0,00%",C41/$C$332) -> 0,00% | E41: =#REF! -> #REF! | F41: =IF(Fluxo_de_Caixa_Janeiro34591171012151619[[#This Row],[% ACUMULADO DEZ/2026]]>=Fluxo_de_Caixa_Janeiro34591171012151619[[#This Row],[% Acum no Ano Comparação]],"Verd","Fals") -> #REF!
B42: =Fluxo_de_Caixa_Janeiro[[#This Row],[Fluxo de Caixa 2026 CTR]] -> 0 | D42: =IF(C42=0,"0,00%",C42/$C$332) -> 0,00% | E42: =#REF! -> #REF! | F42: =IF(Fluxo_de_Caixa_Janeiro34591171012151619[[#This Row],[% ACUMULADO DEZ/2026]]>=Fluxo_de_Caixa_Janeiro34591171012151619[[#This Row],[% Acum no Ano Comparação]],"Verd","Fals") -> #REF!
B43: =Fluxo_de_Caixa_Janeiro[[#This Row],[Fluxo de Caixa 2026 CTR]] -> 0 | D43: =IF(C43=0,"0,00%",C43/$C$332) -> 0,00% | E43: =#REF! -> #REF! | F43: =IF(Fluxo_de_Caixa_Janeiro34591171012151619[[#This Row],[% ACUMULADO DEZ/2026]]>=Fluxo_de_Caixa_Janeiro34591171012151619[[#This Row],[% Acum no Ano Comparação]],"Verd","Fals") -> #REF!
B44: =Fluxo_de_Caixa_Janeiro[[#This Row],[Fluxo de Caixa 2026 CTR]] -> 0 | D44: =IF(C44=0,"0,00%",C44/$C$332) -> 0,00% | E44: =#REF! -> #REF! | F44: =IF(Fluxo_de_Caixa_Janeiro34591171012151619[[#This Row],[% ACUMULADO DEZ/2026]]>=Fluxo_de_Caixa_Janeiro34591171012151619[[#This Row],[% Acum no Ano Comparação]],"Verd","Fals") -> #REF!
B45: =Fluxo_de_Caixa_Janeiro[[#This Row],[Fluxo de Caixa 2026 CTR]] -> 0 | D45: =IF(C45=0,"0,00%",C45/$C$332) -> 0,00% | E45: =#REF! -> #REF! | F45: =IF(Fluxo_de_Caixa_Janeiro34591171012151619[[#This Row],[% ACUMULADO DEZ/2026]]>=Fluxo_de_Caixa_Janeiro34591171012151619[[#This Row],[% Acum no Ano Comparação]],"Verd","Fals") -> #REF!
B46: =Fluxo_de_Caixa_Janeiro[[#This Row],[Fluxo de Caixa 2026 CTR]] -> 0 | C46: 0 | D46: =IF(C46=0,"0,00%",C46/$C$332) -> 0,00% | E46: =#REF! -> #REF! | F46: =IF(Fluxo_de_Caixa_Janeiro34591171012151619[[#This Row],[% ACUMULADO DEZ/2026]]>=Fluxo_de_Caixa_Janeiro34591171012151619[[#This Row],[% Acum no Ano Comparação]],"Verd","Fals") -> #REF!
B47: =Fluxo_de_Caixa_Janeiro[[#This Row],[Fluxo de Caixa 2026 CTR]] -> 0 | D47: =IF(C47=0,"0,00%",C47/$C$332) -> 0,00% | E47: =#REF! -> #REF! | F47: =IF(Fluxo_de_Caixa_Janeiro34591171012151619[[#This Row],[% ACUMULADO DEZ/2026]]>=Fluxo_de_Caixa_Janeiro34591171012151619[[#This Row],[% Acum no Ano Comparação]],"Verd","Fals") -> #REF!
A48: 1.5. Receita de Garantias | B48: =Fluxo_de_Caixa_Janeiro[[#This Row],[Fluxo de Caixa 2026 CTR]] -> 1.5. Receita de Garantias | C48: =+SUBTOTAL(109,C49:C51) -> 0 | D48: =SUM(D49:D51) -> 0 | E48: 0.0027418655 | H48: =SUM(H49:H51) -> 0 | I48: =SUM(I49:I51) -> 0 | J48: =SUM(J49:J51) -> 0
B49: =Fluxo_de_Caixa_Janeiro[[#This Row],[Fluxo de Caixa 2026 CTR]] -> 1.2.01. RECEITA EM DINHEIRO | C49: =H49+I49 -> 0 | D49: =IF(C49=0,"0,00%",C49/$C$332) -> 0,00% | E49: 0.0024323151 | F49: =IF(Fluxo_de_Caixa_Janeiro34591171012151619[[#This Row],[% ACUMULADO DEZ/2026]]>=Fluxo_de_Caixa_Janeiro34591171012151619[[#This Row],[% Acum no Ano Comparação]],"Verd","Fals") -> Verd
B50: =Fluxo_de_Caixa_Janeiro[[#This Row],[Fluxo de Caixa 2026 CTR]] -> 1.2.02. RECEITA EM MERCADORIA | C50: =H50+I50 -> 0 | D50: =IF(C50=0,"0,00%",C50/$C$332) -> 0,00% | E50: 0.00030955038 | F50: =IF(Fluxo_de_Caixa_Janeiro34591171012151619[[#This Row],[% ACUMULADO DEZ/2026]]>=Fluxo_de_Caixa_Janeiro34591171012151619[[#This Row],[% Acum no Ano Comparação]],"Verd","Fals") -> Verd
B51: =Fluxo_de_Caixa_Janeiro[[#This Row],[Fluxo de Caixa 2026 CTR]] -> 0 | C51: =H51+I51 -> 0 | D51: =IF(C51=0,"0,00%",C51/$C$332) -> 0,00% | E51: =#REF! -> #REF! | F51: =IF(Fluxo_de_Caixa_Janeiro34591171012151619[[#This Row],[% ACUMULADO DEZ/2026]]>=Fluxo_de_Caixa_Janeiro34591171012151619[[#This Row],[% Acum no Ano Comparação]],"Verd","Fals") -> #REF!
A52: 2.1. Despesa Com Custo de Aquisição | B52: =Fluxo_de_Caixa_Janeiro[[#This Row],[Fluxo de Caixa 2026 CTR]] -> 2.1. Despesa Com Custo de Aquisição | C52: =-SUBTOTAL(109,C53:C59) -> -376222.97 | D52: =-IFERROR(C52/$C$27,"0,00") -> 0.37277591 | E52: 0.7032551 | F52: =IF(Fluxo_de_Caixa_Janeiro34591171012151619[[#This Row],[% ACUMULADO DEZ/2026]]<=Fluxo_de_Caixa_Janeiro34591171012151619[[#This Row],[% Acum no Ano Comparação]],"Verd","Fals") -> Verd | H52: =-SUBTOTAL(109,H53:H59) -> -351026.56 | I52: =-SUBTOTAL(109,I53:I59) -> -25196.41 | J52: =-SUBTOTAL(109,J53:J59) -> 0
B53: =Fluxo_de_Caixa_Janeiro[[#This Row],[Fluxo de Caixa 2026 CTR]] -> 2.1.01.FORNECEDORES DE MERCADORIAS REVENDA | C53: =H53+I53+J53 -> 366608.48 | D53: =IFERROR(C53/$C$27,"0,00%") -> 0.36324951 | E53: 0.70044704 | F53: =IF(Fluxo_de_Caixa_Janeiro34591171012151619[[#This Row],[% ACUMULADO DEZ/2026]]<=Fluxo_de_Caixa_Janeiro34591171012151619[[#This Row],[% Acum no Ano Comparação]],"Verd","Fals") -> Fals | H53: 341572.07 | I53: 25036.41
B54: =Fluxo_de_Caixa_Janeiro[[#This Row],[Fluxo de Caixa 2026 CTR]] -> 2.1.02.ADIANT. FORNEC. MERCA. REVENDA | C54: =H54+I54+J54 -> 0 | D54: =IFERROR(C54/$C$27,"0,00%") -> 0 | E54: 0.0028080664 | F54: =IF(Fluxo_de_Caixa_Janeiro34591171012151619[[#This Row],[% ACUMULADO DEZ/2026]]<=Fluxo_de_Caixa_Janeiro34591171012151619[[#This Row],[% Acum no Ano Comparação]],"Verd","Fals") -> Fals | H54: 0
B55: =Fluxo_de_Caixa_Janeiro[[#This Row],[Fluxo de Caixa 2026 CTR]] -> 2.1.03.TRANSPORTADORA MERCA. REVENDA | C55: =H55+I55+J55 -> 9614.49 | D55: =IFERROR(C55/$C$27,"0,00%") -> 0.0095263994 | E55: 0 | F55: =IF(Fluxo_de_Caixa_Janeiro34591171012151619[[#This Row],[% ACUMULADO DEZ/2026]]<=Fluxo_de_Caixa_Janeiro34591171012151619[[#This Row],[% Acum no Ano Comparação]],"Verd","Fals") -> Fals | H55: 9454.49 | I55: 160
B56: =Fluxo_de_Caixa_Janeiro[[#This Row],[Fluxo de Caixa 2026 CTR]] -> 2.1.04.OUTROS CUSTOS DE MERC.REVENDA | C56: 0 | D56: =IFERROR(C56/$C$27,"0,00%") -> 0 | E56: =#REF! -> #REF! | F56: =IF(Fluxo_de_Caixa_Janeiro34591171012151619[[#This Row],[% ACUMULADO DEZ/2026]]<=Fluxo_de_Caixa_Janeiro34591171012151619[[#This Row],[% Acum no Ano Comparação]],"Verd","Fals") -> #REF!
B57: =Fluxo_de_Caixa_Janeiro[[#This Row],[Fluxo de Caixa 2026 CTR]] -> 2.1.05.TRANSFE DE MERCAD REVENDA MATRIZ | C57: =H57+I57+J57 -> 0 | D57: =IFERROR(C57/$C$27,"0,00%") -> 0 | E57: =#REF! -> #REF! | F57: =IF(Fluxo_de_Caixa_Janeiro34591171012151619[[#This Row],[% ACUMULADO DEZ/2026]]<=Fluxo_de_Caixa_Janeiro34591171012151619[[#This Row],[% Acum no Ano Comparação]],"Verd","Fals") -> #REF!
B58: =Fluxo_de_Caixa_Janeiro[[#This Row],[Fluxo de Caixa 2026 CTR]] -> 0 | D58: =IFERROR(C58/$C$27,"0,00%") -> 0 | E58: =#REF! -> #REF! | F58: =IF(Fluxo_de_Caixa_Janeiro34591171012151619[[#This Row],[% ACUMULADO DEZ/2026]]<=Fluxo_de_Caixa_Janeiro34591171012151619[[#This Row],[% Acum no Ano Comparação]],"Verd","Fals") -> #REF!
B59: =Fluxo_de_Caixa_Janeiro[[#This Row],[Fluxo de Caixa 2026 CTR]] -> 0 | D59: =IFERROR(C59/$C$27,"0,00%") -> 0 | E59: =#REF! -> #REF! | F59: =IF(Fluxo_de_Caixa_Janeiro34591171012151619[[#This Row],[% ACUMULADO DEZ/2026]]<=Fluxo_de_Caixa_Janeiro34591171012151619[[#This Row],[% Acum no Ano Comparação]],"Verd","Fals") -> #REF!
A60: 2.2. Inadimplência e Perdas | B60: =Fluxo_de_Caixa_Janeiro[[#This Row],[Fluxo de Caixa 2026 CTR]] -> 2.2. Inadimplência e Perdas | C60: =-SUBTOTAL(109,C61:C69) -> 0 | D60: =-IFERROR(C60/$C$27,"0,00") -> 0 | E60: 0.0013173948 | F60: =IF(Fluxo_de_Caixa_Janeiro34591171012151619[[#This Row],[% ACUMULADO DEZ/2026]]<=Fluxo_de_Caixa_Janeiro34591171012151619[[#This Row],[% Acum no Ano Comparação]],"Verd","Fals") -> Verd | H60: =-SUBTOTAL(109,H61:H69) -> 0 | I60: =-SUBTOTAL(109,I61:I69) -> 0 | J60: =-SUBTOTAL(109,J61:J69) -> 0
B61: =Fluxo_de_Caixa_Janeiro[[#This Row],[Fluxo de Caixa 2026 CTR]] -> 2.2.01.CONTAS PERDIDAS/NÃO PAGAS | C61: =H61+I61+J61 -> 0 | D61: =IFERROR(C61/$C$27,"0,00%") -> 0 | E61: 0 | F61: =IF(Fluxo_de_Caixa_Janeiro34591171012151619[[#This Row],[% ACUMULADO DEZ/2026]]<=Fluxo_de_Caixa_Janeiro34591171012151619[[#This Row],[% Acum no Ano Comparação]],"Verd","Fals") -> Fals
B62: =Fluxo_de_Caixa_Janeiro[[#This Row],[Fluxo de Caixa 2026 CTR]] -> 2.2.02.BOLETOS DESCONTADOS DEVOLVIDOS | C62: =H62+I62+J62 -> 0 | D62: =IFERROR(C62/$C$27,"0,00%") -> 0 | E62: 0 | F62: =IF(Fluxo_de_Caixa_Janeiro34591171012151619[[#This Row],[% ACUMULADO DEZ/2026]]<=Fluxo_de_Caixa_Janeiro34591171012151619[[#This Row],[% Acum no Ano Comparação]],"Verd","Fals") -> Fals
B63: =Fluxo_de_Caixa_Janeiro[[#This Row],[Fluxo de Caixa 2026 CTR]] -> 2.2.03.CHEQUES DEVOLVIDOS | C63: =H63+I63+J63 -> 0 | D63: =IFERROR(C63/$C$27,"0,00%") -> 0 | E63: 0 | F63: =IF(Fluxo_de_Caixa_Janeiro34591171012151619[[#This Row],[% ACUMULADO DEZ/2026]]<=Fluxo_de_Caixa_Janeiro34591171012151619[[#This Row],[% Acum no Ano Comparação]],"Verd","Fals") -> Fals
B64: =Fluxo_de_Caixa_Janeiro[[#This Row],[Fluxo de Caixa 2026 CTR]] -> 2.2.04.BOLETOS DESCONTADOS DEVOLVIDOS | C64: =H64+I64+J64 -> 0 | D64: =IFERROR(C64/$C$27,"0,00%") -> 0 | E64: 0.0012728671 | F64: =IF(Fluxo_de_Caixa_Janeiro34591171012151619[[#This Row],[% ACUMULADO DEZ/2026]]<=Fluxo_de_Caixa_Janeiro34591171012151619[[#This Row],[% Acum no Ano Comparação]],"Verd","Fals") -> Fals
B65: =Fluxo_de_Caixa_Janeiro[[#This Row],[Fluxo de Caixa 2026 CTR]] -> 2.2.05.PERDA, ROUBO E DETERIORAÇÃO | C65: =H65+I65+J65 -> 0 | D65: =IFERROR(C65/$C$27,"0,00%") -> 0 | E65: 4.4527688e-05 | F65: =IF(Fluxo_de_Caixa_Janeiro34591171012151619[[#This Row],[% ACUMULADO DEZ/2026]]<=Fluxo_de_Caixa_Janeiro34591171012151619[[#This Row],[% Acum no Ano Comparação]],"Verd","Fals") -> Fals
B66: =Fluxo_de_Caixa_Janeiro[[#This Row],[Fluxo de Caixa 2026 CTR]] -> 0 | C66: =H66+I66+J66 -> 0 | D66: =IFERROR(C66/$C$27,"0,00%") -> 0 | E66: =#REF! -> #REF! | F66: =IF(Fluxo_de_Caixa_Janeiro34591171012151619[[#This Row],[% ACUMULADO DEZ/2026]]<=Fluxo_de_Caixa_Janeiro34591171012151619[[#This Row],[% Acum no Ano Comparação]],"Verd","Fals") -> #REF!
B67: =Fluxo_de_Caixa_Janeiro[[#This Row],[Fluxo de Caixa 2026 CTR]] -> 0 | C67: =H67+I67+J67 -> 0 | D67: =IFERROR(C67/$C$27,"0,00%") -> 0 | E67: =#REF! -> #REF! | F67: =IF(Fluxo_de_Caixa_Janeiro34591171012151619[[#This Row],[% ACUMULADO DEZ/2026]]<=Fluxo_de_Caixa_Janeiro34591171012151619[[#This Row],[% Acum no Ano Comparação]],"Verd","Fals") -> #REF!
B68: =Fluxo_de_Caixa_Janeiro[[#This Row],[Fluxo de Caixa 2026 CTR]] -> 0 | C68: =H68+I68+J68 -> 0 | D68: =IFERROR(C68/$C$27,"0,00%") -> 0 | E68: =#REF! -> #REF! | F68: =IF(Fluxo_de_Caixa_Janeiro34591171012151619[[#This Row],[% ACUMULADO DEZ/2026]]<=Fluxo_de_Caixa_Janeiro34591171012151619[[#This Row],[% Acum no Ano Comparação]],"Verd","Fals") -> #REF!
B69: =Fluxo_de_Caixa_Janeiro[[#This Row],[Fluxo de Caixa 2026 CTR]] -> 0 | C69: =H69+I69+J69 -> 0 | D69: =IFERROR(C69/$C$27,"0,00%") -> 0 | E69: =#REF! -> #REF! | F69: =IF(Fluxo_de_Caixa_Janeiro34591171012151619[[#This Row],[% ACUMULADO DEZ/2026]]<=Fluxo_de_Caixa_Janeiro34591171012151619[[#This Row],[% Acum no Ano Comparação]],"Verd","Fals") -> #REF!
A70: 2.3. Impostos | B70: =Fluxo_de_Caixa_Janeiro[[#This Row],[Fluxo de Caixa 2026 CTR]] -> 2.3. Impostos | C70: =-SUBTOTAL(109,C71:C84) -> -68045.71 | D70: =-IFERROR(C70/$C$27,"0,00") -> 0.067422256 | E70: 0.12754151 | F70: =IF(Fluxo_de_Caixa_Janeiro34591171012151619[[#This Row],[% ACUMULADO DEZ/2026]]<=Fluxo_de_Caixa_Janeiro34591171012151619[[#This Row],[% Acum no Ano Comparação]],"Verd","Fals") -> Verd | H70: =-SUBTOTAL(109,H71:H84) -> -52996.45 | I70: =-SUBTOTAL(109,I71:I84) -> -8056.58 | J70: =-SUBTOTAL(109,J71:J84) -> -6992.68
B71: =Fluxo_de_Caixa_Janeiro[[#This Row],[Fluxo de Caixa 2026 CTR]] -> 0 | D71: =IFERROR(C71/$C$27,"0,00%") -> 0 | E71: 0.0010503863 | F71: =IF(Fluxo_de_Caixa_Janeiro34591171012151619[[#This Row],[% ACUMULADO DEZ/2026]]<=Fluxo_de_Caixa_Janeiro34591171012151619[[#This Row],[% Acum no Ano Comparação]],"Verd","Fals") -> Fals
B72: =Fluxo_de_Caixa_Janeiro[[#This Row],[Fluxo de Caixa 2026 CTR]] -> 2.3.02.IRPJ (SE ESTIVER NO CMV) | C72: =H72+I72+J72 -> 0 | D72: =IFERROR(C72/$C$27,"0,00%") -> 0 | E72: 0.00062053498 | F72: =IF(Fluxo_de_Caixa_Janeiro34591171012151619[[#This Row],[% ACUMULADO DEZ/2026]]<=Fluxo_de_Caixa_Janeiro34591171012151619[[#This Row],[% Acum no Ano Comparação]],"Verd","Fals") -> Fals
B73: =Fluxo_de_Caixa_Janeiro[[#This Row],[Fluxo de Caixa 2026 CTR]] -> 2.3.03.CSSL (SE ESTIVER NO CMV) | C73: =H73+I73+J73 -> 0 | D73: =IFERROR(C73/$C$27,"0,00%") -> 0 | E73: 0.003344374 | F73: =IF(Fluxo_de_Caixa_Janeiro34591171012151619[[#This Row],[% ACUMULADO DEZ/2026]]<=Fluxo_de_Caixa_Janeiro34591171012151619[[#This Row],[% Acum no Ano Comparação]],"Verd","Fals") -> Fals
B74: =Fluxo_de_Caixa_Janeiro[[#This Row],[Fluxo de Caixa 2026 CTR]] -> 2.3.04.COFINS (SE ESTIVER NO CMV) | C74: =H74+I74+J74 -> 0 | D74: =IFERROR(C74/$C$27,"0,00%") -> 0 | E74: 0.00072605477 | F74: =IF(Fluxo_de_Caixa_Janeiro34591171012151619[[#This Row],[% ACUMULADO DEZ/2026]]<=Fluxo_de_Caixa_Janeiro34591171012151619[[#This Row],[% Acum no Ano Comparação]],"Verd","Fals") -> Fals
B75: =Fluxo_de_Caixa_Janeiro[[#This Row],[Fluxo de Caixa 2026 CTR]] -> 2.3.05.PIS (SE ESTIVER NO CMV) | C75: =H75+I75+J75 -> 0 | D75: =IFERROR(C75/$C$27,"0,00%") -> 0 | E75: 0.051721948 | F75: =IF(Fluxo_de_Caixa_Janeiro34591171012151619[[#This Row],[% ACUMULADO DEZ/2026]]<=Fluxo_de_Caixa_Janeiro34591171012151619[[#This Row],[% Acum no Ano Comparação]],"Verd","Fals") -> Fals | J75: 0
B76: =Fluxo_de_Caixa_Janeiro[[#This Row],[Fluxo de Caixa 2026 CTR]] -> 2.3.06.ICMS – Normal (SE ESTIVER NO CMV) | C76: =H76+I76+J76 -> 31430.89 | D76: =IFERROR(C76/$C$27,"0,00%") -> 0.031142911 | E76: 0.067027605 | F76: =IF(Fluxo_de_Caixa_Janeiro34591171012151619[[#This Row],[% ACUMULADO DEZ/2026]]<=Fluxo_de_Caixa_Janeiro34591171012151619[[#This Row],[% Acum no Ano Comparação]],"Verd","Fals") -> Fals | H76: 17074.56 | I76: 8056.58 | J76: 6299.75
B77: =Fluxo_de_Caixa_Janeiro[[#This Row],[Fluxo de Caixa 2026 CTR]] -> 2.3.07. SUBSTITUIÇÃO TRIBUTARIA SAÍDA (TARE) | C77: =H77+I77+J77 -> 20032.79 | D77: =IFERROR(C77/$C$27,"0,00%") -> 0.019849244 | E77: 0.0030506108 | F77: =IF(Fluxo_de_Caixa_Janeiro34591171012151619[[#This Row],[% ACUMULADO DEZ/2026]]<=Fluxo_de_Caixa_Janeiro34591171012151619[[#This Row],[% Acum no Ano Comparação]],"Verd","Fals") -> Fals | H77: 20000.94 | I77: 0 | J77: 31.85
B78: =Fluxo_de_Caixa_Janeiro[[#This Row],[Fluxo de Caixa 2026 CTR]] -> 2.3.08.SUBSTITUIÇÃO TRIBUTÁRIA NA ENTRADA | C78: =H78+I78+J78 -> 0 | D78: =IFERROR(C78/$C$27,"0,00%") -> 0 | E78: =#REF! -> #REF! | F78: =IF(Fluxo_de_Caixa_Janeiro34591171012151619[[#This Row],[% ACUMULADO DEZ/2026]]<=Fluxo_de_Caixa_Janeiro34591171012151619[[#This Row],[% Acum no Ano Comparação]],"Verd","Fals") -> #REF!
B79: =Fluxo_de_Caixa_Janeiro[[#This Row],[Fluxo de Caixa 2026 CTR]] -> 2.3.09.FUNDO DESENVOLVIMENTO ECONOMICO (TARE) | C79: =H79+I79+J79 -> 839.78 | D79: =IFERROR(C79/$C$27,"0,00%") -> 0.0008320857 | E79: =#REF! -> #REF! | F79: =IF(Fluxo_de_Caixa_Janeiro34591171012151619[[#This Row],[% ACUMULADO DEZ/2026]]<=Fluxo_de_Caixa_Janeiro34591171012151619[[#This Row],[% Acum no Ano Comparação]],"Verd","Fals") -> #REF! | H79: 839.78
B80: =Fluxo_de_Caixa_Janeiro[[#This Row],[Fluxo de Caixa 2026 CTR]] -> 0 | C80: =H80+I80+J80 -> 0 | D80: =IFERROR(C80/$C$27,"0,00%") -> 0 | E80: =#REF! -> #REF! | F80: =IF(Fluxo_de_Caixa_Janeiro34591171012151619[[#This Row],[% ACUMULADO DEZ/2026]]<=Fluxo_de_Caixa_Janeiro34591171012151619[[#This Row],[% Acum no Ano Comparação]],"Verd","Fals") -> #REF!
B81: =Fluxo_de_Caixa_Janeiro[[#This Row],[Fluxo de Caixa 2026 CTR]] -> 0 | C81: =H81+I81+J81 -> 0 | D81: =IFERROR(C81/$C$27,"0,00%") -> 0 | E81: =#REF! -> #REF! | F81: =IF(Fluxo_de_Caixa_Janeiro34591171012151619[[#This Row],[% ACUMULADO DEZ/2026]]<=Fluxo_de_Caixa_Janeiro34591171012151619[[#This Row],[% Acum no Ano Comparação]],"Verd","Fals") -> #REF!
B82: =Fluxo_de_Caixa_Janeiro[[#This Row],[Fluxo de Caixa 2026 CTR]] -> 2.3.11. Impostos Parcelado | C82: =H82+I82+J82 -> 15742.25 | D82: =IFERROR(C82/$C$27,"0,00%") -> 0.015598015 | E82: =#REF! -> #REF! | F82: =IF(Fluxo_de_Caixa_Janeiro34591171012151619[[#This Row],[% ACUMULADO DEZ/2026]]<=Fluxo_de_Caixa_Janeiro34591171012151619[[#This Row],[% Acum no Ano Comparação]],"Verd","Fals") -> #REF! | H82: 15081.17 | I82: 0 | J82: 661.08
B83: =Fluxo_de_Caixa_Janeiro[[#This Row],[Fluxo de Caixa 2026 CTR]] -> 0 | D83: =IFERROR(C83/$C$27,"0,00%") -> 0 | E83: =#REF! -> #REF! | F83: =IF(Fluxo_de_Caixa_Janeiro34591171012151619[[#This Row],[% ACUMULADO DEZ/2026]]<=Fluxo_de_Caixa_Janeiro34591171012151619[[#This Row],[% Acum no Ano Comparação]],"Verd","Fals") -> #REF!
B84: =Fluxo_de_Caixa_Janeiro[[#This Row],[Fluxo de Caixa 2026 CTR]] -> 0 | D84: =IFERROR(C84/$C$27,"0,00%") -> 0 | E84: =#REF! -> #REF! | F84: =IF(Fluxo_de_Caixa_Janeiro34591171012151619[[#This Row],[% ACUMULADO DEZ/2026]]<=Fluxo_de_Caixa_Janeiro34591171012151619[[#This Row],[% Acum no Ano Comparação]],"Verd","Fals") -> #REF!
B85: =Fluxo_de_Caixa_Janeiro[[#This Row],[Fluxo de Caixa 2026 CTR]] -> Total dos Custos | C85: =-SUBTOTAL(109,C52:C84) -> -444268.68 | D85: =IFERROR(C85/C27,"0,00%") -> -0.44019817 | E85: =#REF! -> #REF! | F85: =IF(Fluxo_de_Caixa_Janeiro34591171012151619[[#This Row],[% ACUMULADO DEZ/2026]]<=Fluxo_de_Caixa_Janeiro34591171012151619[[#This Row],[% Acum no Ano Comparação]],"Verd","Fals") -> #REF! | H85: =-SUBTOTAL(109,H52:H84) -> -404023.01 | I85: =-SUBTOTAL(109,I52:I84) -> -33252.99 | J85: =-SUBTOTAL(109,J52:J84) -> -6992.68
B86: =Fluxo_de_Caixa_Janeiro[[#This Row],[Fluxo de Caixa 2026 CTR]] -> Receita Operacional Bruta | C86: =SUM(C27,C85) -> 564978.32 | D86: =IFERROR(C86/C27,"0,00%") -> 0.55980183 | E86: =#REF! -> #REF! | F86: =IF(Fluxo_de_Caixa_Janeiro34591171012151619[[#This Row],[% ACUMULADO DEZ/2026]]>=Fluxo_de_Caixa_Janeiro34591171012151619[[#This Row],[% Acum no Ano Comparação]],"Verd","Fals") -> #REF!
B87: =Fluxo_de_Caixa_Janeiro[[#This Row],[Fluxo de Caixa 2026 CTR]] -> 300. Despesas Operac. Fixas e Variáveis
A88: 3.1. DESPESA COM VENDAS | B88: =Fluxo_de_Caixa_Janeiro[[#This Row],[Fluxo de Caixa 2026 CTR]] -> 3.1. DESPESA COM VENDAS | C88: =-SUBTOTAL(109,C89:C99) -> -41738.28 | D88: =-IFERROR(C88/$C$27,"0,00") -> 0.041355862 | E88: 0.030857534 | F88: =IF(Fluxo_de_Caixa_Janeiro34591171012151619[[#This Row],[% ACUMULADO DEZ/2026]]<=Fluxo_de_Caixa_Janeiro34591171012151619[[#This Row],[% Acum no Ano Comparação]],"Verd","Fals") -> Verd | H88: =-SUBTOTAL(109,H89:H99) -> -35734.22 | I88: =-SUBTOTAL(109,I89:I99) -> -2347.22 | J88: =-SUBTOTAL(109,J89:J99) -> -3656.84
B89: =Fluxo_de_Caixa_Janeiro[[#This Row],[Fluxo de Caixa 2026 CTR]] -> 3.1.01. Marketing e Propaganda | C89: =H89+I89+J89 -> 2715 | D89: =IFERROR(C89/$C$27,"0,00%") -> 0.0026901244 | E89: 0.0010458541 | F89: =IF(Fluxo_de_Caixa_Janeiro34591171012151619[[#This Row],[% ACUMULADO DEZ/2026]]<=Fluxo_de_Caixa_Janeiro34591171012151619[[#This Row],[% Acum no Ano Comparação]],"Verd","Fals") -> Fals | H89: 2715
B90: =Fluxo_de_Caixa_Janeiro[[#This Row],[Fluxo de Caixa 2026 CTR]] -> 3.1.02. Promoções e Eventos(Brindes/Café da Manhã p clientes/etc) | C90: =H90+I90+J90 -> 4614.57 | D90: =IFERROR(C90/$C$27,"0,00%") -> 0.00457229 | E90: 0.0011119768 | F90: =IF(Fluxo_de_Caixa_Janeiro34591171012151619[[#This Row],[% ACUMULADO DEZ/2026]]<=Fluxo_de_Caixa_Janeiro34591171012151619[[#This Row],[% Acum no Ano Comparação]],"Verd","Fals") -> Fals | H90: 4614.57
B91: =Fluxo_de_Caixa_Janeiro[[#This Row],[Fluxo de Caixa 2026 CTR]] -> 3.1.03. Sacolas e Embalagens | C91: =H91+I91+J91 -> 412.82 | D91: =IFERROR(C91/$C$27,"0,00%") -> 0.00040903763 | E91: 0.00064528103 | F91: =IF(Fluxo_de_Caixa_Janeiro34591171012151619[[#This Row],[% ACUMULADO DEZ/2026]]<=Fluxo_de_Caixa_Janeiro34591171012151619[[#This Row],[% Acum no Ano Comparação]],"Verd","Fals") -> Fals | H91: 412.82
B92: =Fluxo_de_Caixa_Janeiro[[#This Row],[Fluxo de Caixa 2026 CTR]] -> 3.1.04.DIARIAS E DESPESAS COM VENDEDOR (passagem ônibus, hotel. Etc) | C92: =H92+I92+J92 -> 0 | D92: =IFERROR(C92/$C$27,"0,00%") -> 0 | E92: 8.9915448e-05 | F92: =IF(Fluxo_de_Caixa_Janeiro34591171012151619[[#This Row],[% ACUMULADO DEZ/2026]]<=Fluxo_de_Caixa_Janeiro34591171012151619[[#This Row],[% Acum no Ano Comparação]],"Verd","Fals") -> Fals
B93: =Fluxo_de_Caixa_Janeiro[[#This Row],[Fluxo de Caixa 2026 CTR]] -> 3.1.05. Comissão Representente Comercial | C93: =H93+I93+J93 -> 22420.65 | D93: =IFERROR(C93/$C$27,"0,00%") -> 0.022215226 | E93: 0.012983049 | F93: =IF(Fluxo_de_Caixa_Janeiro34591171012151619[[#This Row],[% ACUMULADO DEZ/2026]]<=Fluxo_de_Caixa_Janeiro34591171012151619[[#This Row],[% Acum no Ano Comparação]],"Verd","Fals") -> Fals | H93: 22420.65
B94: =Fluxo_de_Caixa_Janeiro[[#This Row],[Fluxo de Caixa 2026 CTR]] -> 3.1.06. Frete com entrega de vendas | C94: =H94+I94+J94 -> 4269.79 | D94: =IFERROR(C94/$C$27,"0,00%") -> 0.004230669 | E94: 0.013626993 | F94: =IF(Fluxo_de_Caixa_Janeiro34591171012151619[[#This Row],[% ACUMULADO DEZ/2026]]<=Fluxo_de_Caixa_Janeiro34591171012151619[[#This Row],[% Acum no Ano Comparação]],"Verd","Fals") -> Fals | H94: 4269.79
B95: =Fluxo_de_Caixa_Janeiro[[#This Row],[Fluxo de Caixa 2026 CTR]] -> 3.1.07. TAXAS C/ CART CRÉD/DÉBIT | C95: =H95+I95+J95 -> 7272.91 | D95: =IFERROR(C95/$C$27,"0,00%") -> 0.0072062736 | E95: 0.0013544651 | F95: =IF(Fluxo_de_Caixa_Janeiro34591171012151619[[#This Row],[% ACUMULADO DEZ/2026]]<=Fluxo_de_Caixa_Janeiro34591171012151619[[#This Row],[% Acum no Ano Comparação]],"Verd","Fals") -> Fals | H95: 1301.39 | I95: 2315.45 | J95: 3656.07
B96: =Fluxo_de_Caixa_Janeiro[[#This Row],[Fluxo de Caixa 2026 CTR]] -> 3.1.08. Serviço Motoboy Entrega Vendas | C96: =H96+I96+J96 -> 0 | D96: =IFERROR(C96/$C$27,"0,00%") -> 0 | E96: 0.0013544651 | F96: =IF(Fluxo_de_Caixa_Janeiro34591171012151619[[#This Row],[% ACUMULADO DEZ/2026]]<=Fluxo_de_Caixa_Janeiro34591171012151619[[#This Row],[% Acum no Ano Comparação]],"Verd","Fals") -> Fals
B97: =Fluxo_de_Caixa_Janeiro[[#This Row],[Fluxo de Caixa 2026 CTR]] -> 3.1.09. PGTO DISTRATO REPRES COMERCIAL | C97: =H97+I97+J97 -> 0 | D97: =IFERROR(C97/$C$27,"0,00%") -> 0 | E97: 0.0013544651 | F97: =IF(Fluxo_de_Caixa_Janeiro34591171012151619[[#This Row],[% ACUMULADO DEZ/2026]]<=Fluxo_de_Caixa_Janeiro34591171012151619[[#This Row],[% Acum no Ano Comparação]],"Verd","Fals") -> Fals
B98: =Fluxo_de_Caixa_Janeiro[[#This Row],[Fluxo de Caixa 2026 CTR]] -> 3.1.10. TARIFA PIX RECEBIDO | C98: =H98+I98+J98 -> 32.54 | D98: =IFERROR(C98/$C$27,"0,00%") -> 3.224186e-05 | E98: 0.0013544651 | F98: =IF(Fluxo_de_Caixa_Janeiro34591171012151619[[#This Row],[% ACUMULADO DEZ/2026]]<=Fluxo_de_Caixa_Janeiro34591171012151619[[#This Row],[% Acum no Ano Comparação]],"Verd","Fals") -> Fals | I98: 31.77 | J98: 0.77
B99: =Fluxo_de_Caixa_Janeiro[[#This Row],[Fluxo de Caixa 2026 CTR]] -> 0 | D99: =IFERROR(C99/$C$27,"0,00%") -> 0 | E99: =#REF! -> #REF! | F99: =IF(Fluxo_de_Caixa_Janeiro34591171012151619[[#This Row],[% ACUMULADO DEZ/2026]]<=Fluxo_de_Caixa_Janeiro34591171012151619[[#This Row],[% Acum no Ano Comparação]],"Verd","Fals") -> #REF!
A100: 3.2. FUNCIONÁRIO | B100: =Fluxo_de_Caixa_Janeiro[[#This Row],[Fluxo de Caixa 2026 CTR]] -> 3.2. DESPESA COM FUNCIONÁRIO | C100: =-SUBTOTAL(109,C101:C130) -> -84685.6 | D100: =-IFERROR(C100/$C$27,"0,00") -> 0.083909687 | E100: 0.067282262 | F100: =IF(Fluxo_de_Caixa_Janeiro34591171012151619[[#This Row],[% ACUMULADO DEZ/2026]]<=Fluxo_de_Caixa_Janeiro34591171012151619[[#This Row],[% Acum no Ano Comparação]],"Verd","Fals") -> Verd | H100: =-SUBTOTAL(109,H101:H130) -> -83243.88 | I100: =-SUBTOTAL(109,I101:I130) -> -1441.72 | J100: =-SUBTOTAL(109,J101:J130) -> 0
...

Sheet MAIO
B1: Fluxo de Caixa 2026 CTR | C1: MAIO | D1: % ACUMULADO MAI/2026 | E1: % Acum no Ano Comparação | H1: Matriz | I1: Filia Porto | J1: Filia Palmas
A2: Disponíveis Nas Contas Movimento | B2: =Fluxo_de_Caixa_Janeiro[[#This Row],[Fluxo de Caixa 2026 CTR]] -> Disponíveis Nas Contas Movimento inicial | C2: =SUBTOTAL(109,C3:C26) -> 515135.91 | D2: =SUM(D3:D26) -> 1
B3: =Fluxo_de_Caixa_Janeiro[[#This Row],[Fluxo de Caixa 2026 CTR]] -> 1.0 - TESOURARIA MATRIZ PALMAS | C3: =ABRIL!C337 -> 421.79 | D3: =IF(C3=0,"0,00%",C3/$C$2) -> 0.00081879363
B4: =Fluxo_de_Caixa_Janeiro[[#This Row],[Fluxo de Caixa 2026 CTR]] -> 1.1 - BANCO DO BRASIL C.C.60409-7 MATRIZ | C4: =ABRIL!C338 -> 52517.95 | D4: =IF(C4=0,"0,00%",C4/$C$2) -> 0.1019497
B5: =Fluxo_de_Caixa_Janeiro[[#This Row],[Fluxo de Caixa 2026 CTR]] -> 0 | C5: =ABRIL!C339 -> 0 | D5: =IF(C5=0,"0,00%",C5/$C$2) -> 0,00%
B6: =Fluxo_de_Caixa_Janeiro[[#This Row],[Fluxo de Caixa 2026 CTR]] -> 1.2-BRADESCO 15232-3 MATRIZ | C6: =ABRIL!C340 -> 733.84 | D6: =IF(C6=0,"0,00%",C6/$C$2) -> 0.0014245561
B7: =Fluxo_de_Caixa_Janeiro[[#This Row],[Fluxo de Caixa 2026 CTR]] -> 0 | C7: =ABRIL!C341 -> 0 | D7: =IF(C7=0,"0,00%",C7/$C$2) -> 0,00%
B8: =Fluxo_de_Caixa_Janeiro[[#This Row],[Fluxo de Caixa 2026 CTR]] -> 1.3 - BANCO STONE MATRIZ C.C 40256726-7 | C8: =ABRIL!C342 -> 0 | D8: =IF(C8=0,"0,00%",C8/$C$2) -> 0,00%
B9: =Fluxo_de_Caixa_Janeiro[[#This Row],[Fluxo de Caixa 2026 CTR]] -> 1.4 - BANCO DA AMAZONIA 071730-7 MATRIZ | C9: =ABRIL!C343 -> 5306.88 | D9: =IF(C9=0,"0,00%",C9/$C$2) -> 0.010301903
B10: =Fluxo_de_Caixa_Janeiro[[#This Row],[Fluxo de Caixa 2026 CTR]] -> 1.4.1.INVESTIMENTO CDBORE RCP TXFL | C10: =ABRIL!C344 -> 74541.54 | D10: =IF(C10=0,"0,00%",C10/$C$2) -> 0.14470267
B11: =Fluxo_de_Caixa_Janeiro[[#This Row],[Fluxo de Caixa 2026 CTR]] -> 1.5 - ITAU C.C.98671-6 MATRIZ | C11: =ABRIL!C345 -> 367595.19 | D11: =IF(C11=0,"0,00%",C11/$C$2) -> 0.71358875
B12: =Fluxo_de_Caixa_Janeiro[[#This Row],[Fluxo de Caixa 2026 CTR]] -> 1.5.03. ITAU C.C 83290-2 GARANTIDA | C12: =ABRIL!C346 -> 0 | D12: =IF(C12=0,"0,00%",C12/$C$2) -> 0,00%
B13: =Fluxo_de_Caixa_Janeiro[[#This Row],[Fluxo de Caixa 2026 CTR]] -> 1.9 - CONTA PERDA/ROUBO/BONIFICAÇÃO E DOAÇÃO | C13: =ABRIL!C347 -> -20953.13 | D13: =IF(C13=0,"0,00%",C13/$C$2) -> -0.040674955
B14: =Fluxo_de_Caixa_Janeiro[[#This Row],[Fluxo de Caixa 2026 CTR]] -> 0 | C14: =ABRIL!C348 -> 0 | D14: =IF(C14=0,"0,00%",C14/$C$2) -> 0,00%
... B17: =Fluxo_de_Caixa_Janeiro[[#This Row],[Fluxo de Caixa 2026 CTR]] -> 0 | C17: =ABRIL!C351 -> 0 | D17: =IF(C17=0,"0,00%",C17/$C$2) -> 0,00%
B18: =Fluxo_de_Caixa_Janeiro[[#This Row],[Fluxo de Caixa 2026 CTR]] -> 2.4 - ITAU C.C.98669-0 FILIAL PALMAS | C18: =ABRIL!C352 -> 37.73 | D18: =IF(C18=0,"0,00%",C18/$C$2) -> 7.3242807e-05 | E18: =#REF! -> #REF!
B19: =Fluxo_de_Caixa_Janeiro[[#This Row],[Fluxo de Caixa 2026 CTR]] -> 2.9 - CONTA PERDA/ROUBO E BONIFICAÇÃO FILIAL | C19: =ABRIL!C353 -> -8367.5 | D19: =IF(C19=0,"0,00%",C19/$C$2) -> -0.016243286 | E19: =#REF! -> #REF!
B20: =Fluxo_de_Caixa_Janeiro[[#This Row],[Fluxo de Caixa 2026 CTR]] -> 4.0 - TESOURARIA FILIAL PORTO | C20: =ABRIL!C354 -> 372.39 | D20: =IF(C20=0,"0,00%",C20/$C$2) -> 0.0007228966 | E20: =#REF! -> #REF!
B21: =Fluxo_de_Caixa_Janeiro[[#This Row],[Fluxo de Caixa 2026 CTR]] -> 4.1 - BANCO DO BRASIL C.C.61105-0 FILIAL PORTO | C21: =ABRIL!C355 -> 308.03 | D21: =IF(C21=0,"0,00%",C21/$C$2) -> 0.0005979587 | E21: =#REF! -> #REF!
B22: =Fluxo_de_Caixa_Janeiro[[#This Row],[Fluxo de Caixa 2026 CTR]] -> 0 | C22: =ABRIL!C356 -> 0 | D22: =IF(C22=0,"0,00%",C22/$C$2) -> 0,00% | E22: =#REF! -> #REF!
B23: =Fluxo_de_Caixa_Janeiro[[#This Row],[Fluxo de Caixa 2026 CTR]] -> 4.4 - MERCADO PAGO PIX FILIAL PORTO | C23: =ABRIL!C357 -> 6468.92 | D23: =IF(C23=0,"0,00%",C23/$C$2) -> 0.012557696 | E23: =#REF! -> #REF!
B24: =Fluxo_de_Caixa_Janeiro[[#This Row],[Fluxo de Caixa 2026 CTR]] -> 4.9 - CONTA PERDA/ROUBO E BONIFICAÇÃO FILIAL | C24: =ABRIL!C358 -> -29071.86 | D24: =IF(C24=0,"0,00%",C24/$C$2) -> -0.05643532 | E24: =#REF! -> #REF!
B25: =Fluxo_de_Caixa_Janeiro[[#This Row],[Fluxo de Caixa 2026 CTR]] -> 91.CARTÃO ENDERED 5099+4596+6933+8072 - ESCRITORIO | C25: =ABRIL!C359 -> 3055.01 | D25: =IF(C25=0,"0,00%",C25/$C$2) -> 0.0059304932 | E25: =#REF! -> #REF!
B26: =Fluxo_de_Caixa_Janeiro[[#This Row],[Fluxo de Caixa 2026 CTR]] -> 0 | C26: =ABRIL!C360 -> 0 | D26: =IF(C26=0,"0,00%",C26/$C$2) -> 0,00% | E26: =#REF! -> #REF!
B27: =Fluxo_de_Caixa_Janeiro[[#This Row],[Fluxo de Caixa 2026 CTR]] -> Total Receitas Operacionais / Vendas | C27: =SUBTOTAL(109,C29:C51) -> 749225.37 | D27: =IFERROR(C27/C332,"") -> 0.99894929 | E27: 0.88526119 | H27: =H28+I28 -> 469275.65
A28: 1.1. Receita com Vendas | B28: =Fluxo_de_Caixa_Janeiro[[#This Row],[Fluxo de Caixa 2026 CTR]] -> 1.1. Receita com Vendas | C28: =SUBTOTAL(109,C29:C47) -> 749225.37 | D28: =SUM(D29:D47) -> 0.99894929 | E28: 0.88251933 | H28: =SUM(H29:H36) -> 1520.83 | I28: =SUM(I29:I36) -> 467754.82 | J28: =SUM(J29:J36) -> 279949.72
B29: =Fluxo_de_Caixa_Janeiro[[#This Row],[Fluxo de Caixa 2026 CTR]] -> 1.1.01. Receita em Dinheiro | C29: =H29+I29+J29 -> 7136.53 | D29: =IF(C29=0,"0,00%",C29/$C$332) -> 0.0095152031 | E29: 0.079252981 | F29: =IF(Fluxo_de_Caixa_Janeiro34591171012151619[[#This Row],[% ACUMULADO DEZ/2026]]>=Fluxo_de_Caixa_Janeiro34591171012151619[[#This Row],[% Acum no Ano Comparação]],"Verd","Fals") -> Verd | I29: 4855.02 | J29: 2281.51
B30: =Fluxo_de_Caixa_Janeiro[[#This Row],[Fluxo de Caixa 2026 CTR]] -> 1.1.01. Receita em Cartão (Crédito e Débito) | C30: =H30+I30+J30 -> 106265.12 | D30: =IF(C30=0,"0,00%",C30/$C$332) -> 0.14168429 | E30: 0.092740536 | F30: =IF(Fluxo_de_Caixa_Janeiro34591171012151619[[#This Row],[% ACUMULADO DEZ/2026]]>=Fluxo_de_Caixa_Janeiro34591171012151619[[#This Row],[% Acum no Ano Comparação]],"Verd","Fals") -> Verd | G30: =C361 -> -99.7 | I30: 83483.61 | J30: 22781.51
B31: =Fluxo_de_Caixa_Janeiro[[#This Row],[Fluxo de Caixa 2026 CTR]] -> 1.1.01. Receita de Cheque A Vista | C31: =H31+I31+J31 -> 0 | D31: =IF(C31=0,"0,00%",C31/$C$332) -> 0,00% | E31: 0.00028628486 | F31: =IF(Fluxo_de_Caixa_Janeiro34591171012151619[[#This Row],[% ACUMULADO DEZ/2026]]>=Fluxo_de_Caixa_Janeiro34591171012151619[[#This Row],[% Acum no Ano Comparação]],"Verd","Fals") -> Verd | J31: 0
B32: =Fluxo_de_Caixa_Janeiro[[#This Row],[Fluxo de Caixa 2026 CTR]] -> 1.1.01. Receita de Cheque Pré | C32: =H32+I32+J32 -> 0 | D32: =IF(C32=0,"0,00%",C32/$C$332) -> 0,00% | E32: 0.0063111634 | F32: =IF(Fluxo_de_Caixa_Janeiro34591171012151619[[#This Row],[% ACUMULADO DEZ/2026]]>=Fluxo_de_Caixa_Janeiro34591171012151619[[#This Row],[% Acum no Ano Comparação]],"Verd","Fals") -> Verd | J32: 0
B33: =Fluxo_de_Caixa_Janeiro[[#This Row],[Fluxo de Caixa 2026 CTR]] -> 1.1.01. Recebimento de Carteira (Notinha) | C33: =H33+I33+J33 -> 0 | D33: =IF(C33=0,"0,00%",C33/$C$332) -> 0,00% | E33: 0.0001318638 | F33: =IF(Fluxo_de_Caixa_Janeiro34591171012151619[[#This Row],[% ACUMULADO DEZ/2026]]>=Fluxo_de_Caixa_Janeiro34591171012151619[[#This Row],[% Acum no Ano Comparação]],"Verd","Fals") -> Verd | J33: 0
B34: =Fluxo_de_Caixa_Janeiro[[#This Row],[Fluxo de Caixa 2026 CTR]] -> 1.1.01. Recebimento de Boletos | C34: =H34+I34+J34 -> 98986.01 | D34: =IF(C34=0,"0,00%",C34/$C$332) -> 0.13197899 | E34: 0.66745712 | F34: =IF(Fluxo_de_Caixa_Janeiro34591171012151619[[#This Row],[% ACUMULADO DEZ/2026]]>=Fluxo_de_Caixa_Janeiro34591171012151619[[#This Row],[% Acum no Ano Comparação]],"Verd","Fals") -> Verd | H34: 1520.83 | I34: 32944.28 | J34: 64520.9
B35: =Fluxo_de_Caixa_Janeiro[[#This Row],[Fluxo de Caixa 2026 CTR]] -> 1.1.01. Recebimento em Depósito e Dep. PIX | C35: =H35+I35+J35 -> 536837.71 | D35: =IF(C35=0,"0,00%",C35/$C$332) -> 0.71577081 | E35: 0.036171198 | F35: =IF(Fluxo_de_Caixa_Janeiro34591171012151619[[#This Row],[% ACUMULADO DEZ/2026]]>=Fluxo_de_Caixa_Janeiro34591171012151619[[#This Row],[% Acum no Ano Comparação]],"Verd","Fals") -> Verd | I35: 346471.91 | J35: 190365.8
B36: =Fluxo_de_Caixa_Janeiro[[#This Row],[Fluxo de Caixa 2026 CTR]] -> 1.1.02. Recebimento Cheque Devolvido | C36: =H36+I36+J36 -> 0 | D36: =IF(C36=0,"0,00%",C36/$C$332) -> 0,00% | E36: 0.00016817802 | F36: =IF(Fluxo_de_Caixa_Janeiro34591171012151619[[#This Row],[% ACUMULADO DEZ/2026]]>=Fluxo_de_Caixa_Janeiro34591171012151619[[#This Row],[% Acum no Ano Comparação]],"Verd","Fals") -> Verd
B37: =Fluxo_de_Caixa_Janeiro[[#This Row],[Fluxo de Caixa 2026 CTR]] -> 0 | D37: =IF(C37=0,"0,00%",C37/$C$332) -> 0,00% | E37: =#REF! -> #REF! | F37: =IF(Fluxo_de_Caixa_Janeiro34591171012151619[[#This Row],[% ACUMULADO DEZ/2026]]>=Fluxo_de_Caixa_Janeiro34591171012151619[[#This Row],[% Acum no Ano Comparação]],"Verd","Fals") -> #REF!
B38: =Fluxo_de_Caixa_Janeiro[[#This Row],[Fluxo de Caixa 2026 CTR]] -> 0 | D38: =IF(C38=0,"0,00%",C38/$C$332) -> 0,00% | E38: =#REF! -> #REF! | F38: =IF(Fluxo_de_Caixa_Janeiro34591171012151619[[#This Row],[% ACUMULADO DEZ/2026]]>=Fluxo_de_Caixa_Janeiro34591171012151619[[#This Row],[% Acum no Ano Comparação]],"Verd","Fals") -> #REF!
B39: =Fluxo_de_Caixa_Janeiro[[#This Row],[Fluxo de Caixa 2026 CTR]] -> 0 | D39: =IF(C39=0,"0,00%",C39/$C$332) -> 0,00% | E39: =#REF! -> #REF! | F39: =IF(Fluxo_de_Caixa_Janeiro34591171012151619[[#This Row],[% ACUMULADO DEZ/2026]]>=Fluxo_de_Caixa_Janeiro34591171012151619[[#This Row],[% Acum no Ano Comparação]],"Verd","Fals") -> #REF!
B40: =Fluxo_de_Caixa_Janeiro[[#This Row],[Fluxo de Caixa 2026 CTR]] -> 0 | D40: =IF(C40=0,"0,00%",C40/$C$332) -> 0,00% | E40: =#REF! -> #REF! | F40: =IF(Fluxo_de_Caixa_Janeiro34591171012151619[[#This Row],[% ACUMULADO DEZ/2026]]>=Fluxo_de_Caixa_Janeiro34591171012151619[[#This Row],[% Acum no Ano Comparação]],"Verd","Fals") -> #REF!
B41: =Fluxo_de_Caixa_Janeiro[[#This Row],[Fluxo de Caixa 2026 CTR]] -> 0 | D41: =IF(C41=0,"0,00%",C41/$C$332) -> 0,00% | E41: =#REF! -> #REF! | F41: =IF(Fluxo_de_Caixa_Janeiro34591171012151619[[#This Row],[% ACUMULADO DEZ/2026]]>=Fluxo_de_Caixa_Janeiro34591171012151619[[#This Row],[% Acum no Ano Comparação]],"Verd","Fals") -> #REF!
B42: =Fluxo_de_Caixa_Janeiro[[#This Row],[Fluxo de Caixa 2026 CTR]] -> 0 | D42: =IF(C42=0,"0,00%",C42/$C$332) -> 0,00% | E42: =#REF! -> #REF! | F42: =IF(Fluxo_de_Caixa_Janeiro34591171012151619[[#This Row],[% ACUMULADO DEZ/2026]]>=Fluxo_de_Caixa_Janeiro34591171012151619[[#This Row],[% Acum no Ano Comparação]],"Verd","Fals") -> #REF!
B43: =Fluxo_de_Caixa_Janeiro[[#This Row],[Fluxo de Caixa 2026 CTR]] -> 0 | D43: =IF(C43=0,"0,00%",C43/$C$332) -> 0,00% | E43: =#REF! -> #REF! | F43: =IF(Fluxo_de_Caixa_Janeiro34591171012151619[[#This Row],[% ACUMULADO DEZ/2026]]>=Fluxo_de_Caixa_Janeiro34591171012151619[[#This Row],[% Acum no Ano Comparação]],"Verd","Fals") -> #REF!
B44: =Fluxo_de_Caixa_Janeiro[[#This Row],[Fluxo de Caixa 2026 CTR]] -> 0 | D44: =IF(C44=0,"0,00%",C44/$C$332) -> 0,00% | E44: =#REF! -> #REF! | F44: =IF(Fluxo_de_Caixa_Janeiro34591171012151619[[#This Row],[% ACUMULADO DEZ/2026]]>=Fluxo_de_Caixa_Janeiro34591171012151619[[#This Row],[% Acum no Ano Comparação]],"Verd","Fals") -> #REF!
B45: =Fluxo_de_Caixa_Janeiro[[#This Row],[Fluxo de Caixa 2026 CTR]] -> 0 | D45: =IF(C45=0,"0,00%",C45/$C$332) -> 0,00% | E45: =#REF! -> #REF! | F45: =IF(Fluxo_de_Caixa_Janeiro34591171012151619[[#This Row],[% ACUMULADO DEZ/2026]]>=Fluxo_de_Caixa_Janeiro34591171012151619[[#This Row],[% Acum no Ano Comparação]],"Verd","Fals") -> #REF!
B46: =Fluxo_de_Caixa_Janeiro[[#This Row],[Fluxo de Caixa 2026 CTR]] -> 0 | C46: 0 | D46: =IF(C46=0,"0,00%",C46/$C$332) -> 0,00% | E46: =#REF! -> #REF! | F46: =IF(Fluxo_de_Caixa_Janeiro34591171012151619[[#This Row],[% ACUMULADO DEZ/2026]]>=Fluxo_de_Caixa_Janeiro34591171012151619[[#This Row],[% Acum no Ano Comparação]],"Verd","Fals") -> #REF!
B47: =Fluxo_de_Caixa_Janeiro[[#This Row],[Fluxo de Caixa 2026 CTR]] -> 0 | D47: =IF(C47=0,"0,00%",C47/$C$332) -> 0,00% | E47: =#REF! -> #REF! | F47: =IF(Fluxo_de_Caixa_Janeiro34591171012151619[[#This Row],[% ACUMULADO DEZ/2026]]>=Fluxo_de_Caixa_Janeiro34591171012151619[[#This Row],[% Acum no Ano Comparação]],"Verd","Fals") -> #REF!
A48: 1.5. Receita de Garantias | B48: =Fluxo_de_Caixa_Janeiro[[#This Row],[Fluxo de Caixa 2026 CTR]] -> 1.5. Receita de Garantias | C48: =+SUBTOTAL(109,C49:C51) -> 0 | D48: =SUM(D49:D51) -> 0 | E48: 0.0027418655 | H48: =SUM(H49:H51) -> 0 | I48: =SUM(I49:I51) -> 0 | J48: =SUM(J49:J51) -> 0
